Workbook
Name Slicer_Delivery_Status: #N/A
Name Slicer_Order_Month1: #N/A
Name Slicer_Payment_Method: #N/A
Name Slicer_Region: #N/A

Sheet Dahboard

Sheet Sheet1

Sheet Pivot table
A1: Delivery Status | B1: (Multiple Items) | I1: Cancellation Rate by Region
A2: Payment Method | B2: (All) | I2: Row Labels | J2: Sum of Cancellation Rate by Region | N2: Cleaned Delivery Status | O2: (Multiple Items)
I3: Central | J3: 0.35714286 | N3: Total Revenue
A4: Region | B4: Sum of Total Amount | I4: East | J4: 0.16666667 | N4: Sum of Total Amount
A5: West | B5: 6921 | I5: North | J5: 0.4 | N5: 28297
A6: North | B6: 7030 | I6: South | J6: 0.2
A7: South | B7: 6779 | I7: West | J7: 0.34782609
A8: East | B8: 3353 | I8: Grand Total | J8: 0.3 | N8: % of Fast Deliveries
A9: Central | B9: 4214 | N9: Sum of Field1
A10: Grand Total | B10: 28297 | N10: 0.32352941
A12: Total Sales Amount by Region
N13: Top 3 Performing Regions
N14: Cleaned Delivery Status | O14: (Multiple Items)
A16: Count of Orders by Delivery Status | I16: Total Sales Amount by Product Category | N16: Row Labels | O16: Sum of Total Amount
A17: Payment Method | B17: (All) | I17: Payment Method | J17: (All) | N17: North | O17: 7030
A18: Category | B18: (All) | I18: Cleaned Delivery Status | J18: (Multiple Items) | N18: West | O18: 6921
N19: South | O19: 6779
A20: Row Labels | B20: Count of Order ID | I20: Row Labels | J20: Sum of Total Amount | N20: Central | O20: 4214
A21: Cancelled | B21: 30 | I21: Electronics | J21: 13035 | N21: East | O21: 3353
A22: Delivered | B22: 34 | I22: Fashion | J22: 2425 | N22: Grand Total | O22: 28297
A23: In Transit | B23: 36 | I23: Home | J23: 8450
A24: Grand Total | B24: 100 | I24: Toys | J24: 2989
I25: Books | J25: 1398 | N25: Cleaned Delivery Status | O25: (Multiple Items)
I26: Grand Total | J26: 28297 | N26: Highest-selling Product
N27: Row Labels | O27: Sum of Total Amount
N28: Smartphone | O28: 9644
A29: Average Delivery Time | N29: Grand Total | O29: 9644
A30: Payment Method | B30: (All)
A31: Category | B31: (All)
A33: Average of Delivery Days
A34: 3.7647059
A37: Sales Amount for Delivered Orders only
A38: Sum of Effective Sales
A39: 13656

Sheet AmazonSales
A1: Order ID | B1: Order Date | C1: Delivery Date | D1: Cancel Date | E1: Order Month | F1: Delivery Status | G1: Customer ID | H1: Product ID | I1: Region | J1: Sale Price/Unit | K1: Quantity | L1: Total Amount | M1: Payment Method | N1: Fulfillment Partner | O1: Coustmer Name | P1: Product Name | Q1: Product Category | R1: Delivery Performance | S1: Regional Target | T1: Column1 | U1: Cancellation Count | V1: Oder Count | W1: Fat Delivery | X1: Deliverd
A2: ORD0001 | B2: 45291 | D2: 45293 | E2: =TEXT(tbl_sale[[#This Row],[Order Date]],"MMM") -> Dec | F2: =IF(D2<>"","Cancelled",IF(C2<>"","Delivered","In Transit")) -> Cancelled | G2: CUST021 | H2: PROD012 | I2: North | J2: 44 | K2: 1 | L2: 44 | M2: Apple Pay | N2: DHL | O2: =_xlfn.XLOOKUP(tbl_sale[[#This Row],[Customer ID]],CustomerMaster!A:A,CustomerMaster!B:B,"NA",0) -> Zoe Mitchell | P2: =_xlfn.XLOOKUP(tbl_sale[[#This Row],[Product ID]],ProductMaster!$A$2:$A$23,ProductMaster!$B$2:$B$23,"NA",0) -> Lamp | Q2: =_xlfn.XLOOKUP(tbl_sale[[#This Row],[Product ID]],ProductMaster!$A$2:$A$23,ProductMaster!$C$2:$C$23,"NA",0) -> Home | R2: =IFERROR(IF(tbl_sale[[#This Row],[Delivery Date]]="","Pending",IF(tbl_sale[[#This Row],[Delivery Date]]-tbl_sale[[#This Row],[Order Date]]<= 2,"Fast","Slow")),"Error") -> Pending | S2: =_xlfn.XLOOKUP(tbl_sale[[#This Row],[Region]],RegionGoals!$A$2:$A$6,RegionGoals!$B$2:$B$6, ,0) -> 105000 | T2: =_xlfn.XLOOKUP(tbl_sale[[#This Row],[Customer ID]],CustomerMaster!$A:$A,CustomerMaster!$C:$C,"NA",0) -> Individual | U2: =IF(tbl_sale[[#This Row],[Delivery Status]]="Cancelled",1,0) -> 1 | V2: =IF(tbl_sale[[#This Row],[Order ID]]<>"",1,0) -> 1 | W2: =IF(AND(tbl_sale[[#This Row],[Delivery Status]]="Delivered",tbl_sale[[#This Row],[Delivery Performance]]="Fast"),1,0) -> 0 | X2: =IF(tbl_sale[[#This Row],[Delivery Status]]="Delivered",1,0) -> 0
A3: ORD0002 | B3: 44979 | C3: 44981 | E3: =TEXT(tbl_sale[[#This Row],[Order Date]],"MMM") -> Feb | F3: =IF(D3<>"","Cancelled",IF(C3<>"","Delivered","In Transit")) -> Delivered | G3: CUST029 | H3: PROD018 | I3: East | J3: 96 | K3: 4 | L3: 384 | M3: Credit Card | N3: DHL | O3: =_xlfn.XLOOKUP(tbl_sale[[#This Row],[Customer ID]],CustomerMaster!A:A,CustomerMaster!B:B,"NA",0) -> Ava White | P3: =_xlfn.XLOOKUP(tbl_sale[[#This Row],[Product ID]],ProductMaster!$A$2:$A$23,ProductMaster!$B$2:$B$23,"NA",0) -> Doll House | Q3: =_xlfn.XLOOKUP(tbl_sale[[#This Row],[Product ID]],ProductMaster!$A$2:$A$23,ProductMaster!$C$2:$C$23,"NA",0) -> Toys | R3: =IFERROR(IF(tbl_sale[[#This Row],[Delivery Date]]="","Pending",IF(tbl_sale[[#This Row],[Delivery Date]]-tbl_sale[[#This Row],[Order Date]]<= 2,"Fast","Slow")),"Error") -> Fast | S3: =_xlfn.XLOOKUP(tbl_sale[[#This Row],[Region]],RegionGoals!$A$2:$A$6,RegionGoals!$B$2:$B$6, ,0) -> 50500 | T3: =_xlfn.XLOOKUP(tbl_sale[[#This Row],[Customer ID]],CustomerMaster!$A:$A,CustomerMaster!$C:$C,"NA",0) -> Individual | U3: =IF(tbl_sale[[#This Row],[Delivery Status]]="Cancelled",1,0) -> 0 | V3: =IF(tbl_sale[[#This Row],[Order ID]]<>"",1,0) -> 1 | W3: =IF(AND(tbl_sale[[#This Row],[Delivery Status]]="Delivered",tbl_sale[[#This Row],[Delivery Performance]]="Fast"),1,0) -> 1 | X3: =IF(tbl_sale[[#This Row],[Delivery Status]]="Delivered",1,0) -> 1
A4: ORD0003 | B4: 45210 | E4: =TEXT(tbl_sale[[#This Row],[Order Date]],"MMM") -> Oct | F4: =IF(D4<>"","Cancelled",IF(C4<>"","Delivered","In Transit")) -> In Transit | G4: CUST021 | H4: PROD013 | I4: South | J4: 194 | K4: 4 | L4: 776 | M4: Credit Card | N4: USPS | O4: =_xlfn.XLOOKUP(tbl_sale[[#This Row],[Customer ID]],CustomerMaster!A:A,CustomerMaster!B:B,"NA",0) -> Zoe Mitchell | P4: =_xlfn.XLOOKUP(tbl_sale[[#This Row],[Product ID]],ProductMaster!$A$2:$A$23,ProductMaster!$B$2:$B$23,"NA",0) -> Vacuum Cleaner | Q4: =_xlfn.XLOOKUP(tbl_sale[[#This Row],[Product ID]],ProductMaster!$A$2:$A$23,ProductMaster!$C$2:$C$23,"NA",0) -> Home | R4: =IFERROR(IF(tbl_sale[[#This Row],[Delivery Date]]="","Pending",IF(tbl_sale[[#This Row],[Delivery Date]]-tbl_sale[[#This Row],[Order Date]]<= 2,"Fast","Slow")),"Error") -> Pending | S4: =_xlfn.XLOOKUP(tbl_sale[[#This Row],[Region]],RegionGoals!$A$2:$A$6,RegionGoals!$B$2:$B$6, ,0) -> 91500 | T4: =_xlfn.XLOOKUP(tbl_sale[[#This Row],[Customer ID]],CustomerMaster!$A:$A,CustomerMaster!$C:$C,"NA",0) -> Individual | U4: =IF(tbl_sale[[#This Row],[Delivery Status]]="Cancelled",1,0) -> 0 | V4: =IF(tbl_sale[[#This Row],[Order ID]]<>"",1,0) -> 1 | W4: =IF(AND(tbl_sale[[#This Row],[Delivery Status]]="Delivered",tbl_sale[[#This Row],[Delivery Performance]]="Fast"),1,0) -> 0 | X4: =IF(tbl_sale[[#This Row],[Delivery Status]]="Delivered",1,0) -> 0
A5: ORD0004 | B5: 45051 | D5: 45057 | E5: =TEXT(tbl_sale[[#This Row],[Order Date]],"MMM") -> May | F5: =IF(D5<>"","Cancelled",IF(C5<>"","Delivered","In Transit")) -> Cancelled | G5: CUST044 | H5: PROD013 | I5: North | J5: 196 | K5: 3 | L5: 588 | M5: PayPal | N5: UPS | O5: =_xlfn.XLOOKUP(tbl_sale[[#This Row],[Customer ID]],CustomerMaster!A:A,CustomerMaster!B:B,"NA",0) -> Grace Ward | P5: =_xlfn.XLOOKUP(tbl_sale[[#This Row],[Product ID]],ProductMaster!$A$2:$A$23,ProductMaster!$B$2:$B$23,"NA",0) -> Vacuum Cleaner | Q5: =_xlfn.XLOOKUP(tbl_sale[[#This Row],[Product ID]],ProductMaster!$A$2:$A$23,ProductMaster!$C$2:$C$23,"NA",0) -> Home | R5: =IFERROR(IF(tbl_sale[[#This Row],[Delivery Date]]="","Pending",IF(tbl_sale[[#This Row],[Delivery Date]]-tbl_sale[[#This Row],[Order Date]]<= 2,"Fast","Slow")),"Error") -> Pending | S5: =_xlfn.XLOOKUP(tbl_sale[[#This Row],[Region]],RegionGoals!$A$2:$A$6,RegionGoals!$B$2:$B$6, ,0) -> 105000 | T5: =_xlfn.XLOOKUP(tbl_sale[[#This Row],[Customer ID]],CustomerMaster!$A:$A,CustomerMaster!$C:$C,"NA",0) -> Business | U5: =IF(tbl_sale[[#This Row],[Delivery Status]]="Cancelled",1,0) -> 1 | V5: =IF(tbl_sale[[#This Row],[Order ID]]<>"",1,0) -> 1 | W5: =IF(AND(tbl_sale[[#This Row],[Delivery Status]]="Delivered",tbl_sale[[#This Row],[Delivery Performance]]="Fast"),1,0) -> 0 | X5: =IF(tbl_sale[[#This Row],[Delivery Status]]="Delivered",1,0) -> 0
A6: ORD0005 | B6: 44959 | C6: 44962 | E6: =TEXT(tbl_sale[[#This Row],[Order Date]],"MMM") -> Feb | F6: =IF(D6<>"","Cancelled",IF(C6<>"","Delivered","In Transit")) -> Delivered | G6: CUST027 | H6: PROD010 | I6: North | J6: 59 | K6: 1 | L6: 59 | M6: PayPal | N6: Amazon Logistics | O6: =_xlfn.XLOOKUP(tbl_sale[[#This Row],[Customer ID]],CustomerMaster!A:A,CustomerMaster!B:B,"NA",0) -> Hazel Brooks | P6: =_xlfn.XLOOKUP(tbl_sale[[#This Row],[Product ID]],ProductMaster!$A$2:$A$23,ProductMaster!$B$2:$B$23,"NA",0) -> Jeans | Q6: =_xlfn.XLOOKUP(tbl_sale[[#This Row],[Product ID]],ProductMaster!$A$2:$A$23,ProductMaster!$C$2:$C$23,"NA",0) -> Fashion | R6: =IFERROR(IF(tbl_sale[[#This Row],[Delivery Date]]="","Pending",IF(tbl_sale[[#This Row],[Delivery Date]]-tbl_sale[[#This Row],[Order Date]]<= 2,"Fast","Slow")),"Error") -> Slow | S6: =_xlfn.XLOOKUP(tbl_sale[[#This Row],[Region]],RegionGoals!$A$2:$A$6,RegionGoals!$B$2:$B$6, ,0) -> 105000 | T6: =_xlfn.XLOOKUP(tbl_sale[[#This Row],[Customer ID]],CustomerMaster!$A:$A,CustomerMaster!$C:$C,"NA",0) -> Individual | U6: =IF(tbl_sale[[#This Row],[Delivery Status]]="Cancelled",1,0) -> 0 | V6: =IF(tbl_sale[[#This Row],[Order ID]]<>"",1,0) -> 1 | W6: =IF(AND(tbl_sale[[#This Row],[Delivery Status]]="Delivered",tbl_sale[[#This Row],[Delivery Performance]]="Fast"),1,0) -> 0 | X6: =IF(tbl_sale[[#This Row],[Delivery Status]]="Delivered",1,0) -> 1
A7: ORD0006 | B7: 45231 | D7: 45232 | E7: =TEXT(tbl_sale[[#This Row],[Order Date]],"MMM") -> Nov | F7: =IF(D7<>"","Cancelled",IF(C7<>"","Delivered","In Transit")) -> Cancelled | G7: CUST009 | H7: PROD010 | I7: North | J7: 58 | K7: 4 | L7: 232 | M7: Amazon Pay | N7: DHL | O7: =_xlfn.XLOOKUP(tbl_sale[[#This Row],[Customer ID]],CustomerMaster!A:A,CustomerMaster!B:B,"NA",0) -> Jackson Allen | P7: =_xlfn.XLOOKUP(tbl_sale[[#This Row],[Product ID]],ProductMaster!$A$2:$A$23,ProductMaster!$B$2:$B$23,"NA",0) -> Jeans | Q7: =_xlfn.XLOOKUP(tbl_sale[[#This Row],[Product ID]],ProductMaster!$A$2:$A$23,ProductMaster!$C$2:$C$23,"NA",0) -> Fashion | R7: =IFERROR(IF(tbl_sale[[#This Row],[Delivery Date]]="","Pending",IF(tbl_sale[[#This Row],[Delivery Date]]-tbl_sale[[#This Row],[Order Date]]<= 2,"Fast","Slow")),"Error") -> Pending | S7: =_xlfn.XLOOKUP(tbl_sale[[#This Row],[Region]],RegionGoals!$A$2:$A$6,RegionGoals!$B$2:$B$6, ,0) -> 105000 | T7: =_xlfn.XLOOKUP(tbl_sale[[#This Row],[Customer ID]],CustomerMaster!$A:$A,CustomerMaster!$C:$C,"NA",0) -> Business | U7: =IF(tbl_sale[[#This Row],[Delivery Status]]="Cancelled",1,0) -> 1 | V7: =IF(tbl_sale[[#This Row],[Order ID]]<>"",1,0) -> 1 | W7: =IF(AND(tbl_sale[[#This Row],[Delivery Status]]="Delivered",tbl_sale[[#This Row],[Delivery Performance]]="Fast"),1,0) -> 0 | X7: =IF(tbl_sale[[#This Row],[Delivery Status]]="Delivered",1,0) -> 0
A8: ORD0007 | B8: 45152 | D8: 45156 | E8: =TEXT(tbl_sale[[#This Row],[Order Date]],"MMM") -> Aug | F8: =IF(D8<>"","Cancelled",IF(C8<>"","Delivered","In Transit")) -> Cancelled | G8: CUST042 | H8: PROD020 | I8: Central | J8: 105 | K8: 3 | L8: 315 | M8: Debit Card | N8: DHL | O8: =_xlfn.XLOOKUP(tbl_sale[[#This Row],[Customer ID]],CustomerMaster!A:A,CustomerMaster!B:B,"NA",0) -> Noah Wilson | P8: =_xlfn.XLOOKUP(tbl_sale[[#This Row],[Product ID]],ProductMaster!$A$2:$A$23,ProductMaster!$B$2:$B$23,"NA",0) -> Bluetooth Speaker | Q8: =_xlfn.XLOOKUP(tbl_sale[[#This Row],[Product ID]],ProductMaster!$A$2:$A$23,ProductMaster!$C$2:$C$23,"NA",0) -> Electronics | R8: =IFERROR(IF(tbl_sale[[#This Row],[Delivery Date]]="","Pending",IF(tbl_sale[[#This Row],[Delivery Date]]-tbl_sale[[#This Row],[Order Date]]<= 2,"Fast","Slow")),"Error") -> Pending | S8: =_xlfn.XLOOKUP(tbl_sale[[#This Row],[Region]],RegionGoals!$A$2:$A$6,RegionGoals!$B$2:$B$6, ,0) -> 97500 | T8: =_xlfn.XLOOKUP(tbl_sale[[#This Row],[Customer ID]],CustomerMaster!$A:$A,CustomerMaster!$C:$C,"NA",0) -> Prime | U8: =IF(tbl_sale[[#This Row],[Delivery Status]]="Cancelled",1,0) -> 1 | V8: =IF(tbl_sale[[#This Row],[Order ID]]<>"",1,0) -> 1 | W8: =IF(AND(tbl_sale[[#This Row],[Delivery Status]]="Delivered",tbl_sale[[#This Row],[Delivery Performance]]="Fast"),1,0) -> 0 | X8: =IF(tbl_sale[[#This Row],[Delivery Status]]="Delivered",1,0) -> 0
A9: ORD0008 | B9: 45017 | D9: 45022 | E9: =TEXT(tbl_sale[[#This Row],[Order Date]],"MMM") -> Apr | F9: =IF(D9<>"","Cancelled",IF(C9<>"","Delivered","In Transit")) -> Cancelled | G9: CUST019 | H9: PROD021 | I9: West | J9: 37 | K9: 5 | L9: 185 | M9: PayPal | N9: DHL | O9: =_xlfn.XLOOKUP(tbl_sale[[#This Row],[Customer ID]],CustomerMaster!A:A,CustomerMaster!B:B,"NA",0) -> Ava Robinson | P9: =_xlfn.XLOOKUP(tbl_sale[[#This Row],[Product ID]],ProductMaster!$A$2:$A$23,ProductMaster!$B$2:$B$23,"NA",0) -> Wall Clock | Q9: =_xlfn.XLOOKUP(tbl_sale[[#This Row],[Product ID]],ProductMaster!$A$2:$A$23,ProductMaster!$C$2:$C$23,"NA",0) -> Home | R9: =IFERROR(IF(tbl_sale[[#This Row],[Delivery Date]]="","Pending",IF(tbl_sale[[#This Row],[Delivery Date]]-tbl_sale[[#This Row],[Order Date]]<= 2,"Fast","Slow")),"Error") -> Pending | S9: =_xlfn.XLOOKUP(tbl_sale[[#This Row],[Region]],RegionGoals!$A$2:$A$6,RegionGoals!$B$2:$B$6, ,0) -> 90750 | T9: =_xlfn.XLOOKUP(tbl_sale[[#This Row],[Customer ID]],CustomerMaster!$A:$A,CustomerMaster!$C:$C,"NA",0) -> Prime | U9: =IF(tbl_sale[[#This Row],[Delivery Status]]="Cancelled",1,0) -> 1 | V9: =IF(tbl_sale[[#This Row],[Order ID]]<>"",1,0) -> 1 | W9: =IF(AND(tbl_sale[[#This Row],[Delivery Status]]="Delivered",tbl_sale[[#This Row],[Delivery Performance]]="Fast"),1,0) -> 0 | X9: =IF(tbl_sale[[#This Row],[Delivery Status]]="Delivered",1,0) -> 0
A10: ORD0009 | B10: 45128 | E10: =TEXT(tbl_sale[[#This Row],[Order Date]],"MMM") -> Jul | F10: =IF(D10<>"","Cancelled",IF(C10<>"","Delivered","In Transit")) -> In Transit | G10: CUST013 | H10: PROD019 | I10: Central | J10: 44 | K10: 2 | L10: 88 | M10: Credit Card | N10: Amazon Logistics | O10: =_xlfn.XLOOKUP(tbl_sale[[#This Row],[Customer ID]],CustomerMaster!A:A,CustomerMaster!B:B,"NA",0) -> Olivia Martinez | P10: =_xlfn.XLOOKUP(tbl_sale[[#This Row],[Product ID]],ProductMaster!$A$2:$A$23,ProductMaster!$B$2:$B$23,"NA",0) -> Formal Shirt | Q10: =_xlfn.XLOOKUP(tbl_sale[[#This Row],[Product ID]],ProductMaster!$A$2:$A$23,ProductMaster!$C$2:$C$23,"NA",0) -> Fashion | R10: =IFERROR(IF(tbl_sale[[#This Row],[Delivery Date]]="","Pending",IF(tbl_sale[[#This Row],[Delivery Date]]-tbl_sale[[#This Row],[Order Date]]<= 2,"Fast","Slow")),"Error") -> Pending | S10: =_xlfn.XLOOKUP(tbl_sale[[#This Row],[Region]],RegionGoals!$A$2:$A$6,RegionGoals!$B$2:$B$6, ,0) -> 97500 | T10: =_xlfn.XLOOKUP(tbl_sale[[#This Row],[Customer ID]],CustomerMaster!$A:$A,CustomerMaster!$C:$C,"NA",0) -> Prime | U10: =IF(tbl_sale[[#This Row],[Delivery Status]]="Cancelled",1,0) -> 0 | V10: =IF(tbl_sale[[#This Row],[Order ID]]<>"",1,0) -> 1 | W10: =IF(AND(tbl_sale[[#This Row],[Delivery Status]]="Delivered",tbl_sale[[#This Row],[Delivery Performance]]="Fast"),1,0) -> 0 | X10: =IF(tbl_sale[[#This Row],[Delivery Status]]="Delivered",1,0) -> 0
A11: ORD0010 | B11: 45289 | E11: =TEXT(tbl_sale[[#This Row],[Order Date]],"MMM") -> Dec | F11: =IF(D11<>"","Cancelled",IF(C11<>"","Delivered","In Transit")) -> In Transit | G11: CUST019 | H11: PROD003 | I11: South | J11: 141 | K11: 4 | L11: 564 | M11: Debit Card | N11: DHL | O11: =_xlfn.XLOOKUP(tbl_sale[[#This Row],[Customer ID]],CustomerMaster!A:A,CustomerMaster!B:B,"NA",0) -> Ava Robinson | P11: =_xlfn.XLOOKUP(tbl_sale[[#This Row],[Product ID]],ProductMaster!$A$2:$A$23,ProductMaster!$B$2:$B$23,"NA",0) -> Cookware Set | Q11: =_xlfn.XLOOKUP(tbl_sale[[#This Row],[Product ID]],ProductMaster!$A$2:$A$23,ProductMaster!$C$2:$C$23,"NA",0) -> Home | R11: =IFERROR(IF(tbl_sale[[#This Row],[Delivery Date]]="","Pending",IF(tbl_sale[[#This Row],[Delivery Date]]-tbl_sale[[#This Row],[Order Date]]<= 2,"Fast","Slow")),"Error") -> Pending | S11: =_xlfn.XLOOKUP(tbl_sale[[#This Row],[Region]],RegionGoals!$A$2:$A$6,RegionGoals!$B$2:$B$6, ,0) -> 91500 | T11: =_xlfn.XLOOKUP(tbl_sale[[#This Row],[Customer ID]],CustomerMaster!$A:$A,CustomerMaster!$C:$C,"NA",0) -> Prime | U11: =IF(tbl_sale[[#This Row],[Delivery Status]]="Cancelled",1,0) -> 0 | V11: =IF(tbl_sale[[#This Row],[Order ID]]<>"",1,0) -> 1 | W11: =IF(AND(tbl_sale[[#This Row],[Delivery Status]]="Delivered",tbl_sale[[#This Row],[Delivery Performance]]="Fast"),1,0) -> 0 | X11: =IF(tbl_sale[[#This Row],[Delivery Status]]="Delivered",1,0) -> 0
A12: ORD0011 | B12: 45050 | D12: 45054 | E12: =TEXT(tbl_sale[[#This Row],[Order Date]],"MMM") -> May | F12: =IF(D12<>"","Cancelled",IF(C12<>"","Delivered","In Transit")) -> Cancelled | G12: CUST046 | H12: PROD014 | I12: South | J12: 249 | K12: 1 | L12: 249 | M12: Amazon Pay | N12: USPS | O12: =_xlfn.XLOOKUP(tbl_sale[[#This Row],[Customer ID]],CustomerMaster!A:A,CustomerMaster!B:B,"NA",0) -> Emily Johnson | P12: =_xlfn.XLOOKUP(tbl_sale[[#This Row],[Product ID]],ProductMaster!$A$2:$A$23,ProductMaster!$B$2:$B$23,"NA",0) -> Smartwatch | Q12: =_xlfn.XLOOKUP(tbl_sale[[#This Row],[Product ID]],ProductMaster!$A$2:$A$23,ProductMaster!$C$2:$C$23,"NA",0) -> Electronics | R12: =IFERROR(IF(tbl_sale[[#This Row],[Delivery Date]]="","Pending",IF(tbl_sale[[#This Row],[Delivery Date]]-tbl_sale[[#This Row],[Order Date]]<= 2,"Fast","Slow")),"Error") -> Pending | S12: =_xlfn.XLOOKUP(tbl_sale[[#This Row],[Region]],RegionGoals!$A$2:$A$6,RegionGoals!$B$2:$B$6, ,0) -> 91500 | T12: =_xlfn.XLOOKUP(tbl_sale[[#This Row],[Customer ID]],CustomerMaster!$A:$A,CustomerMaster!$C:$C,"NA",0) -> Prime | U12: =IF(tbl_sale[[#This Row],[Delivery Status]]="Cancelled",1,0) -> 1 | V12: =IF(tbl_sale[[#This Row],[Order ID]]<>"",1,0) -> 1 | W12: =IF(AND(tbl_sale[[#This Row],[Delivery Status]]="Delivered",tbl_sale[[#This Row],[Delivery Performance]]="Fast"),1,0) -> 0 | X12: =IF(tbl_sale[[#This Row],[Delivery Status]]="Delivered",1,0) -> 0
A13: ORD0012 | B13: 45132 | E13: =TEXT(tbl_sale[[#This Row],[Order Date]],"MMM") -> Jul | F13: =IF(D13<>"","Cancelled",IF(C13<>"","Delivered","In Transit")) -> In Transit | G13: CUST045 | H13: PROD014 | I13: Central | J13: 247 | K13: 3 | L13: 741 | M13: Amazon Pay | N13: FedEx | O13: =_xlfn.XLOOKUP(tbl_sale[[#This Row],[Customer ID]],CustomerMaster!A:A,CustomerMaster!B:B,"NA",0) -> Emily Johnson | P13: =_xlfn.XLOOKUP(tbl_sale[[#This Row],[Product ID]],ProductMaster!$A$2:$A$23,ProductMaster!$B$2:$B$23,"NA",0) -> Smartwatch | Q13: =_xlfn.XLOOKUP(tbl_sale[[#This Row],[Product ID]],ProductMaster!$A$2:$A$23,ProductMaster!$C$2:$C$23,"NA",0) -> Electronics | R13: =IFERROR(IF(tbl_sale[[#This Row],[Delivery Date]]="","Pending",IF(tbl_sale[[#This Row],[Delivery Date]]-tbl_sale[[#This Row],[Order Date]]<= 2,"Fast","Slow")),"Error") -> Pending | S13: =_xlfn.XLOOKUP(tbl_sale[[#This Row],[Region]],RegionGoals!$A$2:$A$6,RegionGoals!$B$2:$B$6, ,0) -> 97500 | T13: =_xlfn.XLOOKUP(tbl_sale[[#This Row],[Customer ID]],CustomerMaster!$A:$A,CustomerMaster!$C:$C,"NA",0) -> Individual | U13: =IF(tbl_sale[[#This Row],[Delivery Status]]="Cancelled",1,0) -> 0 | V13: =IF(tbl_sale[[#This Row],[Order ID]]<>"",1,0) -> 1 | W13: =IF(AND(tbl_sale[[#This Row],[Delivery Status]]="Delivered",tbl_sale[[#This Row],[Delivery Performance]]="Fast"),1,0) -> 0 | X13: =IF(tbl_sale[[#This Row],[Delivery Status]]="Delivered",1,0) -> 0
A14: ORD0013 | B14: 44982 | D14: 44985 | E14: =TEXT(tbl_sale[[#This Row],[Order Date]],"MMM") -> Feb | F14: =IF(D14<>"","Cancelled",IF(C14<>"","Delivered","In Transit")) -> Cancelled | G14: CUST023 | H14: PROD006 | I14: Central | J14: 96 | K14: 1 | L14: 96 | M14: Apple Pay | N14: Amazon Logistics | O14: =_xlfn.XLOOKUP(tbl_sale[[#This Row],[Customer ID]],CustomerMaster!A:A,CustomerMaster!B:B,"NA",0) -> Charlotte Reed | P14: =_xlfn.XLOOKUP(tbl_sale[[#This Row],[Product ID]],ProductMaster!$A$2:$A$23,ProductMaster!$B$2:$B$23,"NA",0) -> Shoes | Q14: =_xlfn.XLOOKUP(tbl_sale[[#This Row],[Product ID]],ProductMaster!$A$2:$A$23,ProductMaster!$C$2:$C$23,"NA",0) -> Fashion | R14: =IFERROR(IF(tbl_sale[[#This Row],[Delivery Date]]="","Pending",IF(tbl_sale[[#This Row],[Delivery Date]]-tbl_sale[[#This Row],[Order Date]]<= 2,"Fast","Slow")),"Error") -> Pending | S14: =_xlfn.XLOOKUP(tbl_sale[[#This Row],[Region]],RegionGoals!$A$2:$A$6,RegionGoals!$B$2:$B$6, ,0) -> 97500 | T14: =_xlfn.XLOOKUP(tbl_sale[[#This Row],[Customer ID]],CustomerMaster!$A:$A,CustomerMaster!$C:$C,"NA",0) -> Individual | U14: =IF(tbl_sale[[#This Row],[Delivery Status]]="Cancelled",1,0) -> 1 | V14: =IF(tbl_sale[[#This Row],[Order ID]]<>"",1,0) -> 1 | W14: =IF(AND(tbl_sale[[#This Row],[Delivery Status]]="Delivered",tbl_sale[[#This Row],[Delivery Performance]]="Fast"),1,0) -> 0 | X14: =IF(tbl_sale[[#This Row],[Delivery Status]]="Delivered",1,0) -> 0
A15: ORD0014 | B15: 44981 | D15: 44982 | E15: =TEXT(tbl_sale[[#This Row],[Order Date]],"MMM") -> Feb | F15: =IF(D15<>"","Cancelled",IF(C15<>"","Delivered","In Transit")) -> Cancelled | G15: CUST033 | H15: PROD017 | I15: West | J15: 74 | K15: 5 | L15: 370 | M15: Apple Pay | N15: Amazon Logistics | O15: =_xlfn.XLOOKUP(tbl_sale[[#This Row],[Customer ID]],CustomerMaster!A:A,CustomerMaster!B:B,"NA",0) -> Hazel Rivera | P15: =_xlfn.XLOOKUP(tbl_sale[[#This Row],[Product ID]],ProductMaster!$A$2:$A$23,ProductMaster!$B$2:$B$23,"NA",0) -> Gaming Mouse | Q15: =_xlfn.XLOOKUP(tbl_sale[[#This Row],[Product ID]],ProductMaster!$A$2:$A$23,ProductMaster!$C$2:$C$23,"NA",0) -> Electronics | R15: =IFERROR(IF(tbl_sale[[#This Row],[Delivery Date]]="","Pending",IF(tbl_sale[[#This Row],[Delivery Date]]-tbl_sale[[#This Row],[Order Date]]<= 2,"Fast","Slow")),"Error") -> Pending | S15: =_xlfn.XLOOKUP(tbl_sale[[#This Row],[Region]],RegionGoals!$A$2:$A$6,RegionGoals!$B$2:$B$6, ,0) -> 90750 | T15: =_xlfn.XLOOKUP(tbl_sale[[#This Row],[Customer ID]],CustomerMaster!$A:$A,CustomerMaster!$C:$C,"NA",0) -> Business | U15: =IF(tbl_sale[[#This Row],[Delivery Status]]="Cancelled",1,0) -> 1 | V15: =IF(tbl_sale[[#This Row],[Order ID]]<>"",1,0) -> 1 | W15: =IF(AND(tbl_sale[[#This Row],[Delivery Status]]="Delivered",tbl_sale[[#This Row],[Delivery Performance]]="Fast"),1,0) -> 0 | X15: =IF(tbl_sale[[#This Row],[Delivery Status]]="Delivered",1,0) -> 0
A16: ORD0015 | B16: 45164 | D16: 45171 | E16: =TEXT(tbl_sale[[#This Row],[Order Date]],"MMM") -> Aug | F16: =IF(D16<>"","Cancelled",IF(C16<>"","Delivered","In Transit")) -> Cancelled | G16: CUST033 | H16: PROD005 | I16: South | J16: 27 | K16: 1 | L16: 27 | M16: Credit Card | N16: Amazon Logistics | O16: =_xlfn.XLOOKUP(tbl_sale[[#This Row],[Customer ID]],CustomerMaster!A:A,CustomerMaster!B:B,"NA",0) -> Hazel Rivera | P16: =_xlfn.XLOOKUP(tbl_sale[[#This Row],[Product ID]],ProductMaster!$A$2:$A$23,ProductMaster!$B$2:$B$23,"NA",0) -> T-Shirt | Q16: =_xlfn.XLOOKUP(tbl_sale[[#This Row],[Product ID]],ProductMaster!$A$2:$A$23,ProductMaster!$C$2:$C$23,"NA",0) -> Fashion | R16: =IFERROR(IF(tbl_sale[[#This Row],[Delivery Date]]="","Pending",IF(tbl_sale[[#This Row],[Delivery Date]]-tbl_sale[[#This Row],[Order Date]]<= 2,"Fast","Slow")),"Error") -> Pending | S16: =_xlfn.XLOOKUP(tbl_sale[[#This Row],[Region]],RegionGoals!$A$2:$A$6,RegionGoals!$B$2:$B$6, ,0) -> 91500 | T16: =_xlfn.XLOOKUP(tbl_sale[[#This Row],[Customer ID]],CustomerMaster!$A:$A,CustomerMaster!$C:$C,"NA",0) -> Business | U16: =IF(tbl_sale[[#This Row],[Delivery Status]]="Cancelled",1,0) -> 1 | V16: =IF(tbl_sale[[#This Row],[Order ID]]<>"",1,0) -> 1 | W16: =IF(AND(tbl_sale[[#This Row],[Delivery Status]]="Delivered",tbl_sale[[#This Row],[Delivery Performance]]="Fast"),1,0) -> 0 | X16: =IF(tbl_sale[[#This Row],[Delivery Status]]="Delivered",1,0) -> 0
A17: ORD0016 | B17: 44970 | E17: =TEXT(tbl_sale[[#This Row],[Order Date]],"MMM") -> Feb | F17: =IF(D17<>"","Cancelled",IF(C17<>"","Delivered","In Transit")) -> In Transit | G17: CUST047 | H17: PROD005 | I17: South | J17: 27 | K17: 3 | L17: 81 | M17: Debit Card | N17: Amazon Logistics | O17: =_xlfn.XLOOKUP(tbl_sale[[#This Row],[Customer ID]],CustomerMaster!A:A,CustomerMaster!B:B,"NA",0) -> Scarlett Murphy | P17: =_xlfn.XLOOKUP(tbl_sale[[#This Row],[Product ID]],ProductMaster!$A$2:$A$23,ProductMaster!$B$2:$B$23,"NA",0) -> T-Shirt | Q17: =_xlfn.XLOOKUP(tbl_sale[[#This Row],[Product ID]],ProductMaster!$A$2:$A$23,ProductMaster!$C$2:$C$23,"NA",0) -> Fashion | R17: =IFERROR(IF(tbl_sale[[#This Row],[Delivery Date]]="","Pending",IF(tbl_sale[[#This Row],[Delivery Date]]-tbl_sale[[#This Row],[Order Date]]<= 2,"Fast","Slow")),"Error") -> Pending | S17: =_xlfn.XLOOKUP(tbl_sale[[#This Row],[Region]],RegionGoals!$A$2:$A$6,RegionGoals!$B$2:$B$6, ,0) -> 91500 | T17: =_xlfn.XLOOKUP(tbl_sale[[#This Row],[Customer ID]],CustomerMaster!$A:$A,CustomerMaster!$C:$C,"NA",0) -> Individual | U17: =IF(tbl_sale[[#This Row],[Delivery Status]]="Cancelled",1,0) -> 0 | V17: =IF(tbl_sale[[#This Row],[Order ID]]<>"",1,0) -> 1 | W17: =IF(AND(tbl_sale[[#This Row],[Delivery Status]]="Delivered",tbl_sale[[#This Row],[Delivery Performance]]="Fast"),1,0) -> 0 | X17: =IF(tbl_sale[[#This Row],[Delivery Status]]="Delivered",1,0) -> 0
A18: ORD0017 | B18: 45105 | C18: 45108 | E18: =TEXT(tbl_sale[[#This Row],[Order Date]],"MMM") -> Jun | F18: =IF(D18<>"","Cancelled",IF(C18<>"","Delivered","In Transit")) -> Delivered | G18: CUST045 | H18: PROD015 | I18: East | J18: 21 | K18: 3 | L18: 63 | M18: Credit Card | N18: DHL | O18: =_xlfn.XLOOKUP(tbl_sale[[#This Row],[Customer ID]],CustomerMaster!A:A,CustomerMaster!B:B,"NA",0) -> Emily Johnson | P18: =_xlfn.XLOOKUP(tbl_sale[[#This Row],[Product ID]],ProductMaster!$A$2:$A$23,ProductMaster!$B$2:$B$23,"NA",0) -> Novel | Q18: =_xlfn.XLOOKUP(tbl_sale[[#This Row],[Product ID]],ProductMaster!$A$2:$A$23,ProductMaster!$C$2:$C$23,"NA",0) -> Books | R18: =IFERROR(IF(tbl_sale[[#This Row],[Delivery Date]]="","Pending",IF(tbl_sale[[#This Row],[Delivery Date]]-tbl_sale[[#This Row],[Order Date]]<= 2,"Fast","Slow")),"Error") -> Slow | S18: =_xlfn.XLOOKUP(tbl_sale[[#This Row],[Region]],RegionGoals!$A$2:$A$6,RegionGoals!$B$2:$B$6, ,0) -> 50500 | T18: =_xlfn.XLOOKUP(tbl_sale[[#This Row],[Customer ID]],CustomerMaster!$A:$A,CustomerMaster!$C:$C,"NA",0) -> Individual | U18: =IF(tbl_sale[[#This Row],[Delivery Status]]="Cancelled",1,0) -> 0 | V18: =IF(tbl_sale[[#This Row],[Order ID]]<>"",1,0) -> 1 | W18: =IF(AND(tbl_sale[[#This Row],[Delivery Status]]="Delivered",tbl_sale[[#This Row],[Delivery Performance]]="Fast"),1,0) -> 0 | X18: =IF(tbl_sale[[#This Row],[Delivery Status]]="Delivered",1,0) -> 1
A19: ORD0018 | B19: 45258 | E19: =TEXT(tbl_sale[[#This Row],[Order Date]],"MMM") -> Nov | F19: =IF(D19<>"","Cancelled",IF(C19<>"","Delivered","In Transit")) -> In Transit | G19: CUST011 | H19: PROD008 | I19: West | J19: 70 | K19: 5 | L19: 350 | M19: PayPal | N19: Amazon Logistics | O19: =_xlfn.XLOOKUP(tbl_sale[[#This Row],[Customer ID]],CustomerMaster!A:A,CustomerMaster!B:B,"NA",0) -> Mason Hall | P19: =_xlfn.XLOOKUP(tbl_sale[[#This Row],[Product ID]],ProductMaster!$A$2:$A$23,ProductMaster!$B$2:$B$23,"NA",0) -> Textbook | Q19: =_xlfn.XLOOKUP(tbl_sale[[#This Row],[Product ID]],ProductMaster!$A$2:$A$23,ProductMaster!$C$2:$C$23,"NA",0) -> Books | R19: =IFERROR(IF(tbl_sale[[#This Row],[Delivery Date]]="","Pending",IF(tbl_sale[[#This Row],[Delivery Date]]-tbl_sale[[#This Row],[Order Date]]<= 2,"Fast","Slow")),"Error") -> Pending | S19: =_xlfn.XLOOKUP(tbl_sale[[#This Row],[Region]],RegionGoals!$A$2:$A$6,RegionGoals!$B$2:$B$6, ,0) -> 90750 | T19: =_xlfn.XLOOKUP(tbl_sale[[#This Row],[Customer ID]],CustomerMaster!$A:$A,CustomerMaster!$C:$C,"NA",0) -> Business | U19: =IF(tbl_sale[[#This Row],[Delivery Status]]="Cancelled",1,0) -> 0 | V19: =IF(tbl_sale[[#This Row],[Order ID]]<>"",1,0) -> 1 | W19: =IF(AND(tbl_sale[[#This Row],[Delivery Status]]="Delivered",tbl_sale[[#This Row],[Delivery Performance]]="Fast"),1,0) -> 0 | X19: =IF(tbl_sale[[#This Row],[Delivery Status]]="Delivered",1,0) -> 0
A20: ORD0019 | B20: 45163 | E20: =TEXT(tbl_sale[[#This Row],[Order Date]],"MMM") -> Aug | F20: =IF(D20<>"","Cancelled",IF(C20<>"","Delivered","In Transit")) -> In Transit | G20: CUST041 | H20: PROD006 | I20: South | J20: 94 | K20: 4 | L20: 376 | M20: Credit Card | N20: USPS | O20: =_xlfn.XLOOKUP(tbl_sale[[#This Row],[Customer ID]],CustomerMaster!A:A,CustomerMaster!B:B,"NA",0) -> Jacob Price | P20: =_xlfn.XLOOKUP(tbl_sale[[#This Row],[Product ID]],ProductMaster!$A$2:$A$23,ProductMaster!$B$2:$B$23,"NA",0) -> Shoes | Q20: =_xlfn.XLOOKUP(tbl_sale[[#This Row],[Product ID]],ProductMaster!$A$2:$A$23,ProductMaster!$C$2:$C$23,"NA",0) -> Fashion | R20: =IFERROR(IF(tbl_sale[[#This Row],[Delivery Date]]="","Pending",IF(tbl_sale[[#This Row],[Delivery Date]]-tbl_sale[[#This Row],[Order Date]]<= 2,"Fast","Slow")),"Error") -> Pending | S20: =_xlfn.XLOOKUP(tbl_sale[[#This Row],[Region]],RegionGoals!$A$2:$A$6,RegionGoals!$B$2:$B$6, ,0) -> 91500 | T20: =_xlfn.XLOOKUP(tbl_sale[[#This Row],[Customer ID]],CustomerMaster!$A:$A,CustomerMaster!$C:$C,"NA",0) -> Business | U20: =IF(tbl_sale[[#This Row],[Delivery Status]]="Cancelled",1,0) -> 0 | V20: =IF(tbl_sale[[#This Row],[Order ID]]<>"",1,0) -> 1 | W20: =IF(AND(tbl_sale[[#This Row],[Delivery Status]]="Delivered",tbl_sale[[#This Row],[Delivery Performance]]="Fast"),1,0) -> 0 | X20: =IF(tbl_sale[[#This Row],[Delivery Status]]="Delivered",1,0) -> 0
A21: ORD0020 | B21: 45028 | E21: =TEXT(tbl_sale[[#This Row],[Order Date]],"MMM") -> Apr | F21: =IF(D21<>"","Cancelled",IF(C21<>"","Delivered","In Transit")) -> In Transit | G21: CUST025 | H21: PROD001 | I21: North | J21: 813 | K21: 2 | L21: 1626 | M21: Credit Card | N21: FedEx | O21: =_xlfn.XLOOKUP(tbl_sale[[#This Row],[Customer ID]],CustomerMaster!A:A,CustomerMaster!B:B,"NA",0) -> Emma King | P21: =_xlfn.XLOOKUP(tbl_sale[[#This Row],[Product ID]],ProductMaster!$A$2:$A$23,ProductMaster!$B$2:$B$23,"NA",0) -> Smartphone | Q21: =_xlfn.XLOOKUP(tbl_sale[[#This Row],[Product ID]],ProductMaster!$A$2:$A$23,ProductMaster!$C$2:$C$23,"NA",0) -> Electronics | R21: =IFERROR(IF(tbl_sale[[#This Row],[Delivery Date]]="","Pending",IF(tbl_sale[[#This Row],[Delivery Date]]-tbl_sale[[#This Row],[Order Date]]<= 2,"Fast","Slow")),"Error") -> Pending | S21: =_xlfn.XLOOKUP(tbl_sale[[#This Row],[Region]],RegionGoals!$A$2:$A$6,RegionGoals!$B$2:$B$6, ,0) -> 105000 | T21: =_xlfn.XLOOKUP(tbl_sale[[#This Row],[Customer ID]],CustomerMaster!$A:$A,CustomerMaster!$C:$C,"NA",0) -> Individual | U21: =IF(tbl_sale[[#This Row],[Delivery Status]]="Cancelled",1,0) -> 0 | V21: =IF(tbl_sale[[#This Row],[Order ID]]<>"",1,0) -> 1 | W21: =IF(AND(tbl_sale[[#This Row],[Delivery Status]]="Delivered",tbl_sale[[#This Row],[Delivery Performance]]="Fast"),1,0) -> 0 | X21: =IF(tbl_sale[[#This Row],[Delivery Status]]="Delivered",1,0) -> 0
A22: ORD0021 | B22: 45201 | E22: =TEXT(tbl_sale[[#This Row],[Order Date]],"MMM") -> Oct | F22: =IF(D22<>"","Cancelled",IF(C22<>"","Delivered","In Transit")) -> In Transit | G22: CUST013 | H22: PROD015 | I22: Central | J22: 21 | K22: 4 | L22: 84 | M22: PayPal | N22: Amazon Logistics | O22: =_xlfn.XLOOKUP(tbl_sale[[#This Row],[Customer ID]],CustomerMaster!A:A,CustomerMaster!B:B,"NA",0) -> Olivia Martinez | P22: =_xlfn.XLOOKUP(tbl_sale[[#This Row],[Product ID]],ProductMaster!$A$2:$A$23,ProductMaster!$B$2:$B$23,"NA",0) -> Novel | Q22: =_xlfn.XLOOKUP(tbl_sale[[#This Row],[Product ID]],ProductMaster!$A$2:$A$23,ProductMaster!$C$2:$C$23,"NA",0) -> Books | R22: =IFERROR(IF(tbl_sale[[#This Row],[Delivery Date]]="","Pending",IF(tbl_sale[[#This Row],[Delivery Date]]-tbl_sale[[#This Row],[Order Date]]<= 2,"Fast","Slow")),"Error") -> Pending | S22: =_xlfn.XLOOKUP(tbl_sale[[#This Row],[Region]],RegionGoals!$A$2:$A$6,RegionGoals!$B$2:$B$6, ,0) -> 97500 | T22: =_xlfn.XLOOKUP(tbl_sale[[#This Row],[Customer ID]],CustomerMaster!$A:$A,CustomerMaster!$C:$C,"NA",0) -> Prime | U22: =IF(tbl_sale[[#This Row],[Delivery Status]]="Cancelled",1,0) -> 0 | V22: =IF(tbl_sale[[#This Row],[Order ID]]<>"",1,0) -> 1 | W22: =IF(AND(tbl_sale[[#This Row],[Delivery Status]]="Delivered",tbl_sale[[#This Row],[Delivery Performance]]="Fast"),1,0) -> 0 | X22: =IF(tbl_sale[[#This Row],[Delivery Status]]="Delivered",1,0) -> 0
A23: ORD0022 | B23: 45239 | E23: =TEXT(tbl_sale[[#This Row],[Order Date]],"MMM") -> Nov | F23: =IF(D23<>"","Cancelled",IF(C23<>"","Delivered","In Transit")) -> In Transit | G23: CUST023 | H23: PROD012 | I23: West | J23: 46 | K23: 5 | L23: 230 | M23: PayPal | N23: USPS | O23: =_xlfn.XLOOKUP(tbl_sale[[#This Row],[Customer ID]],CustomerMaster!A:A,CustomerMaster!B:B,"NA",0) -> Charlotte Reed | P23: =_xlfn.XLOOKUP(tbl_sale[[#This Row],[Product ID]],ProductMaster!$A$2:$A$23,ProductMaster!$B$2:$B$23,"NA",0) -> Lamp | Q23: =_xlfn.XLOOKUP(tbl_sale[[#This Row],[Product ID]],ProductMaster!$A$2:$A$23,ProductMaster!$C$2:$C$23,"NA",0) -> Home | R23: =IFERROR(IF(tbl_sale[[#This Row],[Delivery Date]]="","Pending",IF(tbl_sale[[#This Row],[Delivery Date]]-tbl_sale[[#This Row],[Order Date]]<= 2,"Fast","Slow")),"Error") -> Pending | S23: =_xlfn.XLOOKUP(tbl_sale[[#This Row],[Region]],RegionGoals!$A$2:$A$6,RegionGoals!$B$2:$B$6, ,0) -> 90750 | T23: =_xlfn.XLOOKUP(tbl_sale[[#This Row],[Customer ID]],CustomerMaster!$A:$A,CustomerMaster!$C:$C,"NA",0) -> Individual | U23: =IF(tbl_sale[[#This Row],[Delivery Status]]="Cancelled",1,0) -> 0 | V23: =IF(tbl_sale[[#This Row],[Order ID]]<>"",1,0) -> 1 | W23: =IF(AND(tbl_sale[[#This Row],[Delivery Status]]="Delivered",tbl_sale[[#This Row],[Delivery Performance]]="Fast"),1,0) -> 0 | X23: =IF(tbl_sale[[#This Row],[Delivery Status]]="Delivered",1,0) -> 0
A24: ORD0023 | B24: 44970 | D24: 44971 | E24: =TEXT(tbl_sale[[#This Row],[Order Date]],"MMM") -> Feb | F24: =IF(D24<>"","Cancelled",IF(C24<>"","Delivered","In Transit")) -> Cancelled | G24: CUST016 | H24: PROD010 | I24: West | J24: 58 | K24: 3 | L24: 174 | M24: Amazon Pay | N24: Amazon Logistics | O24: =_xlfn.XLOOKUP(tbl_sale[[#This Row],[Customer ID]],CustomerMaster!A:A,CustomerMaster!B:B,"NA",0) -> Elijah Lewis | P24: =_xlfn.XLOOKUP(tbl_sale[[#This Row],[Product ID]],ProductMaster!$A$2:$A$23,ProductMaster!$B$2:$B$23,"NA",0) -> Jeans | Q24: =_xlfn.XLOOKUP(tbl_sale[[#This Row],[Product ID]],ProductMaster!$A$2:$A$23,ProductMaster!$C$2:$C$23,"NA",0) -> Fashion | R24: =IFERROR(IF(tbl_sale[[#This Row],[Delivery Date]]="","Pending",IF(tbl_sale[[#This Row],[Delivery Date]]-tbl_sale[[#This Row],[Order Date]]<= 2,"Fast","Slow")),"Error") -> Pending | S24: =_xlfn.XLOOKUP(tbl_sale[[#This Row],[Region]],RegionGoals!$A$2:$A$6,RegionGoals!$B$2:$B$6, ,0) -> 90750 | T24: =_xlfn.XLOOKUP(tbl_sale[[#This Row],[Customer ID]],CustomerMaster!$A:$A,CustomerMaster!$C:$C,"NA",0) -> Prime | U24: =IF(tbl_sale[[#This Row],[Delivery Status]]="Cancelled",1,0) -> 1 | V24: =IF(tbl_sale[[#This Row],[Order ID]]<>"",1,0) -> 1 | W24: =IF(AND(tbl_sale[[#This Row],[Delivery Status]]="Delivered",tbl_sale[[#This Row],[Delivery Performance]]="Fast"),1,0) -> 0 | X24: =IF(tbl_sale[[#This Row],[Delivery Status]]="Delivered",1,0) -> 0
A25: ORD0024 | B25: 45232 | C25: 45235 | E25: =TEXT(tbl_sale[[#This Row],[Order Date]],"MMM") -> Nov | F25: =IF(D25<>"","Cancelled",IF(C25<>"","Delivered","In Transit")) -> Delivered | G25: CUST028 | H25: PROD006 | I25: West | J25: 96 | K25: 5 | L25: 480 | M25: Amazon Pay | N25: Amazon Logistics | O25: =_xlfn.XLOOKUP(tbl_sale[[#This Row],[Customer ID]],CustomerMaster!A:A,CustomerMaster!B:B,"NA",0) -> Lily Bennett | P25: =_xlfn.XLOOKUP(tbl_sale[[#This Row],[Product ID]],ProductMaster!$A$2:$A$23,ProductMaster!$B$2:$B$23,"NA",0) -> Shoes | Q25: =_xlfn.XLOOKUP(tbl_sale[[#This Row],[Product ID]],ProductMaster!$A$2:$A$23,ProductMaster!$C$2:$C$23,"NA",0) -> Fashion | R25: =IFERROR(IF(tbl_sale[[#This Row],[Delivery Date]]="","Pending",IF(tbl_sale[[#This Row],[Delivery Date]]-tbl_sale[[#This Row],[Order Date]]<= 2,"Fast","Slow")),"Error") -> Slow | S25: =_xlfn.XLOOKUP(tbl_sale[[#This Row],[Region]],RegionGoals!$A$2:$A$6,RegionGoals!$B$2:$B$6, ,0) -> 90750 | T25: =_xlfn.XLOOKUP(tbl_sale[[#This Row],[Customer ID]],CustomerMaster!$A:$A,CustomerMaster!$C:$C,"NA",0) -> Business | U25: =IF(tbl_sale[[#This Row],[Delivery Status]]="Cancelled",1,0) -> 0 | V25: =IF(tbl_sale[[#This Row],[Order ID]]<>"",1,0) -> 1 | W25: =IF(AND(tbl_sale[[#This Row],[Delivery Status]]="Delivered",tbl_sale[[#This Row],[Delivery Performance]]="Fast"),1,0) -> 0 | X25: =IF(tbl_sale[[#This Row],[Delivery Status]]="Delivered",1,0) -> 1
A26: ORD0025 | B26: 45074 | C26: 45076 | E26: =TEXT(tbl_sale[[#This Row],[Order Date]],"MMM") -> May | F26: =IF(D26<>"","Cancelled",IF(C26<>"","Delivered","In Transit")) -> Delivered | G26: CUST040 | H26: PROD002 | I26: South | J26: 43 | K26: 1 | L26: 43 | M26: Debit Card | N26: Amazon Logistics | O26: =_xlfn.XLOOKUP(tbl_sale[[#This Row],[Customer ID]],CustomerMaster!A:A,CustomerMaster!B:B,"NA",0) -> Benjamin Clark | P26: =_xlfn.XLOOKUP(tbl_sale[[#This Row],[Product ID]],ProductMaster!$A$2:$A$23,ProductMaster!$B$2:$B$23,"NA",0) -> Action Figure | Q26: =_xlfn.XLOOKUP(tbl_sale[[#This Row],[Product ID]],ProductMaster!$A$2:$A$23,ProductMaster!$C$2:$C$23,"NA",0) -> Toys | R26: =IFERROR(IF(tbl_sale[[#This Row],[Delivery Date]]="","Pending",IF(tbl_sale[[#This Row],[Delivery Date]]-tbl_sale[[#This Row],[Order Date]]<= 2,"Fast","Slow")),"Error") -> Fast | S26: =_xlfn.XLOOKUP(tbl_sale[[#This Row],[Region]],RegionGoals!$A$2:$A$6,RegionGoals!$B$2:$B$6, ,0) -> 91500 | T26: =_xlfn.XLOOKUP(tbl_sale[[#This Row],[Customer ID]],CustomerMaster!$A:$A,CustomerMaster!$C:$C,"NA",0) -> Prime | U26: =IF(tbl_sale[[#This Row],[Delivery Status]]="Cancelled",1,0) -> 0 | V26: =IF(tbl_sale[[#This Row],[Order ID]]<>"",1,0) -> 1 | W26: =IF(AND(tbl_sale[[#This Row],[Delivery Status]]="Delivered",tbl_sale[[#This Row],[Delivery Performance]]="Fast"),1,0) -> 1 | X26: =IF(tbl_sale[[#This Row],[Delivery Status]]="Delivered",1,0) -> 1
A27: ORD0026 | B27: 45214 | C27: 45220 | E27: =TEXT(tbl_sale[[#This Row],[Order Date]],"MMM") -> Oct | F27: =IF(D27<>"","Cancelled",IF(C27<>"","Delivered","In Transit")) -> Delivered | G27: CUST027 | H27: PROD022 | I27: South | J27: 64 | K27: 4 | L27: 256 | M27: Debit Card | N27: USPS | O27: =_xlfn.XLOOKUP(tbl_sale[[#This Row],[Customer ID]],CustomerMaster!A:A,CustomerMaster!B:B,"NA",0) -> Hazel Brooks | P27: =_xlfn.XLOOKUP(tbl_sale[[#This Row],[Product ID]],ProductMaster!$A$2:$A$23,ProductMaster!$B$2:$B$23,"NA",0) -> Backpack | Q27: =_xlfn.XLOOKUP(tbl_sale[[#This Row],[Product ID]],ProductMaster!$A$2:$A$23,ProductMaster!$C$2:$C$23,"NA",0) -> Fashion | R27: =IFERROR(IF(tbl_sale[[#This Row],[Delivery Date]]="","Pending",IF(tbl_sale[[#This Row],[Delivery Date]]-tbl_sale[[#This Row],[Order Date]]<= 2,"Fast","Slow")),"Error") -> Slow | S27: =_xlfn.XLOOKUP(tbl_sale[[#This Row],[Region]],RegionGoals!$A$2:$A$6,RegionGoals!$B$2:$B$6, ,0) -> 91500 | T27: =_xlfn.XLOOKUP(tbl_sale[[#This Row],[Customer ID]],CustomerMaster!$A:$A,CustomerMaster!$C:$C,"NA",0) -> Individual | U27: =IF(tbl_sale[[#This Row],[Delivery Status]]="Cancelled",1,0) -> 0 | V27: =IF(tbl_sale[[#This Row],[Order ID]]<>"",1,0) -> 1 | W27: =IF(AND(tbl_sale[[#This Row],[Delivery Status]]="Delivered",tbl_sale[[#This Row],[Delivery Performance]]="Fast"),1,0) -> 0 | X27: =IF(tbl_sale[[#This Row],[Delivery Status]]="Delivered",1,0) -> 1
A28: ORD0027 | B28: 44942 | E28: =TEXT(tbl_sale[[#This Row],[Order Date]],"MMM") -> Jan | F28: =IF(D28<>"","Cancelled",IF(C28<>"","Delivered","In Transit")) -> In Transit | G28: CUST018 | H28: PROD008 | I28: South | J28: 70 | K28: 2 | L28: 140 | M28: Amazon Pay | N28: Amazon Logistics | O28: =_xlfn.XLOOKUP(tbl_sale[[#This Row],[Customer ID]],CustomerMaster!A:A,CustomerMaster!B:B,"NA",0) -> Grace Scott | P28: =_xlfn.XLOOKUP(tbl_sale[[#This Row],[Product ID]],ProductMaster!$A$2:$A$23,ProductMaster!$B$2:$B$23,"NA",0) -> Textbook | Q28: =_xlfn.XLOOKUP(tbl_sale[[#This Row],[Product ID]],ProductMaster!$A$2:$A$23,ProductMaster!$C$2:$C$23,"NA",0) -> Books | R28: =IFERROR(IF(tbl_sale[[#This Row],[Delivery Date]]="","Pending",IF(tbl_sale[[#This Row],[Delivery Date]]-tbl_sale[[#This Row],[Order Date]]<= 2,"Fast","Slow")),"Error") -> Pending | S28: =_xlfn.XLOOKUP(tbl_sale[[#This Row],[Region]],RegionGoals!$A$2:$A$6,RegionGoals!$B$2:$B$6, ,0) -> 91500 | T28: =_xlfn.XLOOKUP(tbl_sale[[#This Row],[Customer ID]],CustomerMaster!$A:$A,CustomerMaster!$C:$C,"NA",0) -> Individual | U28: =IF(tbl_sale[[#This Row],[Delivery Status]]="Cancelled",1,0) -> 0 | V28: =IF(tbl_sale[[#This Row],[Order ID]]<>"",1,0) -> 1 | W28: =IF(AND(tbl_sale[[#This Row],[Delivery Status]]="Delivered",tbl_sale[[#This Row],[Delivery Performance]]="Fast"),1,0) -> 0 | X28: =IF(tbl_sale[[#This Row],[Delivery Status]]="Delivered",1,0) -> 0
A29: ORD0028 | B29: 45208 | E29: =TEXT(tbl_sale[[#This Row],[Order Date]],"MMM") -> Oct | F29: =IF(D29<>"","Cancelled",IF(C29<>"","Delivered","In Transit")) -> In Transit | G29: CUST018 | H29: PROD018 | I29: Central | J29: 97 | K29: 3 | L29: 291 | M29: Credit Card | N29: Amazon Logistics | O29: =_xlfn.XLOOKUP(tbl_sale[[#This Row],[Customer ID]],CustomerMaster!A:A,CustomerMaster!B:B,"NA",0) -> Grace Scott | P29: =_xlfn.XLOOKUP(tbl_sale[[#This Row],[Product ID]],ProductMaster!$A$2:$A$23,ProductMaster!$B$2:$B$23,"NA",0) -> Doll House | Q29: =_xlfn.XLOOKUP(tbl_sale[[#This Row],[Product ID]],ProductMaster!$A$2:$A$23,ProductMaster!$C$2:$C$23,"NA",0) -> Toys | R29: =IFERROR(IF(tbl_sale[[#This Row],[Delivery Date]]="","Pending",IF(tbl_sale[[#This Row],[Delivery Date]]-tbl_sale[[#This Row],[Order Date]]<= 2,"Fast","Slow")),"Error") -> Pending | S29: =_xlfn.XLOOKUP(tbl_sale[[#This Row],[Region]],RegionGoals!$A$2:$A$6,RegionGoals!$B$2:$B$6, ,0) -> 97500 | T29: =_xlfn.XLOOKUP(tbl_sale[[#This Row],[Customer ID]],CustomerMaster!$A:$A,CustomerMaster!$C:$C,"NA",0) -> Individual | U29: =IF(tbl_sale[[#This Row],[Delivery Status]]="Cancelled",1,0) -> 0 | V29: =IF(tbl_sale[[#This Row],[Order ID]]<>"",1,0) -> 1 | W29: =IF(AND(tbl_sale[[#This Row],[Delivery Status]]="Delivered",tbl_sale[[#This Row],[Delivery Performance]]="Fast"),1,0) -> 0 | X29: =IF(tbl_sale[[#This Row],[Delivery Status]]="Delivered",1,0) -> 0
A30: ORD0029 | B30: 45206 | D30: 45209 | E30: =TEXT(tbl_sale[[#This Row],[Order Date]],"MMM") -> Oct | F30: =IF(D30<>"","Cancelled",IF(C30<>"","Delivered","In Transit")) -> Cancelled | G30: CUST007 | H30: PROD021 | I30: East | J30: 37 | K30: 3 | L30: 111 | M30: Apple Pay | N30: DHL | O30: =_xlfn.XLOOKUP(tbl_sale[[#This Row],[Customer ID]],CustomerMaster!A:A,CustomerMaster!B:B,"NA",0) -> Liam Walker | P30: =_xlfn.XLOOKUP(tbl_sale[[#This Row],[Product ID]],ProductMaster!$A$2:$A$23,ProductMaster!$B$2:$B$23,"NA",0) -> Wall Clock | Q30: =_xlfn.XLOOKUP(tbl_sale[[#This Row],[Product ID]],ProductMaster!$A$2:$A$23,ProductMaster!$C$2:$C$23,"NA",0) -> Home | R30: =IFERROR(IF(tbl_sale[[#This Row],[Delivery Date]]="","Pending",IF(tbl_sale[[#This Row],[Delivery Date]]-tbl_sale[[#This Row],[Order Date]]<= 2,"Fast","Slow")),"Error") -> Pending | S30: =_xlfn.XLOOKUP(tbl_sale[[#This Row],[Region]],RegionGoals!$A$2:$A$6,RegionGoals!$B$2:$B$6, ,0) -> 50500 | T30: =_xlfn.XLOOKUP(tbl_sale[[#This Row],[Customer ID]],CustomerMaster!$A:$A,CustomerMaster!$C:$C,"NA",0) -> Prime | U30: =IF(tbl_sale[[#This Row],[Delivery Status]]="Cancelled",1,0) -> 1 | V30: =IF(tbl_sale[[#This Row],[Order ID]]<>"",1,0) -> 1 | W30: =IF(AND(tbl_sale[[#This Row],[Delivery Status]]="Delivered",tbl_sale[[#This Row],[Delivery Performance]]="Fast"),1,0) -> 0 | X30: =IF(tbl_sale[[#This Row],[Delivery Status]]="Delivered",1,0) -> 0
A31: ORD0030 | B31: 44971 | E31: =TEXT(tbl_sale[[#This Row],[Order Date]],"MMM") -> Feb | F31: =IF(D31<>"","Cancelled",IF(C31<>"","Delivered","In Transit")) -> In Transit | G31: CUST008 | H31: PROD008 | I31: North | J31: 69 | K31: 5 | L31: 345 | M31: Amazon Pay | N31: Amazon Logistics | O31: =_xlfn.XLOOKUP(tbl_sale[[#This Row],[Customer ID]],CustomerMaster!A:A,CustomerMaster!B:B,"NA",0) -> Harper Young | P31: =_xlfn.XLOOKUP(tbl_sale[[#This Row],[Product ID]],ProductMaster!$A$2:$A$23,ProductMaster!$B$2:$B$23,"NA",0) -> Textbook | Q31: =_xlfn.XLOOKUP(tbl_sale[[#This Row],[Product ID]],ProductMaster!$A$2:$A$23,ProductMaster!$C$2:$C$23,"NA",0) -> Books | R31: =IFERROR(IF(tbl_sale[[#This Row],[Delivery Date]]="","Pending",IF(tbl_sale[[#This Row],[Delivery Date]]-tbl_sale[[#This Row],[Order Date]]<= 2,"Fast","Slow")),"Error") -> Pending | S31: =_xlfn.XLOOKUP(tbl_sale[[#This Row],[Region]],RegionGoals!$A$2:$A$6,RegionGoals!$B$2:$B$6, ,0) -> 105000 | T31: =_xlfn.XLOOKUP(tbl_sale[[#This Row],[Customer ID]],CustomerMaster!$A:$A,CustomerMaster!$C:$C,"NA",0) -> Business | U31: =IF(tbl_sale[[#This Row],[Delivery Status]]="Cancelled",1,0) -> 0 | V31: =IF(tbl_sale[[#This Row],[Order ID]]<>"",1,0) -> 1 | W31: =IF(AND(tbl_sale[[#This Row],[Delivery Status]]="Delivered",tbl_sale[[#This Row],[Delivery Performance]]="Fast"),1,0) -> 0 | X31: =IF(tbl_sale[[#This Row],[Delivery Status]]="Delivered",1,0) -> 0
A32: ORD0031 | B32: 45011 | E32: =TEXT(tbl_sale[[#This Row],[Order Date]],"MMM") -> Mar | F32: =IF(D32<>"","Cancelled",IF(C32<>"","Delivered","In Transit")) -> In Transit | G32: CUST014 | H32: PROD002 | I32: North | J32: 42 | K32: 5 | L32: 210 | M32: Amazon Pay | N32: UPS | O32: =_xlfn.XLOOKUP(tbl_sale[[#This Row],[Customer ID]],CustomerMaster!A:A,CustomerMaster!B:B,"NA",0) -> Harper Young | P32: =_xlfn.XLOOKUP(tbl_sale[[#This Row],[Product ID]],ProductMaster!$A$2:$A$23,ProductMaster!$B$2:$B$23,"NA",0) -> Action Figure | Q32: =_xlfn.XLOOKUP(tbl_sale[[#This Row],[Product ID]],ProductMaster!$A$2:$A$23,ProductMaster!$C$2:$C$23,"NA",0) -> Toys | R32: =IFERROR(IF(tbl_sale[[#This Row],[Delivery Date]]="","Pending",IF(tbl_sale[[#This Row],[Delivery Date]]-tbl_sale[[#This Row],[Order Date]]<= 2,"Fast","Slow")),"Error") -> Pending | S32: =_xlfn.XLOOKUP(tbl_sale[[#This Row],[Region]],RegionGoals!$A$2:$A$6,RegionGoals!$B$2:$B$6, ,0) -> 105000 | T32: =_xlfn.XLOOKUP(tbl_sale[[#This Row],[Customer ID]],CustomerMaster!$A:$A,CustomerMaster!$C:$C,"NA",0) -> Individual | U32: =IF(tbl_sale[[#This Row],[Delivery Status]]="Cancelled",1,0) -> 0 | V32: =IF(tbl_sale[[#This Row],[Order ID]]<>"",1,0) -> 1 | W32: =IF(AND(tbl_sale[[#This Row],[Delivery Status]]="Delivered",tbl_sale[[#This Row],[Delivery Performance]]="Fast"),1,0) -> 0 | X32: =IF(tbl_sale[[#This Row],[Delivery Status]]="Delivered",1,0) -> 0
A33: ORD0032 | B33: 45092 | D33: 45099 | E33: =TEXT(tbl_sale[[#This Row],[Order Date]],"MMM") -> Jun | F33: =IF(D33<>"","Cancelled",IF(C33<>"","Delivered","In Transit")) -> Cancelled | G33: CUST037 | H33: PROD009 | I33: East | J33: 11 | K33: 5 | L33: 55 | M33: Debit Card | N33: FedEx | O33: =_xlfn.XLOOKUP(tbl_sale[[#This Row],[Customer ID]],CustomerMaster!A:A,CustomerMaster!B:B,"NA",0) -> Emily Johnson | P33: =_xlfn.XLOOKUP(tbl_sale[[#This Row],[Product ID]],ProductMaster!$A$2:$A$23,ProductMaster!$B$2:$B$23,"NA",0) -> Magazine | Q33: =_xlfn.XLOOKUP(tbl_sale[[#This Row],[Product ID]],ProductMaster!$A$2:$A$23,ProductMaster!$C$2:$C$23,"NA",0) -> Books | R33: =IFERROR(IF(tbl_sale[[#This Row],[Delivery Date]]="","Pending",IF(tbl_sale[[#This Row],[Delivery Date]]-tbl_sale[[#This Row],[Order Date]]<= 2,"Fast","Slow")),"Error") -> Pending | S33: =_xlfn.XLOOKUP(tbl_sale[[#This Row],[Region]],RegionGoals!$A$2:$A$6,RegionGoals!$B$2:$B$6, ,0) -> 50500 | T33: =_xlfn.XLOOKUP(tbl_sale[[#This Row],[Customer ID]],CustomerMaster!$A:$A,CustomerMaster!$C:$C,"NA",0) -> Individual | U33: =IF(tbl_sale[[#This Row],[Delivery Status]]="Cancelled",1,0) -> 1 | V33: =IF(tbl_sale[[#This Row],[Order ID]]<>"",1,0) -> 1 | W33: =IF(AND(tbl_sale[[#This Row],[Delivery Status]]="Delivered",tbl_sale[[#This Row],[Delivery Performance]]="Fast"),1,0) -> 0 | X33: =IF(tbl_sale[[#This Row],[Delivery Status]]="Delivered",1,0) -> 0
A34: ORD0033 | B34: 45068 | C34: 45069 | E34: =TEXT(tbl_sale[[#This Row],[Order Date]],"MMM") -> May | F34: =IF(D34<>"","Cancelled",IF(C34<>"","Delivered","In Transit")) -> Delivered | G34: CUST016 | H34: PROD005 | I34: South | J34: 27 | K34: 2 | L34: 54 | M34: Apple Pay | N34: USPS | O34: =_xlfn.XLOOKUP(tbl_sale[[#This Row],[Customer ID]],CustomerMaster!A:A,CustomerMaster!B:B,"NA",0) -> Elijah Lewis | P34: =_xlfn.XLOOKUP(tbl_sale[[#This Row],[Product ID]],ProductMaster!$A$2:$A$23,ProductMaster!$B$2:$B$23,"NA",0) -> T-Shirt | Q34: =_xlfn.XLOOKUP(tbl_sale[[#This Row],[Product ID]],ProductMaster!$A$2:$A$23,ProductMaster!$C$2:$C$23,"NA",0) -> Fashion | R34: =IFERROR(IF(tbl_sale[[#This Row],[Delivery Date]]="","Pending",IF(tbl_sale[[#This Row],[Delivery Date]]-tbl_sale[[#This Row],[Order Date]]<= 2,"Fast","Slow")),"Error") -> Fast | S34: =_xlfn.XLOOKUP(tbl_sale[[#This Row],[Region]],RegionGoals!$A$2:$A$6,RegionGoals!$B$2:$B$6, ,0) -> 91500 | T34: =_xlfn.XLOOKUP(tbl_sale[[#This Row],[Customer ID]],CustomerMaster!$A:$A,CustomerMaster!$C:$C,"NA",0) -> Prime | U34: =IF(tbl_sale[[#This Row],[Delivery Status]]="Cancelled",1,0) -> 0 | V34: =IF(tbl_sale[[#This Row],[Order ID]]<>"",1,0) -> 1 | W34: =IF(AND(tbl_sale[[#This Row],[Delivery Status]]="Delivered",tbl_sale[[#This Row],[Delivery Performance]]="Fast"),1,0) -> 1 | X34: =IF(tbl_sale[[#This Row],[Delivery Status]]="Delivered",1,0) -> 1
A35: ORD0034 | B35: 45250 | E35: =TEXT(tbl_sale[[#This Row],[Order Date]],"MMM") -> Nov | F35: =IF(D35<>"","Cancelled",IF(C35<>"","Delivered","In Transit")) -> In Transit | G35: CUST025 | H35: PROD015 | I35: South | J35: 21 | K35: 1 | L35: 21 | M35: Amazon Pay | N35: DHL | O35: =_xlfn.XLOOKUP(tbl_sale[[#This Row],[Customer ID]],CustomerMaster!A:A,CustomerMaster!B:B,"NA",0) -> Emma King | P35: =_xlfn.XLOOKUP(tbl_sale[[#This Row],[Product ID]],ProductMaster!$A$2:$A$23,ProductMaster!$B$2:$B$23,"NA",0) -> Novel | Q35: =_xlfn.XLOOKUP(tbl_sale[[#This Row],[Product ID]],ProductMaster!$A$2:$A$23,ProductMaster!$C$2:$C$23,"NA",0) -> Books | R35: =IFERROR(IF(tbl_sale[[#This Row],[Delivery Date]]="","Pending",IF(tbl_sale[[#This Row],[Delivery Date]]-tbl_sale[[#This Row],[Order Date]]<= 2,"Fast","Slow")),"Error") -> Pending | S35: =_xlfn.XLOOKUP(tbl_sale[[#This Row],[Region]],RegionGoals!$A$2:$A$6,RegionGoals!$B$2:$B$6, ,0) -> 91500 | T35: =_xlfn.XLOOKUP(tbl_sale[[#This Row],[Customer ID]],CustomerMaster!$A:$A,CustomerMaster!$C:$C,"NA",0) -> Individual | U35: =IF(tbl_sale[[#This Row],[Delivery Status]]="Cancelled",1,0) -> 0 | V35: =IF(tbl_sale[[#This Row],[Order ID]]<>"",1,0) -> 1 | W35: =IF(AND(tbl_sale[[#This Row],[Delivery Status]]="Delivered",tbl_sale[[#This Row],[Delivery Performance]]="Fast"),1,0) -> 0 | X35: =IF(tbl_sale[[#This Row],[Delivery Status]]="Delivered",1,0) -> 0
A36: ORD0035 | B36: 45282 | C36: 45286 | E36: =TEXT(tbl_sale[[#This Row],[Order Date]],"MMM") -> Dec | F36: =IF(D36<>"","Cancelled",IF(C36<>"","Delivered","In Transit")) -> Delivered | G36: CUST032 | H36: PROD011 | I36: South | J36: 172 | K36: 1 | L36: 172 | M36: PayPal | N36: USPS | O36: =_xlfn.XLOOKUP(tbl_sale[[#This Row],[Customer ID]],CustomerMaster!A:A,CustomerMaster!B:B,"NA",0) -> Luke Gray | P36: =_xlfn.XLOOKUP(tbl_sale[[#This Row],[Product ID]],ProductMaster!$A$2:$A$23,ProductMaster!$B$2:$B$23,"NA",0) -> Headphones | Q36: =_xlfn.XLOOKUP(tbl_sale[[#This Row],[Product ID]],ProductMaster!$A$2:$A$23,ProductMaster!$C$2:$C$23,"NA",0) -> Electronics | R36: =IFERROR(IF(tbl_sale[[#This Row],[Delivery Date]]="","Pending",IF(tbl_sale[[#This Row],[Delivery Date]]-tbl_sale[[#This Row],[Order Date]]<= 2,"Fast","Slow")),"Error") -> Slow | S36: =_xlfn.XLOOKUP(tbl_sale[[#This Row],[Region]],RegionGoals!$A$2:$A$6,RegionGoals!$B$2:$B$6, ,0) -> 91500 | T36: =_xlfn.XLOOKUP(tbl_sale[[#This Row],[Customer ID]],CustomerMaster!$A:$A,CustomerMaster!$C:$C,"NA",0) -> Business | U36: =IF(tbl_sale[[#This Row],[Delivery Status]]="Cancelled",1,0) -> 0 | V36: =IF(tbl_sale[[#This Row],[Order ID]]<>"",1,0) -> 1 | W36: =IF(AND(tbl_sale[[#This Row],[Delivery Status]]="Delivered",tbl_sale[[#This Row],[Delivery Performance]]="Fast"),1,0) -> 0 | X36: =IF(tbl_sale[[#This Row],[Delivery Status]]="Delivered",1,0) -> 1
A37: ORD0036 | B37: 45130 | E37: =TEXT(tbl_sale[[#This Row],[Order Date]],"MMM") -> Jul | F37: =IF(D37<>"","Cancelled",IF(C37<>"","Delivered","In Transit")) -> In Transit | G37: CUST014 | H37: PROD016 | I37: North | J37: 212 | K37: 3 | L37: 636 | M37: Amazon Pay | N37: UPS | O37: =_xlfn.XLOOKUP(tbl_sale[[#This Row],[Customer ID]],CustomerMaster!A:A,CustomerMaster!B:B,"NA",0) -> Harper Young | P37: =_xlfn.XLOOKUP(tbl_sale[[#This Row],[Product ID]],ProductMaster!$A$2:$A$23,ProductMaster!$B$2:$B$23,"NA",0) -> Cookware Set Pro | Q37: =_xlfn.XLOOKUP(tbl_sale[[#This Row],[Product ID]],ProductMaster!$A$2:$A$23,ProductMaster!$C$2:$C$23,"NA",0) -> Home | R37: =IFERROR(IF(tbl_sale[[#This Row],[Delivery Date]]="","Pending",IF(tbl_sale[[#This Row],[Delivery Date]]-tbl_sale[[#This Row],[Order Date]]<= 2,"Fast","Slow")),"Error") -> Pending | S37: =_xlfn.XLOOKUP(tbl_sale[[#This Row],[Region]],RegionGoals!$A$2:$A$6,RegionGoals!$B$2:$B$6, ,0) -> 105000 | T37: =_xlfn.XLOOKUP(tbl_sale[[#This Row],[Customer ID]],CustomerMaster!$A:$A,CustomerMaster!$C:$C,"NA",0) -> Individual | U37: =IF(tbl_sale[[#This Row],[Delivery Status]]="Cancelled",1,0) -> 0 | V37: =IF(tbl_sale[[#This Row],[Order ID]]<>"",1,0) -> 1 | W37: =IF(AND(tbl_sale[[#This Row],[Delivery Status]]="Delivered",tbl_sale[[#This Row],[Delivery Performance]]="Fast"),1,0) -> 0 | X37: =IF(tbl_sale[[#This Row],[Delivery Status]]="Delivered",1,0) -> 0
A38: ORD0037 | B38: 45216 | C38: 45221 | E38: =TEXT(tbl_sale[[#This Row],[Order Date]],"MMM") -> Oct | F38: =IF(D38<>"","Cancelled",IF(C38<>"","Delivered","In Transit")) -> Delivered | G38: CUST044 | H38: PROD002 | I38: East | J38: 41 | K38: 4 | L38: 164 | M38: Credit Card | N38: Amazon Logistics | O38: =_xlfn.XLOOKUP(tbl_sale[[#This Row],[Customer ID]],CustomerMaster!A:A,CustomerMaster!B:B,"NA",0) -> Grace Ward | P38: =_xlfn.XLOOKUP(tbl_sale[[#This Row],[Product ID]],ProductMaster!$A$2:$A$23,ProductMaster!$B$2:$B$23,"NA",0) -> Action Figure | Q38: =_xlfn.XLOOKUP(tbl_sale[[#This Row],[Product ID]],ProductMaster!$A$2:$A$23,ProductMaster!$C$2:$C$23,"NA",0) -> Toys | R38: =IFERROR(IF(tbl_sale[[#This Row],[Delivery Date]]="","Pending",IF(tbl_sale[[#This Row],[Delivery Date]]-tbl_sale[[#This Row],[Order Date]]<= 2,"Fast","Slow")),"Error") -> Slow | S38: =_xlfn.XLOOKUP(tbl_sale[[#This Row],[Region]],RegionGoals!$A$2:$A$6,RegionGoals!$B$2:$B$6, ,0) -> 50500 | T38: =_xlfn.XLOOKUP(tbl_sale[[#This Row],[Customer ID]],CustomerMaster!$A:$A,CustomerMaster!$C:$C,"NA",0) -> Business | U38: =IF(tbl_sale[[#This Row],[Delivery Status]]="Cancelled",1,0) -> 0 | V38: =IF(tbl_sale[[#This Row],[Order ID]]<>"",1,0) -> 1 | W38: =IF(AND(tbl_sale[[#This Row],[Delivery Status]]="Delivered",tbl_sale[[#This Row],[Delivery Performance]]="Fast"),1,0) -> 0 | X38: =IF(tbl_sale[[#This Row],[Delivery Status]]="Delivered",1,0) -> 1
A39: ORD0038 | B39: 45160 | D39: 45162 | E39: =TEXT(tbl_sale[[#This Row],[Order Date]],"MMM") -> Aug | F39: =IF(D39<>"","Cancelled",IF(C39<>"","Delivered","In Transit")) -> Cancelled | G39: CUST028 | H39: PROD007 | I39: North | J39: 32 | K39: 2 | L39: 64 | M39: Debit Card | N39: FedEx | O39: =_xlfn.XLOOKUP(tbl_sale[[#This Row],[Customer ID]],CustomerMaster!A:A,CustomerMaster!B:B,"NA",0) -> Lily Bennett | P39: =_xlfn.XLOOKUP(tbl_sale[[#This Row],[Product ID]],ProductMaster!$A$2:$A$23,ProductMaster!$B$2:$B$23,"NA",0) -> Puzzle | Q39: =_xlfn.XLOOKUP(tbl_sale[[#This Row],[Product ID]],ProductMaster!$A$2:$A$23,ProductMaster!$C$2:$C$23,"NA",0) -> Toys | R39: =IFERROR(IF(tbl_sale[[#This Row],[Delivery Date]]="","Pending",IF(tbl_sale[[#This Row],[Delivery Date]]-tbl_sale[[#This Row],[Order Date]]<= 2,"Fast","Slow")),"Error") -> Pending | S39: =_xlfn.XLOOKUP(tbl_sale[[#This Row],[Region]],RegionGoals!$A$2:$A$6,RegionGoals!$B$2:$B$6, ,0) -> 105000 | T39: =_xlfn.XLOOKUP(tbl_sale[[#This Row],[Customer ID]],CustomerMaster!$A:$A,CustomerMaster!$C:$C,"NA",0) -> Business | U39: =IF(tbl_sale[[#This Row],[Delivery Status]]="Cancelled",1,0) -> 1 | V39: =IF(tbl_sale[[#This Row],[Order ID]]<>"",1,0) -> 1 | W39: =IF(AND(tbl_sale[[#This Row],[Delivery Status]]="Delivered",tbl_sale[[#This Row],[Delivery Performance]]="Fast"),1,0) -> 0 | X39: =IF(tbl_sale[[#This Row],[Delivery Status]]="Delivered",1,0) -> 0
A40: ORD0039 | B40: 45262 | E40: =TEXT(tbl_sale[[#This Row],[Order Date]],"MMM") -> Dec | F40: =IF(D40<>"","Cancelled",IF(C40<>"","Delivered","In Transit")) -> In Transit | G40: CUST024 | H40: PROD022 | I40: East | J40: 66 | K40: 2 | L40: 132 | M40: Apple Pay | N40: DHL | O40: =_xlfn.XLOOKUP(tbl_sale[[#This Row],[Customer ID]],CustomerMaster!A:A,CustomerMaster!B:B,"NA",0) -> Scarlett Murphy | P40: =_xlfn.XLOOKUP(tbl_sale[[#This Row],[Product ID]],ProductMaster!$A$2:$A$23,ProductMaster!$B$2:$B$23,"NA",0) -> Backpack | Q40: =_xlfn.XLOOKUP(tbl_sale[[#This Row],[Product ID]],ProductMaster!$A$2:$A$23,ProductMaster!$C$2:$C$23,"NA",0) -> Fashion | R40: =IFERROR(IF(tbl_sale[[#This Row],[Delivery Date]]="","Pending",IF(tbl_sale[[#This Row],[Delivery Date]]-tbl_sale[[#This Row],[Order Date]]<= 2,"Fast","Slow")),"Error") -> Pending | S40: =_xlfn.XLOOKUP(tbl_sale[[#This Row],[Region]],RegionGoals!$A$2:$A$6,RegionGoals!$B$2:$B$6, ,0) -> 50500 | T40: =_xlfn.XLOOKUP(tbl_sale[[#This Row],[Customer ID]],CustomerMaster!$A:$A,CustomerMaster!$C:$C,"NA",0) -> Business | U40: =IF(tbl_sale[[#This Row],[Delivery Status]]="Cancelled",1,0) -> 0 | V40: =IF(tbl_sale[[#This Row],[Order ID]]<>"",1,0) -> 1 | W40: =IF(AND(tbl_sale[[#This Row],[Delivery Status]]="Delivered",tbl_sale[[#This Row],[Delivery Performance]]="Fast"),1,0) -> 0 | X40: =IF(tbl_sale[[#This Row],[Delivery Status]]="Delivered",1,0) -> 0
A41: ORD0040 | B41: 45285 | E41: =TEXT(tbl_sale[[#This Row],[Order Date]],"MMM") -> Dec | F41: =IF(D41<>"","Cancelled",IF(C41<>"","Delivered","In Transit")) -> In Transit | G41: CUST006 | H41: PROD004 | I41: East | J41: 62 | K41: 4 | L41: 248 | M41: Debit Card | N41: UPS | O41: =_xlfn.XLOOKUP(tbl_sale[[#This Row],[Customer ID]],CustomerMaster!A:A,CustomerMaster!B:B,"NA",0) -> Ava Robinson | P41: =_xlfn.XLOOKUP(tbl_sale[[#This Row],[Product ID]],ProductMaster!$A$2:$A$23,ProductMaster!$B$2:$B$23,"NA",0) -> Leg Set | Q41: =_xlfn.XLOOKUP(tbl_sale[[#This Row],[Product ID]],ProductMaster!$A$2:$A$23,ProductMaster!$C$2:$C$23,"NA",0) -> Toys | R41: =IFERROR(IF(tbl_sale[[#This Row],[Delivery Date]]="","Pending",IF(tbl_sale[[#This Row],[Delivery Date]]-tbl_sale[[#This Row],[Order Date]]<= 2,"Fast","Slow")),"Error") -> Pending | S41: =_xlfn.XLOOKUP(tbl_sale[[#This Row],[Region]],RegionGoals!$A$2:$A$6,RegionGoals!$B$2:$B$6, ,0) -> 50500 | T41: =_xlfn.XLOOKUP(tbl_sale[[#This Row],[Customer ID]],CustomerMaster!$A:$A,CustomerMaster!$C:$C,"NA",0) -> Prime | U41: =IF(tbl_sale[[#This Row],[Delivery Status]]="Cancelled",1,0) -> 0 | V41: =IF(tbl_sale[[#This Row],[Order ID]]<>"",1,0) -> 1 | W41: =IF(AND(tbl_sale[[#This Row],[Delivery Status]]="Delivered",tbl_sale[[#This Row],[Delivery Performance]]="Fast"),1,0) -> 0 | X41: =IF(tbl_sale[[#This Row],[Delivery Status]]="Delivered",1,0) -> 0
A42: ORD0041 | B42: 45192 | C42: 45199 | E42: =TEXT(tbl_sale[[#This Row],[Order Date]],"MMM") -> Sep | F42: =IF(D42<>"","Cancelled",IF(C42<>"","Delivered","In Transit")) -> Delivered | G42: CUST001 | H42: PROD011 | I42: West | J42: 173 | K42: 4 | L42: 692 | M42: Apple Pay | N42: UPS | O42: =_xlfn.XLOOKUP(tbl_sale[[#This Row],[Customer ID]],CustomerMaster!A:A,CustomerMaster!B:B,"NA",0) -> James Miller | P42: =_xlfn.XLOOKUP(tbl_sale[[#This Row],[Product ID]],ProductMaster!$A$2:$A$23,ProductMaster!$B$2:$B$23,"NA",0) -> Headphones | Q42: =_xlfn.XLOOKUP(tbl_sale[[#This Row],[Product ID]],ProductMaster!$A$2:$A$23,ProductMaster!$C$2:$C$23,"NA",0) -> Electronics | R42: =IFERROR(IF(tbl_sale[[#This Row],[Delivery Date]]="","Pending",IF(tbl_sale[[#This Row],[Delivery Date]]-tbl_sale[[#This Row],[Order Date]]<= 2,"Fast","Slow")),"Error") -> Slow | S42: =_xlfn.XLOOKUP(tbl_sale[[#This Row],[Region]],RegionGoals!$A$2:$A$6,RegionGoals!$B$2:$B$6, ,0) -> 90750 | T42: =_xlfn.XLOOKUP(tbl_sale[[#This Row],[Customer ID]],CustomerMaster!$A:$A,CustomerMaster!$C:$C,"NA",0) -> Business | U42: =IF(tbl_sale[[#This Row],[Delivery Status]]="Cancelled",1,0) -> 0 | V42: =IF(tbl_sale[[#This Row],[Order ID]]<>"",1,0) -> 1 | W42: =IF(AND(tbl_sale[[#This Row],[Delivery Status]]="Delivered",tbl_sale[[#This Row],[Delivery Performance]]="Fast"),1,0) -> 0 | X42: =IF(tbl_sale[[#This Row],[Delivery Status]]="Delivered",1,0) -> 1
A43: ORD0042 | B43: 45123 | C43: 45125 | E43: =TEXT(tbl_sale[[#This Row],[Order Date]],"MMM") -> Jul | F43: =IF(D43<>"","Cancelled",IF(C43<>"","Delivered","In Transit")) -> Delivered | G43: CUST007 | H43: PROD004 | I43: West | J43: 63 | K43: 3 | L43: 189 | M43: Apple Pay | N43: UPS | O43: =_xlfn.XLOOKUP(tbl_sale[[#This Row],[Customer ID]],CustomerMaster!A:A,CustomerMaster!B:B,"NA",0) -> Liam Walker | P43: =_xlfn.XLOOKUP(tbl_sale[[#This Row],[Product ID]],ProductMaster!$A$2:$A$23,ProductMaster!$B$2:$B$23,"NA",0) -> Leg Set | Q43: =_xlfn.XLOOKUP(tbl_sale[[#This Row],[Product ID]],ProductMaster!$A$2:$A$23,ProductMaster!$C$2:$C$23,"NA",0) -> Toys | R43: =IFERROR(IF(tbl_sale[[#This Row],[Delivery Date]]="","Pending",IF(tbl_sale[[#This Row],[Delivery Date]]-tbl_sale[[#This Row],[Order Date]]<= 2,"Fast","Slow")),"Error") -> Fast | S43: =_xlfn.XLOOKUP(tbl_sale[[#This Row],[Region]],RegionGoals!$A$2:$A$6,RegionGoals!$B$2:$B$6, ,0) -> 90750 | T43: =_xlfn.XLOOKUP(tbl_sale[[#This Row],[Customer ID]],CustomerMaster!$A:$A,CustomerMaster!$C:$C,"NA",0) -> Prime | U43: =IF(tbl_sale[[#This Row],[Delivery Status]]="Cancelled",1,0) -> 0 | V43: =IF(tbl_sale[[#This Row],[Order ID]]<>"",1,0) -> 1 | W43: =IF(AND(tbl_sale[[#This Row],[Delivery Status]]="Delivered",tbl_sale[[#This Row],[Delivery Performance]]="Fast"),1,0) -> 1 | X43: =IF(tbl_sale[[#This Row],[Delivery Status]]="Delivered",1,0) -> 1
A44: ORD0043 | B44: 44962 | D44: 44968 | E44: =TEXT(tbl_sale[[#This Row],[Order Date]],"MMM") -> Feb | F44: =IF(D44<>"","Cancelled",IF(C44<>"","Delivered","In Transit")) -> Cancelled | G44: CUST040 | H44: PROD021 | I44: West | J44: 36 | K44: 3 | L44: 108 | M44: Debit Card | N44: USPS | O44: =_xlfn.XLOOKUP(tbl_sale[[#This Row],[Customer ID]],CustomerMaster!A:A,CustomerMaster!B:B,"NA",0) -> Benjamin Clark | P44: =_xlfn.XLOOKUP(tbl_sale[[#This Row],[Product ID]],ProductMaster!$A$2:$A$23,ProductMaster!$B$2:$B$23,"NA",0) -> Wall Clock | Q44: =_xlfn.XLOOKUP(tbl_sale[[#This Row],[Product ID]],ProductMaster!$A$2:$A$23,ProductMaster!$C$2:$C$23,"NA",0) -> Home | R44: =IFERROR(IF(tbl_sale[[#This Row],[Delivery Date]]="","Pending",IF(tbl_sale[[#This Row],[Delivery Date]]-tbl_sale[[#This Row],[Order Date]]<= 2,"Fast","Slow")),"Error") -> Pending | S44: =_xlfn.XLOOKUP(tbl_sale[[#This Row],[Region]],RegionGoals!$A$2:$A$6,RegionGoals!$B$2:$B$6, ,0) -> 90750 | T44: =_xlfn.XLOOKUP(tbl_sale[[#This Row],[Customer ID]],CustomerMaster!$A:$A,CustomerMaster!$C:$C,"NA",0) -> Prime | U44: =IF(tbl_sale[[#This Row],[Delivery Status]]="Cancelled",1,0) -> 1 | V44: =IF(tbl_sale[[#This Row],[Order ID]]<>"",1,0) -> 1 | W44: =IF(AND(tbl_sale[[#This Row],[Delivery Status]]="Delivered",tbl_sale[[#This Row],[Delivery Performance]]="Fast"),1,0) -> 0 | X44: =IF(tbl_sale[[#This Row],[Delivery Status]]="Delivered",1,0) -> 0
A45: ORD0044 | B45: 45278 | D45: 45283 | E45: =TEXT(tbl_sale[[#This Row],[Order Date]],"MMM") -> Dec | F45: =IF(D45<>"","Cancelled",IF(C45<>"","Delivered","In Transit")) -> Cancelled | G45: CUST006 | H45: PROD004 | I45: Central | J45: 62 | K45: 1 | L45: 62 | M45: Apple Pay | N45: Amazon Logistics | O45: =_xlfn.XLOOKUP(tbl_sale[[#This Row],[Customer ID]],CustomerMaster!A:A,CustomerMaster!B:B,"NA",0) -> Ava Robinson | P45: =_xlfn.XLOOKUP(tbl_sale[[#This Row],[Product ID]],ProductMaster!$A$2:$A$23,ProductMaster!$B$2:$B$23,"NA",0) -> Leg Set | Q45: =_xlfn.XLOOKUP(tbl_sale[[#This Row],[Product ID]],ProductMaster!$A$2:$A$23,ProductMaster!$C$2:$C$23,"NA",0) -> Toys | R45: =IFERROR(IF(tbl_sale[[#This Row],[Delivery Date]]="","Pending",IF(tbl_sale[[#This Row],[Delivery Date]]-tbl_sale[[#This Row],[Order Date]]<= 2,"Fast","Slow")),"Error") -> Pending | S45: =_xlfn.XLOOKUP(tbl_sale[[#This Row],[Region]],RegionGoals!$A$2:$A$6,RegionGoals!$B$2:$B$6, ,0) -> 97500 | T45: =_xlfn.XLOOKUP(tbl_sale[[#This Row],[Customer ID]],CustomerMaster!$A:$A,CustomerMaster!$C:$C,"NA",0) -> Prime | U45: =IF(tbl_sale[[#This Row],[Delivery Status]]="Cancelled",1,0) -> 1 | V45: =IF(tbl_sale[[#This Row],[Order ID]]<>"",1,0) -> 1 | W45: =IF(AND(tbl_sale[[#This Row],[Delivery Status]]="Delivered",tbl_sale[[#This Row],[Delivery Performance]]="Fast"),1,0) -> 0 | X45: =IF(tbl_sale[[#This Row],[Delivery Status]]="Delivered",1,0) -> 0
A46: ORD0045 | B46: 45088 | D46: 45091 | E46: =TEXT(tbl_sale[[#This Row],[Order Date]],"MMM") -> Jun | F46: =IF(D46<>"","Cancelled",IF(C46<>"","Delivered","In Transit")) -> Cancelled | G46: CUST042 | H46: PROD003 | I46: Central | J46: 137 | K46: 5 | L46: 685 | M46: Amazon Pay | N46: FedEx | O46: =_xlfn.XLOOKUP(tbl_sale[[#This Row],[Customer ID]],CustomerMaster!A:A,CustomerMaster!B:B,"NA",0) -> Noah Wilson | P46: =_xlfn.XLOOKUP(tbl_sale[[#This Row],[Product ID]],ProductMaster!$A$2:$A$23,ProductMaster!$B$2:$B$23,"NA",0) -> Cookware Set | Q46: =_xlfn.XLOOKUP(tbl_sale[[#This Row],[Product ID]],ProductMaster!$A$2:$A$23,ProductMaster!$C$2:$C$23,"NA",0) -> Home | R46: =IFERROR(IF(tbl_sale[[#This Row],[Delivery Date]]="","Pending",IF(tbl_sale[[#This Row],[Delivery Date]]-tbl_sale[[#This Row],[Order Date]]<= 2,"Fast","Slow")),"Error") -> Pending | S46: =_xlfn.XLOOKUP(tbl_sale[[#This Row],[Region]],RegionGoals!$A$2:$A$6,RegionGoals!$B$2:$B$6, ,0) -> 97500 | T46: =_xlfn.XLOOKUP(tbl_sale[[#This Row],[Customer ID]],CustomerMaster!$A:$A,CustomerMaster!$C:$C,"NA",0) -> Prime | U46: =IF(tbl_sale[[#This Row],[Delivery Status]]="Cancelled",1,0) -> 1 | V46: =IF(tbl_sale[[#This Row],[Order ID]]<>"",1,0) -> 1 | W46: =IF(AND(tbl_sale[[#This Row],[Delivery Status]]="Delivered",tbl_sale[[#This Row],[Delivery Performance]]="Fast"),1,0) -> 0 | X46: =IF(tbl_sale[[#This Row],[Delivery Status]]="Delivered",1,0) -> 0
A47: ORD0046 | B47: 45264 | C47: 45268 | E47: =TEXT(tbl_sale[[#This Row],[Order Date]],"MMM") -> Dec | F47: =IF(D47<>"","Cancelled",IF(C47<>"","Delivered","In Transit")) -> Delivered | G47: CUST039 | H47: PROD017 | I47: North | J47: 73 | K47: 4 | L47: 292 | M47: Credit Card | N47: Amazon Logistics | O47: =_xlfn.XLOOKUP(tbl_sale[[#This Row],[Customer ID]],CustomerMaster!A:A,CustomerMaster!B:B,"NA",0) -> Logan Ramirez | P47: =_xlfn.XLOOKUP(tbl_sale[[#This Row],[Product ID]],ProductMaster!$A$2:$A$23,ProductMaster!$B$2:$B$23,"NA",0) -> Gaming Mouse | Q47: =_xlfn.XLOOKUP(tbl_sale[[#This Row],[Product ID]],ProductMaster!$A$2:$A$23,ProductMaster!$C$2:$C$23,"NA",0) -> Electronics | R47: =IFERROR(IF(tbl_sale[[#This Row],[Delivery Date]]="","Pending",IF(tbl_sale[[#This Row],[Delivery Date]]-tbl_sale[[#This Row],[Order Date]]<= 2,"Fast","Slow")),"Error") -> Slow | S47: =_xlfn.XLOOKUP(tbl_sale[[#This Row],[Region]],RegionGoals!$A$2:$A$6,RegionGoals!$B$2:$B$6, ,0) -> 105000 | T47: =_xlfn.XLOOKUP(tbl_sale[[#This Row],[Customer ID]],CustomerMaster!$A:$A,CustomerMaster!$C:$C,"NA",0) -> Individual | U47: =IF(tbl_sale[[#This Row],[Delivery Status]]="Cancelled",1,0) -> 0 | V47: =IF(tbl_sale[[#This Row],[Order ID]]<>"",1,0) -> 1 | W47: =IF(AND(tbl_sale[[#This Row],[Delivery Status]]="Delivered",tbl_sale[[#This Row],[Delivery Performance]]="Fast"),1,0) -> 0 | X47: =IF(tbl_sale[[#This Row],[Delivery Status]]="Delivered",1,0) -> 1
A48: ORD0047 | B48: 45124 | C48: 45126 | E48: =TEXT(tbl_sale[[#This Row],[Order Date]],"MMM") -> Jul | F48: =IF(D48<>"","Cancelled",IF(C48<>"","Delivered","In Transit")) -> Delivered | G48: CUST041 | H48: PROD020 | I48: North | J48: 104 | K48: 1 | L48: 104 | M48: PayPal | N48: Amazon Logistics | O48: =_xlfn.XLOOKUP(tbl_sale[[#This Row],[Customer ID]],CustomerMaster!A:A,CustomerMaster!B:B,"NA",0) -> Jacob Price | P48: =_xlfn.XLOOKUP(tbl_sale[[#This Row],[Product ID]],ProductMaster!$A$2:$A$23,ProductMaster!$B$2:$B$23,"NA",0) -> Bluetooth Speaker | Q48: =_xlfn.XLOOKUP(tbl_sale[[#This Row],[Product ID]],ProductMaster!$A$2:$A$23,ProductMaster!$C$2:$C$23,"NA",0) -> Electronics | R48: =IFERROR(IF(tbl_sale[[#This Row],[Delivery Date]]="","Pending",IF(tbl_sale[[#This Row],[Delivery Date]]-tbl_sale[[#This Row],[Order Date]]<= 2,"Fast","Slow")),"Error") -> Fast | S48: =_xlfn.XLOOKUP(tbl_sale[[#This Row],[Region]],RegionGoals!$A$2:$A$6,RegionGoals!$B$2:$B$6, ,0) -> 105000 | T48: =_xlfn.XLOOKUP(tbl_sale[[#This Row],[Customer ID]],CustomerMaster!$A:$A,CustomerMaster!$C:$C,"NA",0) -> Business | U48: =IF(tbl_sale[[#This Row],[Delivery Status]]="Cancelled",1,0) -> 0 | V48: =IF(tbl_sale[[#This Row],[Order ID]]<>"",1,0) -> 1 | W48: =IF(AND(tbl_sale[[#This Row],[Delivery Status]]="Delivered",tbl_sale[[#This Row],[Delivery Performance]]="Fast"),1,0) -> 1 | X48: =IF(tbl_sale[[#This Row],[Delivery Status]]="Delivered",1,0) -> 1
A49: ORD0048 | B49: 45218 | C49: 45223 | E49: =TEXT(tbl_sale[[#This Row],[Order Date]],"MMM") -> Oct | F49: =IF(D49<>"","Cancelled",IF(C49<>"","Delivered","In Transit")) -> Delivered | G49: CUST044 | H49: PROD006 | I49: East | J49: 97 | K49: 1 | L49: 97 | M49: Amazon Pay | N49: FedEx | O49: =_xlfn.XLOOKUP(tbl_sale[[#This Row],[Customer ID]],CustomerMaster!A:A,CustomerMaster!B:B,"NA",0) -> Grace Ward | P49: =_xlfn.XLOOKUP(tbl_sale[[#This Row],[Product ID]],ProductMaster!$A$2:$A$23,ProductMaster!$B$2:$B$23,"NA",0) -> Shoes | Q49: =_xlfn.XLOOKUP(tbl_sale[[#This Row],[Product ID]],ProductMaster!$A$2:$A$23,ProductMaster!$C$2:$C$23,"NA",0) -> Fashion | R49: =IFERROR(IF(tbl_sale[[#This Row],[Delivery Date]]="","Pending",IF(tbl_sale[[#This Row],[Delivery Date]]-tbl_sale[[#This Row],[Order Date]]<= 2,"Fast","Slow")),"Error") -> Slow | S49: =_xlfn.XLOOKUP(tbl_sale[[#This Row],[Region]],RegionGoals!$A$2:$A$6,RegionGoals!$B$2:$B$6, ,0) -> 50500 | T49: =_xlfn.XLOOKUP(tbl_sale[[#This Row],[Customer ID]],CustomerMaster!$A:$A,CustomerMaster!$C:$C,"NA",0) -> Business | U49: =IF(tbl_sale[[#This Row],[Delivery Status]]="Cancelled",1,0) -> 0 | V49: =IF(tbl_sale[[#This Row],[Order ID]]<>"",1,0) -> 1 | W49: =IF(AND(tbl_sale[[#This Row],[Delivery Status]]="Delivered",tbl_sale[[#This Row],[Delivery Performance]]="Fast"),1,0) -> 0 | X49: =IF(tbl_sale[[#This Row],[Delivery Status]]="Delivered",1,0) -> 1
A50: ORD0049 | B50: 45061 | E50: =TEXT(tbl_sale[[#This Row],[Order Date]],"MMM") -> May | F50: =IF(D50<>"","Cancelled",IF(C50<>"","Delivered","In Transit")) -> In Transit | G50: CUST026 | H50: PROD017 | I50: South | J50: 73 | K50: 5 | L50: 365 | M50: Apple Pay | N50: Amazon Logistics | O50: =_xlfn.XLOOKUP(tbl_sale[[#This Row],[Customer ID]],CustomerMaster!A:A,CustomerMaster!B:B,"NA",0) -> Zoe Mitchell | P50: =_xlfn.XLOOKUP(tbl_sale[[#This Row],[Product ID]],ProductMaster!$A$2:$A$23,ProductMaster!$B$2:$B$23,"NA",0) -> Gaming Mouse | Q50: =_xlfn.XLOOKUP(tbl_sale[[#This Row],[Product ID]],ProductMaster!$A$2:$A$23,ProductMaster!$C$2:$C$23,"NA",0) -> Electronics | R50: =IFERROR(IF(tbl_sale[[#This Row],[Delivery Date]]="","Pending",IF(tbl_sale[[#This Row],[Delivery Date]]-tbl_sale[[#This Row],[Order Date]]<= 2,"Fast","Slow")),"Error") -> Pending | S50: =_xlfn.XLOOKUP(tbl_sale[[#This Row],[Region]],RegionGoals!$A$2:$A$6,RegionGoals!$B$2:$B$6, ,0) -> 91500 | T50: =_xlfn.XLOOKUP(tbl_sale[[#This Row],[Customer ID]],CustomerMaster!$A:$A,CustomerMaster!$C:$C,"NA",0) -> Individual | U50: =IF(tbl_sale[[#This Row],[Delivery Status]]="Cancelled",1,0) -> 0 | V50: =IF(tbl_sale[[#This Row],[Order ID]]<>"",1,0) -> 1 | W50: =IF(AND(tbl_sale[[#This Row],[Delivery Status]]="Delivered",tbl_sale[[#This Row],[Delivery Performance]]="Fast"),1,0) -> 0 | X50: =IF(tbl_sale[[#This Row],[Delivery Status]]="Delivered",1,0) -> 0
A51: ORD0050 | B51: 44969 | C51: 44976 | E51: =TEXT(tbl_sale[[#This Row],[Order Date]],"MMM") -> Feb | F51: =IF(D51<>"","Cancelled",IF(C51<>"","Delivered","In Transit")) -> Delivered | G51: CUST040 | H51: PROD005 | I51: East | J51: 27 | K51: 3 | L51: 81 | M51: Amazon Pay | N51: UPS | O51: =_xlfn.XLOOKUP(tbl_sale[[#This Row],[Customer ID]],CustomerMaster!A:A,CustomerMaster!B:B,"NA",0) -> Benjamin Clark | P51: =_xlfn.XLOOKUP(tbl_sale[[#This Row],[Product ID]],ProductMaster!$A$2:$A$23,ProductMaster!$B$2:$B$23,"NA",0) -> T-Shirt | Q51: =_xlfn.XLOOKUP(tbl_sale[[#This Row],[Product ID]],ProductMaster!$A$2:$A$23,ProductMaster!$C$2:$C$23,"NA",0) -> Fashion | R51: =IFERROR(IF(tbl_sale[[#This Row],[Delivery Date]]="","Pending",IF(tbl_sale[[#This Row],[Delivery Date]]-tbl_sale[[#This Row],[Order Date]]<= 2,"Fast","Slow")),"Error") -> Slow | S51: =_xlfn.XLOOKUP(tbl_sale[[#This Row],[Region]],RegionGoals!$A$2:$A$6,RegionGoals!$B$2:$B$6, ,0) -> 50500 | T51: =_xlfn.XLOOKUP(tbl_sale[[#This Row],[Customer ID]],CustomerMaster!$A:$A,CustomerMaster!$C:$C,"NA",0) -> Prime | U51: =IF(tbl_sale[[#This Row],[Delivery Status]]="Cancelled",1,0) -> 0 | V51: =IF(tbl_sale[[#This Row],[Order ID]]<>"",1,0) -> 1 | W51: =IF(AND(tbl_sale[[#This Row],[Delivery Status]]="Delivered",tbl_sale[[#This Row],[Delivery Performance]]="Fast"),1,0) -> 0 | X51: =IF(tbl_sale[[#This Row],[Delivery Status]]="Delivered",1,0) -> 1
A52: ORD0051 | B52: 45201 | E52: =TEXT(tbl_sale[[#This Row],[Order Date]],"MMM") -> Oct | F52: =IF(D52<>"","Cancelled",IF(C52<>"","Delivered","In Transit")) -> In Transit | G52: CUST041 | H52: PROD021 | I52: North | J52: 37 | K52: 1 | L52: 37 | M52: Apple Pay | N52: UPS | O52: =_xlfn.XLOOKUP(tbl_sale[[#This Row],[Customer ID]],CustomerMaster!A:A,CustomerMaster!B:B,"NA",0) -> Jacob Price | P52: =_xlfn.XLOOKUP(tbl_sale[[#This Row],[Product ID]],ProductMaster!$A$2:$A$23,ProductMaster!$B$2:$B$23,"NA",0) -> Wall Clock | Q52: =_xlfn.XLOOKUP(tbl_sale[[#This Row],[Product ID]],ProductMaster!$A$2:$A$23,ProductMaster!$C$2:$C$23,"NA",0) -> Home | R52: =IFERROR(IF(tbl_sale[[#This Row],[Delivery Date]]="","Pending",IF(tbl_sale[[#This Row],[Delivery Date]]-tbl_sale[[#This Row],[Order Date]]<= 2,"Fast","Slow")),"Error") -> Pending | S52: =_xlfn.XLOOKUP(tbl_sale[[#This Row],[Region]],RegionGoals!$A$2:$A$6,RegionGoals!$B$2:$B$6, ,0) -> 105000 | T52: =_xlfn.XLOOKUP(tbl_sale[[#This Row],[Customer ID]],CustomerMaster!$A:$A,CustomerMaster!$C:$C,"NA",0) -> Business | U52: =IF(tbl_sale[[#This Row],[Delivery Status]]="Cancelled",1,0) -> 0 | V52: =IF(tbl_sale[[#This Row],[Order ID]]<>"",1,0) -> 1 | W52: =IF(AND(tbl_sale[[#This Row],[Delivery Status]]="Delivered",tbl_sale[[#This Row],[Delivery Performance]]="Fast"),1,0) -> 0 | X52: =IF(tbl_sale[[#This Row],[Delivery Status]]="Delivered",1,0) -> 0
A53: ORD0052 | B53: 44956 | C53: 44958 | E53: =TEXT(tbl_sale[[#This Row],[Order Date]],"MMM") -> Jan | F53: =IF(D53<>"","Cancelled",IF(C53<>"","Delivered","In Transit")) -> Delivered | G53: CUST008 | H53: PROD015 | I53: North | J53: 22 | K53: 1 | L53: 22 | M53: Debit Card | N53: FedEx | O53: =_xlfn.XLOOKUP(tbl_sale[[#This Row],[Customer ID]],CustomerMaster!A:A,CustomerMaster!B:B,"NA",0) -> Harper Young | P53: =_xlfn.XLOOKUP(tbl_sale[[#This Row],[Product ID]],ProductMaster!$A$2:$A$23,ProductMaster!$B$2:$B$23,"NA",0) -> Novel | Q53: =_xlfn.XLOOKUP(tbl_sale[[#This Row],[Product ID]],ProductMaster!$A$2:$A$23,ProductMaster!$C$2:$C$23,"NA",0) -> Books | R53: =IFERROR(IF(tbl_sale[[#This Row],[Delivery Date]]="","Pending",IF(tbl_sale[[#This Row],[Delivery Date]]-tbl_sale[[#This Row],[Order Date]]<= 2,"Fast","Slow")),"Error") -> Fast | S53: =_xlfn.XLOOKUP(tbl_sale[[#This Row],[Region]],RegionGoals!$A$2:$A$6,RegionGoals!$B$2:$B$6, ,0) -> 105000 | T53: =_xlfn.XLOOKUP(tbl_sale[[#This Row],[Customer ID]],CustomerMaster!$A:$A,CustomerMaster!$C:$C,"NA",0) -> Business | U53: =IF(tbl_sale[[#This Row],[Delivery Status]]="Cancelled",1,0) -> 0 | V53: =IF(tbl_sale[[#This Row],[Order ID]]<>"",1,0) -> 1 | W53: =IF(AND(tbl_sale[[#This Row],[Delivery Status]]="Delivered",tbl_sale[[#This Row],[Delivery Performance]]="Fast"),1,0) -> 1 | X53: =IF(tbl_sale[[#This Row],[Delivery Status]]="Delivered",1,0) -> 1
A54: ORD0053 | B54: 45289 | C54: 45292 | E54: =TEXT(tbl_sale[[#This Row],[Order Date]],"MMM") -> Dec | F54: =IF(D54<>"","Cancelled",IF(C54<>"","Delivered","In Transit")) -> Delivered | G54: CUST011 | H54: PROD016 | I54: Central | J54: 218 | K54: 5 | L54: 1090 | M54: PayPal | N54: DHL | O54: =_xlfn.XLOOKUP(tbl_sale[[#This Row],[Customer ID]],CustomerMaster!A:A,CustomerMaster!B:B,"NA",0) -> Mason Hall | P54: =_xlfn.XLOOKUP(tbl_sale[[#This Row],[Product ID]],ProductMaster!$A$2:$A$23,ProductMaster!$B$2:$B$23,"NA",0) -> Cookware Set Pro | Q54: =_xlfn.XLOOKUP(tbl_sale[[#This Row],[Product ID]],ProductMaster!$A$2:$A$23,ProductMaster!$C$2:$C$23,"NA",0) -> Home | R54: =IFERROR(IF(tbl_sale[[#This Row],[Delivery Date]]="","Pending",IF(tbl_sale[[#This Row],[Delivery Date]]-tbl_sale[[#This Row],[Order Date]]<= 2,"Fast","Slow")),"Error") -> Slow | S54: =_xlfn.XLOOKUP(tbl_sale[[#This Row],[Region]],RegionGoals!$A$2:$A$6,RegionGoals!$B$2:$B$6, ,0) -> 97500 | T54: =_xlfn.XLOOKUP(tbl_sale[[#This Row],[Customer ID]],CustomerMaster!$A:$A,CustomerMaster!$C:$C,"NA",0) -> Business | U54: =IF(tbl_sale[[#This Row],[Delivery Status]]="Cancelled",1,0) -> 0 | V54: =IF(tbl_sale[[#This Row],[Order ID]]<>"",1,0) -> 1 | W54: =IF(AND(tbl_sale[[#This Row],[Delivery Status]]="Delivered",tbl_sale[[#This Row],[Delivery Performance]]="Fast"),1,0) -> 0 | X54: =IF(tbl_sale[[#This Row],[Delivery Status]]="Delivered",1,0) -> 1
A55: ORD0054 | B55: 44991 | D55: 44998 | E55: =TEXT(tbl_sale[[#This Row],[Order Date]],"MMM") -> Mar | F55: =IF(D55<>"","Cancelled",IF(C55<>"","Delivered","In Transit")) -> Cancelled | G55: CUST018 | H55: PROD004 | I55: North | J55: 64 | K55: 1 | L55: 64 | M55: Apple Pay | N55: USPS | O55: =_xlfn.XLOOKUP(tbl_sale[[#This Row],[Customer ID]],CustomerMaster!A:A,CustomerMaster!B:B,"NA",0) -> Grace Scott | P55: =_xlfn.XLOOKUP(tbl_sale[[#This Row],[Product ID]],ProductMaster!$A$2:$A$23,ProductMaster!$B$2:$B$23,"NA",0) -> Leg Set | Q55: =_xlfn.XLOOKUP(tbl_sale[[#This Row],[Product ID]],ProductMaster!$A$2:$A$23,ProductMaster!$C$2:$C$23,"NA",0) -> Toys | R55: =IFERROR(IF(tbl_sale[[#This Row],[Delivery Date]]="","Pending",IF(tbl_sale[[#This Row],[Delivery Date]]-tbl_sale[[#This Row],[Order Date]]<= 2,"Fast","Slow")),"Error") -> Pending | S55: =_xlfn.XLOOKUP(tbl_sale[[#This Row],[Region]],RegionGoals!$A$2:$A$6,RegionGoals!$B$2:$B$6, ,0) -> 105000 | T55: =_xlfn.XLOOKUP(tbl_sale[[#This Row],[Customer ID]],CustomerMaster!$A:$A,CustomerMaster!$C:$C,"NA",0) -> Individual | U55: =IF(tbl_sale[[#This Row],[Delivery Status]]="Cancelled",1,0) -> 1 | V55: =IF(tbl_sale[[#This Row],[Order ID]]<>"",1,0) -> 1 | W55: =IF(AND(tbl_sale[[#This Row],[Delivery Status]]="Delivered",tbl_sale[[#This Row],[Delivery Performance]]="Fast"),1,0) -> 0 | X55: =IF(tbl_sale[[#This Row],[Delivery Status]]="Delivered",1,0) -> 0
A56: ORD0055 | B56: 44959 | C56: 44963 | E56: =TEXT(tbl_sale[[#This Row],[Order Date]],"MMM") -> Feb | F56: =IF(D56<>"","Cancelled",IF(C56<>"","Delivered","In Transit")) -> Delivered | G56: CUST037 | H56: PROD021 | I56: Central | J56: 36 | K56: 4 | L56: 144 | M56: PayPal | N56: Amazon Logistics | O56: =_xlfn.XLOOKUP(tbl_sale[[#This Row],[Customer ID]],CustomerMaster!A:A,CustomerMaster!B:B,"NA",0) -> Emily Johnson | P56: =_xlfn.XLOOKUP(tbl_sale[[#This Row],[Product ID]],ProductMaster!$A$2:$A$23,ProductMaster!$B$2:$B$23,"NA",0) -> Wall Clock | Q56: =_xlfn.XLOOKUP(tbl_sale[[#This Row],[Product ID]],ProductMaster!$A$2:$A$23,ProductMaster!$C$2:$C$23,"NA",0) -> Home | R56: =IFERROR(IF(tbl_sale[[#This Row],[Delivery Date]]="","Pending",IF(tbl_sale[[#This Row],[Delivery Date]]-tbl_sale[[#This Row],[Order Date]]<= 2,"Fast","Slow")),"Error") -> Slow | S56: =_xlfn.XLOOKUP(tbl_sale[[#This Row],[Region]],RegionGoals!$A$2:$A$6,RegionGoals!$B$2:$B$6, ,0) -> 97500 | T56: =_xlfn.XLOOKUP(tbl_sale[[#This Row],[Customer ID]],CustomerMaster!$A:$A,CustomerMaster!$C:$C,"NA",0) -> Individual | U56: =IF(tbl_sale[[#This Row],[Delivery Status]]="Cancelled",1,0) -> 0 | V56: =IF(tbl_sale[[#This Row],[Order ID]]<>"",1,0) -> 1 | W56: =IF(AND(tbl_sale[[#This Row],[Delivery Status]]="Delivered",tbl_sale[[#This Row],[Delivery Performance]]="Fast"),1,0) -> 0 | X56: =IF(tbl_sale[[#This Row],[Delivery Status]]="Delivered",1,0) -> 1
A57: ORD0056 | B57: 45217 | C57: 45220 | E57: =TEXT(tbl_sale[[#This Row],[Order Date]],"MMM") -> Oct | F57: =IF(D57<>"","Cancelled",IF(C57<>"","Delivered","In Transit")) -> Delivered | G57: CUST017 | H57: PROD004 | I57: West | J57: 65 | K57: 1 | L57: 65 | M57: Amazon Pay | N57: FedEx | O57: =_xlfn.XLOOKUP(tbl_sale[[#This Row],[Customer ID]],CustomerMaster!A:A,CustomerMaster!B:B,"NA",0) -> Emma King | P57: =_xlfn.XLOOKUP(tbl_sale[[#This Row],[Product ID]],ProductMaster!$A$2:$A$23,ProductMaster!$B$2:$B$23,"NA",0) -> Leg Set | Q57: =_xlfn.XLOOKUP(tbl_sale[[#This Row],[Product ID]],ProductMaster!$A$2:$A$23,ProductMaster!$C$2:$C$23,"NA",0) -> Toys | R57: =IFERROR(IF(tbl_sale[[#This Row],[Delivery Date]]="","Pending",IF(tbl_sale[[#This Row],[Delivery Date]]-tbl_sale[[#This Row],[Order Date]]<= 2,"Fast","Slow")),"Error") -> Slow | S57: =_xlfn.XLOOKUP(tbl_sale[[#This Row],[Region]],RegionGoals!$A$2:$A$6,RegionGoals!$B$2:$B$6, ,0) -> 90750 | T57: =_xlfn.XLOOKUP(tbl_sale[[#This Row],[Customer ID]],CustomerMaster!$A:$A,CustomerMaster!$C:$C,"NA",0) -> Business | U57: =IF(tbl_sale[[#This Row],[Delivery Status]]="Cancelled",1,0) -> 0 | V57: =IF(tbl_sale[[#This Row],[Order ID]]<>"",1,0) -> 1 | W57: =IF(AND(tbl_sale[[#This Row],[Delivery Status]]="Delivered",tbl_sale[[#This Row],[Delivery Performance]]="Fast"),1,0) -> 0 | X57: =IF(tbl_sale[[#This Row],[Delivery Status]]="Delivered",1,0) -> 1
A58: ORD0057 | B58: 44933 | C58: 44935 | E58: =TEXT(tbl_sale[[#This Row],[Order Date]],"MMM") -> Jan | F58: =IF(D58<>"","Cancelled",IF(C58<>"","Delivered","In Transit")) -> Delivered | G58: CUST025 | H58: PROD005 | I58: Central | J58: 26 | K58: 1 | L58: 26 | M58: Apple Pay | N58: DHL | O58: =_xlfn.XLOOKUP(tbl_sale[[#This Row],[Customer ID]],CustomerMaster!A:A,CustomerMaster!B:B,"NA",0) -> Emma King | P58: =_xlfn.XLOOKUP(tbl_sale[[#This Row],[Product ID]],ProductMaster!$A$2:$A$23,ProductMaster!$B$2:$B$23,"NA",0) -> T-Shirt | Q58: =_xlfn.XLOOKUP(tbl_sale[[#This Row],[Product ID]],ProductMaster!$A$2:$A$23,ProductMaster!$C$2:$C$23,"NA",0) -> Fashion | R58: =IFERROR(IF(tbl_sale[[#This Row],[Delivery Date]]="","Pending",IF(tbl_sale[[#This Row],[Delivery Date]]-tbl_sale[[#This Row],[Order Date]]<= 2,"Fast","Slow")),"Error") -> Fast | S58: =_xlfn.XLOOKUP(tbl_sale[[#This Row],[Region]],RegionGoals!$A$2:$A$6,RegionGoals!$B$2:$B$6, ,0) -> 97500 | T58: =_xlfn.XLOOKUP(tbl_sale[[#This Row],[Customer ID]],CustomerMaster!$A:$A,CustomerMaster!$C:$C,"NA",0) -> Individual | U58: =IF(tbl_sale[[#This Row],[Delivery Status]]="Cancelled",1,0) -> 0 | V58: =IF(tbl_sale[[#This Row],[Order ID]]<>"",1,0) -> 1 | W58: =IF(AND(tbl_sale[[#This Row],[Delivery Status]]="Delivered",tbl_sale[[#This Row],[Delivery Performance]]="Fast"),1,0) -> 1 | X58: =IF(tbl_sale[[#This Row],[Delivery Status]]="Delivered",1,0) -> 1
A59: ORD0058 | B59: 45054 | E59: =TEXT(tbl_sale[[#This Row],[Order Date]],"MMM") -> May | F59: =IF(D59<>"","Cancelled",IF(C59<>"","Delivered","In Transit")) -> In Transit | G59: CUST021 | H59: PROD009 | I59: North | J59: 11 | K59: 5 | L59: 55 | M59: Credit Card | N59: FedEx | O59: =_xlfn.XLOOKUP(tbl_sale[[#This Row],[Customer ID]],CustomerMaster!A:A,CustomerMaster!B:B,"NA",0) -> Zoe Mitchell | P59: =_xlfn.XLOOKUP(tbl_sale[[#This Row],[Product ID]],ProductMaster!$A$2:$A$23,ProductMaster!$B$2:$B$23,"NA",0) -> Magazine | Q59: =_xlfn.XLOOKUP(tbl_sale[[#This Row],[Product ID]],ProductMaster!$A$2:$A$23,ProductMaster!$C$2:$C$23,"NA",0) -> Books | R59: =IFERROR(IF(tbl_sale[[#This Row],[Delivery Date]]="","Pending",IF(tbl_sale[[#This Row],[Delivery Date]]-tbl_sale[[#This Row],[Order Date]]<= 2,"Fast","Slow")),"Error") -> Pending | S59: =_xlfn.XLOOKUP(tbl_sale[[#This Row],[Region]],RegionGoals!$A$2:$A$6,RegionGoals!$B$2:$B$6, ,0) -> 105000 | T59: =_xlfn.XLOOKUP(tbl_sale[[#This Row],[Customer ID]],CustomerMaster!$A:$A,CustomerMaster!$C:$C,"NA",0) -> Individual | U59: =IF(tbl_sale[[#This Row],[Delivery Status]]="Cancelled",1,0) -> 0 | V59: =IF(tbl_sale[[#This Row],[Order ID]]<>"",1,0) -> 1 | W59: =IF(AND(tbl_sale[[#This Row],[Delivery Status]]="Delivered",tbl_sale[[#This Row],[Delivery Performance]]="Fast"),1,0) -> 0 | X59: =IF(tbl_sale[[#This Row],[Delivery Status]]="Delivered",1,0) -> 0
A60: ORD0059 | B60: 45018 | D60: 45021 | E60: =TEXT(tbl_sale[[#This Row],[Order Date]],"MMM") -> Apr | F60: =IF(D60<>"","Cancelled",IF(C60<>"","Delivered","In Transit")) -> Cancelled | G60: CUST003 | H60: PROD013 | I60: North | J60: 195 | K60: 4 | L60: 780 | M60: PayPal | N60: FedEx | O60: =_xlfn.XLOOKUP(tbl_sale[[#This Row],[Customer ID]],CustomerMaster!A:A,CustomerMaster!B:B,"NA",0) -> Ethan Davis | P60: =_xlfn.XLOOKUP(tbl_sale[[#This Row],[Product ID]],ProductMaster!$A$2:$A$23,ProductMaster!$B$2:$B$23,"NA",0) -> Vacuum Cleaner | Q60: =_xlfn.XLOOKUP(tbl_sale[[#This Row],[Product ID]],ProductMaster!$A$2:$A$23,ProductMaster!$C$2:$C$23,"NA",0) -> Home | R60: =IFERROR(IF(tbl_sale[[#This Row],[Delivery Date]]="","Pending",IF(tbl_sale[[#This Row],[Delivery Date]]-tbl_sale[[#This Row],[Order Date]]<= 2,"Fast","Slow")),"Error") -> Pending | S60: =_xlfn.XLOOKUP(tbl_sale[[#This Row],[Region]],RegionGoals!$A$2:$A$6,RegionGoals!$B$2:$B$6, ,0) -> 105000 | T60: =_xlfn.XLOOKUP(tbl_sale[[#This Row],[Customer ID]],CustomerMaster!$A:$A,CustomerMaster!$C:$C,"NA",0) -> Prime | U60: =IF(tbl_sale[[#This Row],[Delivery Status]]="Cancelled",1,0) -> 1 | V60: =IF(tbl_sale[[#This Row],[Order ID]]<>"",1,0) -> 1 | W60: =IF(AND(tbl_sale[[#This Row],[Delivery Status]]="Delivered",tbl_sale[[#This Row],[Delivery Performance]]="Fast"),1,0) -> 0 | X60: =IF(tbl_sale[[#This Row],[Delivery Status]]="Delivered",1,0) -> 0
A61: ORD0060 | B61: 45210 | D61: 45211 | E61: =TEXT(tbl_sale[[#This Row],[Order Date]],"MMM") -> Oct | F61: =IF(D61<>"","Cancelled",IF(C61<>"","Delivered","In Transit")) -> Cancelled | G61: CUST019 | H61: PROD019 | I61: West | J61: 44 | K61: 5 | L61: 220 | M61: Apple Pay | N61: USPS | O61: =_xlfn.XLOOKUP(tbl_sale[[#This Row],[Customer ID]],CustomerMaster!A:A,CustomerMaster!B:B,"NA",0) -> Ava Robinson | P61: =_xlfn.XLOOKUP(tbl_sale[[#This Row],[Product ID]],ProductMaster!$A$2:$A$23,ProductMaster!$B$2:$B$23,"NA",0) -> Formal Shirt | Q61: =_xlfn.XLOOKUP(tbl_sale[[#This Row],[Product ID]],ProductMaster!$A$2:$A$23,ProductMaster!$C$2:$C$23,"NA",0) -> Fashion | R61: =IFERROR(IF(tbl_sale[[#This Row],[Delivery Date]]="","Pending",IF(tbl_sale[[#This Row],[Delivery Date]]-tbl_sale[[#This Row],[Order Date]]<= 2,"Fast","Slow")),"Error") -> Pending | S61: =_xlfn.XLOOKUP(tbl_sale[[#This Row],[Region]],RegionGoals!$A$2:$A$6,RegionGoals!$B$2:$B$6, ,0) -> 90750 | T61: =_xlfn.XLOOKUP(tbl_sale[[#This Row],[Customer ID]],CustomerMaster!$A:$A,CustomerMaster!$C:$C,"NA",0) -> Prime | U61: =IF(tbl_sale[[#This Row],[Delivery Status]]="Cancelled",1,0) -> 1 | V61: =IF(tbl_sale[[#This Row],[Order ID]]<>"",1,0) -> 1 | W61: =IF(AND(tbl_sale[[#This Row],[Delivery Status]]="Delivered",tbl_sale[[#This Row],[Delivery Performance]]="Fast"),1,0) -> 0 | X61: =IF(tbl_sale[[#This Row],[Delivery Status]]="Delivered",1,0) -> 0
A62: ORD0061 | B62: 45179 | E62: =TEXT(tbl_sale[[#This Row],[Order Date]],"MMM") -> Sep | F62: =IF(D62<>"","Cancelled",IF(C62<>"","Delivered","In Transit")) -> In Transit | G62: CUST035 | H62: PROD008 | I62: East | J62: 69 | K62: 4 | L62: 276 | M62: Debit Card | N62: DHL | O62: =_xlfn.XLOOKUP(tbl_sale[[#This Row],[Customer ID]],CustomerMaster!A:A,CustomerMaster!B:B,"NA",0) -> Scarlett Adams | P62: =_xlfn.XLOOKUP(tbl_sale[[#This Row],[Product ID]],ProductMaster!$A$2:$A$23,ProductMaster!$B$2:$B$23,"NA",0) -> Textbook | Q62: =_xlfn.XLOOKUP(tbl_sale[[#This Row],[Product ID]],ProductMaster!$A$2:$A$23,ProductMaster!$C$2:$C$23,"NA",0) -> Books | R62: =IFERROR(IF(tbl_sale[[#This Row],[Delivery Date]]="","Pending",IF(tbl_sale[[#This Row],[Delivery Date]]-tbl_sale[[#This Row],[Order Date]]<= 2,"Fast","Slow")),"Error") -> Pending | S62: =_xlfn.XLOOKUP(tbl_sale[[#This Row],[Region]],RegionGoals!$A$2:$A$6,RegionGoals!$B$2:$B$6, ,0) -> 50500 | T62: =_xlfn.XLOOKUP(tbl_sale[[#This Row],[Customer ID]],CustomerMaster!$A:$A,CustomerMaster!$C:$C,"NA",0) -> Business | U62: =IF(tbl_sale[[#This Row],[Delivery Status]]="Cancelled",1,0) -> 0 | V62: =IF(tbl_sale[[#This Row],[Order ID]]<>"",1,0) -> 1 | W62: =IF(AND(tbl_sale[[#This Row],[Delivery Status]]="Delivered",tbl_sale[[#This Row],[Delivery Performance]]="Fast"),1,0) -> 0 | X62: =IF(tbl_sale[[#This Row],[Delivery Status]]="Delivered",1,0) -> 0
A63: ORD0062 | B63: 45252 | C63: 45259 | E63: =TEXT(tbl_sale[[#This Row],[Order Date]],"MMM") -> Nov | F63: =IF(D63<>"","Cancelled",IF(C63<>"","Delivered","In Transit")) -> Delivered | G63: CUST022 | H63: PROD001 | I63: North | J63: 815 | K63: 4 | L63: 3260 | M63: Credit Card | N63: USPS | O63: =_xlfn.XLOOKUP(tbl_sale[[#This Row],[Customer ID]],CustomerMaster!A:A,CustomerMaster!B:B,"NA",0) -> Elijah Lewis | P63: =_xlfn.XLOOKUP(tbl_sale[[#This Row],[Product ID]],ProductMaster!$A$2:$A$23,ProductMaster!$B$2:$B$23,"NA",0) -> Smartphone | Q63: =_xlfn.XLOOKUP(tbl_sale[[#This Row],[Product ID]],ProductMaster!$A$2:$A$23,ProductMaster!$C$2:$C$23,"NA",0) -> Electronics | R63: =IFERROR(IF(tbl_sale[[#This Row],[Delivery Date]]="","Pending",IF(tbl_sale[[#This Row],[Delivery Date]]-tbl_sale[[#This Row],[Order Date]]<= 2,"Fast","Slow")),"Error") -> Slow | S63: =_xlfn.XLOOKUP(tbl_sale[[#This Row],[Region]],RegionGoals!$A$2:$A$6,RegionGoals!$B$2:$B$6, ,0) -> 105000 | T63: =_xlfn.XLOOKUP(tbl_sale[[#This Row],[Customer ID]],CustomerMaster!$A:$A,CustomerMaster!$C:$C,"NA",0) -> Individual | U63: =IF(tbl_sale[[#This Row],[Delivery Status]]="Cancelled",1,0) -> 0 | V63: =IF(tbl_sale[[#This Row],[Order ID]]<>"",1,0) -> 1 | W63: =IF(AND(tbl_sale[[#This Row],[Delivery Status]]="Delivered",tbl_sale[[#This Row],[Delivery Performance]]="Fast"),1,0) -> 0 | X63: =IF(tbl_sale[[#This Row],[Delivery Status]]="Delivered",1,0) -> 1
A64: ORD0063 | B64: 45048 | E64: =TEXT(tbl_sale[[#This Row],[Order Date]],"MMM") -> May | F64: =IF(D64<>"","Cancelled",IF(C64<>"","Delivered","In Transit")) -> In Transit | G64: CUST004 | H64: PROD005 | I64: East | J64: 27 | K64: 1 | L64: 27 | M64: Debit Card | N64: Amazon Logistics | O64: =_xlfn.XLOOKUP(tbl_sale[[#This Row],[Customer ID]],CustomerMaster!A:A,CustomerMaster!B:B,"NA",0) -> Noah Wilson | P64: =_xlfn.XLOOKUP(tbl_sale[[#This Row],[Product ID]],ProductMaster!$A$2:$A$23,ProductMaster!$B$2:$B$23,"NA",0) -> T-Shirt | Q64: =_xlfn.XLOOKUP(tbl_sale[[#This Row],[Product ID]],ProductMaster!$A$2:$A$23,ProductMaster!$C$2:$C$23,"NA",0) -> Fashion | R64: =IFERROR(IF(tbl_sale[[#This Row],[Delivery Date]]="","Pending",IF(tbl_sale[[#This Row],[Delivery Date]]-tbl_sale[[#This Row],[Order Date]]<= 2,"Fast","Slow")),"Error") -> Pending | S64: =_xlfn.XLOOKUP(tbl_sale[[#This Row],[Region]],RegionGoals!$A$2:$A$6,RegionGoals!$B$2:$B$6, ,0) -> 50500 | T64: =_xlfn.XLOOKUP(tbl_sale[[#This Row],[Customer ID]],CustomerMaster!$A:$A,CustomerMaster!$C:$C,"NA",0) -> Prime | U64: =IF(tbl_sale[[#This Row],[Delivery Status]]="Cancelled",1,0) -> 0 | V64: =IF(tbl_sale[[#This Row],[Order ID]]<>"",1,0) -> 1 | W64: =IF(AND(tbl_sale[[#This Row],[Delivery Status]]="Delivered",tbl_sale[[#This Row],[Delivery Performance]]="Fast"),1,0) -> 0 | X64: =IF(tbl_sale[[#This Row],[Delivery Status]]="Delivered",1,0) -> 0
A65: ORD0064 | B65: 45285 | C65: 45289 | E65: =TEXT(tbl_sale[[#This Row],[Order Date]],"MMM") -> Dec | F65: =IF(D65<>"","Cancelled",IF(C65<>"","Delivered","In Transit")) -> Delivered | G65: CUST048 | H65: PROD003 | I65: West | J65: 139 | K65: 5 | L65: 695 | M65: Apple Pay | N65: USPS | O65: =_xlfn.XLOOKUP(tbl_sale[[#This Row],[Customer ID]],CustomerMaster!A:A,CustomerMaster!B:B,"NA",0) -> Noah Wilson | P65: =_xlfn.XLOOKUP(tbl_sale[[#This Row],[Product ID]],ProductMaster!$A$2:$A$23,ProductMaster!$B$2:$B$23,"NA",0) -> Cookware Set | Q65: =_xlfn.XLOOKUP(tbl_sale[[#This Row],[Product ID]],ProductMaster!$A$2:$A$23,ProductMaster!$C$2:$C$23,"NA",0) -> Home | R65: =IFERROR(IF(tbl_sale[[#This Row],[Delivery Date]]="","Pending",IF(tbl_sale[[#This Row],[Delivery Date]]-tbl_sale[[#This Row],[Order Date]]<= 2,"Fast","Slow")),"Error") -> Slow | S65: =_xlfn.XLOOKUP(tbl_sale[[#This Row],[Region]],RegionGoals!$A$2:$A$6,RegionGoals!$B$2:$B$6, ,0) -> 90750 | T65: =_xlfn.XLOOKUP(tbl_sale[[#This Row],[Customer ID]],CustomerMaster!$A:$A,CustomerMaster!$C:$C,"NA",0) -> Business | U65: =IF(tbl_sale[[#This Row],[Delivery Status]]="Cancelled",1,0) -> 0 | V65: =IF(tbl_sale[[#This Row],[Order ID]]<>"",1,0) -> 1 | W65: =IF(AND(tbl_sale[[#This Row],[Delivery Status]]="Delivered",tbl_sale[[#This Row],[Delivery Performance]]="Fast"),1,0) -> 0 | X65: =IF(tbl_sale[[#This Row],[Delivery Status]]="Delivered",1,0) -> 1
A66: ORD0065 | B66: 45217 | D66: 45219 | E66: =TEXT(tbl_sale[[#This Row],[Order Date]],"MMM") -> Oct | F66: =IF(D66<>"","Cancelled",IF(C66<>"","Delivered","In Transit")) -> Cancelled | G66: CUST009 | H66: PROD008 | I66: South | J66: 69 | K66: 3 | L66: 207 | M66: PayPal | N66: Amazon Logistics | O66: =_xlfn.XLOOKUP(tbl_sale[[#This Row],[Customer ID]],CustomerMaster!A:A,CustomerMaster!B:B,"NA",0) -> Jackson Allen | P66: =_xlfn.XLOOKUP(tbl_sale[[#This Row],[Product ID]],ProductMaster!$A$2:$A$23,ProductMaster!$B$2:$B$23,"NA",0) -> Textbook | Q66: =_xlfn.XLOOKUP(tbl_sale[[#This Row],[Product ID]],ProductMaster!$A$2:$A$23,ProductMaster!$C$2:$C$23,"NA",0) -> Books | R66: =IFERROR(IF(tbl_sale[[#This Row],[Delivery Date]]="","Pending",IF(tbl_sale[[#This Row],[Delivery Date]]-tbl_sale[[#This Row],[Order Date]]<= 2,"Fast","Slow")),"Error") -> Pending | S66: =_xlfn.XLOOKUP(tbl_sale[[#This Row],[Region]],RegionGoals!$A$2:$A$6,RegionGoals!$B$2:$B$6, ,0) -> 91500 | T66: =_xlfn.XLOOKUP(tbl_sale[[#This Row],[Customer ID]],CustomerMaster!$A:$A,CustomerMaster!$C:$C,"NA",0) -> Business | U66: =IF(tbl_sale[[#This Row],[Delivery Status]]="Cancelled",1,0) -> 1 | V66: =IF(tbl_sale[[#This Row],[Order ID]]<>"",1,0) -> 1 | W66: =IF(AND(tbl_sale[[#This Row],[Delivery Status]]="Delivered",tbl_sale[[#This Row],[Delivery Performance]]="Fast"),1,0) -> 0 | X66: =IF(tbl_sale[[#This Row],[Delivery Status]]="Delivered",1,0) -> 0
A67: ORD0066 | B67: 45066 | D67: 45067 | E67: =TEXT(tbl_sale[[#This Row],[Order Date]],"MMM") -> May | F67: =IF(D67<>"","Cancelled",IF(C67<>"","Delivered","In Transit")) -> Cancelled | G67: CUST009 | H67: PROD019 | I67: West | J67: 42 | K67: 1 | L67: 42 | M67: Apple Pay | N67: DHL | O67: =_xlfn.XLOOKUP(tbl_sale[[#This Row],[Customer ID]],CustomerMaster!A:A,CustomerMaster!B:B,"NA",0) -> Jackson Allen | P67: =_xlfn.XLOOKUP(tbl_sale[[#This Row],[Product ID]],ProductMaster!$A$2:$A$23,ProductMaster!$B$2:$B$23,"NA",0) -> Formal Shirt | Q67: =_xlfn.XLOOKUP(tbl_sale[[#This Row],[Product ID]],ProductMaster!$A$2:$A$23,ProductMaster!$C$2:$C$23,"NA",0) -> Fashion | R67: =IFERROR(IF(tbl_sale[[#This Row],[Delivery Date]]="","Pending",IF(tbl_sale[[#This Row],[Delivery Date]]-tbl_sale[[#This Row],[Order Date]]<= 2,"Fast","Slow")),"Error") -> Pending | S67: =_xlfn.XLOOKUP(tbl_sale[[#This Row],[Region]],RegionGoals!$A$2:$A$6,RegionGoals!$B$2:$B$6, ,0) -> 90750 | T67: =_xlfn.XLOOKUP(tbl_sale[[#This Row],[Customer ID]],CustomerMaster!$A:$A,CustomerMaster!$C:$C,"NA",0) -> Business | U67: =IF(tbl_sale[[#This Row],[Delivery Status]]="Cancelled",1,0) -> 1 | V67: =IF(tbl_sale[[#This Row],[Order ID]]<>"",1,0) -> 1 | W67: =IF(AND(tbl_sale[[#This Row],[Delivery Status]]="Delivered",tbl_sale[[#This Row],[Delivery Performance]]="Fast"),1,0) -> 0 | X67: =IF(tbl_sale[[#This Row],[Delivery Status]]="Delivered",1,0) -> 0
A68: ORD0067 | B68: 45135 | C68: 45137 | E68: =TEXT(tbl_sale[[#This Row],[Order Date]],"MMM") -> Jul | F68: =IF(D68<>"","Cancelled",IF(C68<>"","Delivered","In Transit")) -> Delivered | G68: CUST050 | H68: PROD007 | I68: North | J68: 31 | K68: 4 | L68: 124 | M68: Credit Card | N68: UPS | O68: =_xlfn.XLOOKUP(tbl_sale[[#This Row],[Customer ID]],CustomerMaster!A:A,CustomerMaster!B:B,"NA",0) -> NA | P68: =_xlfn.XLOOKUP(tbl_sale[[#This Row],[Product ID]],ProductMaster!$A$2:$A$23,ProductMaster!$B$2:$B$23,"NA",0) -> Puzzle | Q68: =_xlfn.XLOOKUP(tbl_sale[[#This Row],[Product ID]],ProductMaster!$A$2:$A$23,ProductMaster!$C$2:$C$23,"NA",0) -> Toys | R68: =IFERROR(IF(tbl_sale[[#This Row],[Delivery Date]]="","Pending",IF(tbl_sale[[#This Row],[Delivery Date]]-tbl_sale[[#This Row],[Order Date]]<= 2,"Fast","Slow")),"Error") -> Fast | S68: =_xlfn.XLOOKUP(tbl_sale[[#This Row],[Region]],RegionGoals!$A$2:$A$6,RegionGoals!$B$2:$B$6, ,0) -> 105000 | T68: =_xlfn.XLOOKUP(tbl_sale[[#This Row],[Customer ID]],CustomerMaster!$A:$A,CustomerMaster!$C:$C,"NA",0) -> NA | U68: =IF(tbl_sale[[#This Row],[Delivery Status]]="Cancelled",1,0) -> 0 | V68: =IF(tbl_sale[[#This Row],[Order ID]]<>"",1,0) -> 1 | W68: =IF(AND(tbl_sale[[#This Row],[Delivery Status]]="Delivered",tbl_sale[[#This Row],[Delivery Performance]]="Fast"),1,0) -> 1 | X68: =IF(tbl_sale[[#This Row],[Delivery Status]]="Delivered",1,0) -> 1
A69: ORD0068 | B69: 45278 | E69: =TEXT(tbl_sale[[#This Row],[Order Date]],"MMM") -> Dec | F69: =IF(D69<>"","Cancelled",IF(C69<>"","Delivered","In Transit")) -> In Transit | G69: CUST045 | H69: PROD020 | I69: West | J69: 104 | K69: 3 | L69: 312 | M69: Credit Card | N69: UPS | O69: =_xlfn.XLOOKUP(tbl_sale[[#This Row],[Customer ID]],CustomerMaster!A:A,CustomerMaster!B:B,"NA",0) -> Emily Johnson | P69: =_xlfn.XLOOKUP(tbl_sale[[#This Row],[Product ID]],ProductMaster!$A$2:$A$23,ProductMaster!$B$2:$B$23,"NA",0) -> Bluetooth Speaker | Q69: =_xlfn.XLOOKUP(tbl_sale[[#This Row],[Product ID]],ProductMaster!$A$2:$A$23,ProductMaster!$C$2:$C$23,"NA",0) -> Electronics | R69: =IFERROR(IF(tbl_sale[[#This Row],[Delivery Date]]="","Pending",IF(tbl_sale[[#This Row],[Delivery Date]]-tbl_sale[[#This Row],[Order Date]]<= 2,"Fast","Slow")),"Error") -> Pending | S69: =_xlfn.XLOOKUP(tbl_sale[[#This Row],[Region]],RegionGoals!$A$2:$A$6,RegionGoals!$B$2:$B$6, ,0) -> 90750 | T69: =_xlfn.XLOOKUP(tbl_sale[[#This Row],[Customer ID]],CustomerMaster!$A:$A,CustomerMaster!$C:$C,"NA",0) -> Individual | U69: =IF(tbl_sale[[#This Row],[Delivery Status]]="Cancelled",1,0) -> 0 | V69: =IF(tbl_sale[[#This Row],[Order ID]]<>"",1,0) -> 1 | W69: =IF(AND(tbl_sale[[#This Row],[Delivery Status]]="Delivered",tbl_sale[[#This Row],[Delivery Performance]]="Fast"),1,0) -> 0 | X69: =IF(tbl_sale[[#This Row],[Delivery Status]]="Delivered",1,0) -> 0
A70: ORD0069 | B70: 45109 | D70: 45114 | E70: =TEXT(tbl_sale[[#This Row],[Order Date]],"MMM") -> Jul | F70: =IF(D70<>"","Cancelled",IF(C70<>"","Delivered","In Transit")) -> Cancelled | G70: CUST044 | H70: PROD010 | I70: East | J70: 58 | K70: 2 | L70: 116 | M70: Apple Pay | N70: USPS | O70: =_xlfn.XLOOKUP(tbl_sale[[#This Row],[Customer ID]],CustomerMaster!A:A,CustomerMaster!B:B,"NA",0) -> Grace Ward | P70: =_xlfn.XLOOKUP(tbl_sale[[#This Row],[Product ID]],ProductMaster!$A$2:$A$23,ProductMaster!$B$2:$B$23,"NA",0) -> Jeans | Q70: =_xlfn.XLOOKUP(tbl_sale[[#This Row],[Product ID]],ProductMaster!$A$2:$A$23,ProductMaster!$C$2:$C$23,"NA",0) -> Fashion | R70: =IFERROR(IF(tbl_sale[[#This Row],[Delivery Date]]="","Pending",IF(tbl_sale[[#This Row],[Delivery Date]]-tbl_sale[[#This Row],[Order Date]]<= 2,"Fast","Slow")),"Error") -> Pending | S70: =_xlfn.XLOOKUP(tbl_sale[[#This Row],[Region]],RegionGoals!$A$2:$A$6,RegionGoals!$B$2:$B$6, ,0) -> 50500 | T70: =_xlfn.XLOOKUP(tbl_sale[[#This Row],[Customer ID]],CustomerMaster!$A:$A,CustomerMaster!$C:$C,"NA",0) -> Business | U70: =IF(tbl_sale[[#This Row],[Delivery Status]]="Cancelled",1,0) -> 1 | V70: =IF(tbl_sale[[#This Row],[Order ID]]<>"",1,0) -> 1 | W70: =IF(AND(tbl_sale[[#This Row],[Delivery Status]]="Delivered",tbl_sale[[#This Row],[Delivery Performance]]="Fast"),1,0) -> 0 | X70: =IF(tbl_sale[[#This Row],[Delivery Status]]="Delivered",1,0) -> 0
A71: ORD0070 | B71: 45208 | D71: 45209 | E71: =TEXT(tbl_sale[[#This Row],[Order Date]],"MMM") -> Oct | F71: =IF(D71<>"","Cancelled",IF(C71<>"","Delivered","In Transit")) -> Cancelled | G71: CUST009 | H71: PROD004 | I71: West | J71: 62 | K71: 2 | L71: 124 | M71: Debit Card | N71: DHL | O71: =_xlfn.XLOOKUP(tbl_sale[[#This Row],[Customer ID]],CustomerMaster!A:A,CustomerMaster!B:B,"NA",0) -> Jackson Allen | P71: =_xlfn.XLOOKUP(tbl_sale[[#This Row],[Product ID]],ProductMaster!$A$2:$A$23,ProductMaster!$B$2:$B$23,"NA",0) -> Leg Set | Q71: =_xlfn.XLOOKUP(tbl_sale[[#This Row],[Product ID]],ProductMaster!$A$2:$A$23,ProductMaster!$C$2:$C$23,"NA",0) -> Toys | R71: =IFERROR(IF(tbl_sale[[#This Row],[Delivery Date]]="","Pending",IF(tbl_sale[[#This Row],[Delivery Date]]-tbl_sale[[#This Row],[Order Date]]<= 2,"Fast","Slow")),"Error") -> Pending | S71: =_xlfn.XLOOKUP(tbl_sale[[#This Row],[Region]],RegionGoals!$A$2:$A$6,RegionGoals!$B$2:$B$6, ,0) -> 90750 | T71: =_xlfn.XLOOKUP(tbl_sale[[#This Row],[Customer ID]],CustomerMaster!$A:$A,CustomerMaster!$C:$C,"NA",0) -> Business | U71: =IF(tbl_sale[[#This Row],[Delivery Status]]="Cancelled",1,0) -> 1 | V71: =IF(tbl_sale[[#This Row],[Order ID]]<>"",1,0) -> 1 | W71: =IF(AND(tbl_sale[[#This Row],[Delivery Status]]="Delivered",tbl_sale[[#This Row],[Delivery Performance]]="Fast"),1,0) -> 0 | X71: =IF(tbl_sale[[#This Row],[Delivery Status]]="Delivered",1,0) -> 0
A72: ORD0071 | B72: 45278 | C72: 45285 | E72: =TEXT(tbl_sale[[#This Row],[Order Date]],"MMM") -> Dec | F72: =IF(D72<>"","Cancelled",IF(C72<>"","Delivered","In Transit")) -> Delivered | G72: CUST006 | H72: PROD019 | I72: East | J72: 43 | K72: 1 | L72: 43 | M72: Credit Card | N72: Amazon Logistics | O72: =_xlfn.XLOOKUP(tbl_sale[[#This Row],[Customer ID]],CustomerMaster!A:A,CustomerMaster!B:B,"NA",0) -> Ava Robinson | P72: =_xlfn.XLOOKUP(tbl_sale[[#This Row],[Product ID]],ProductMaster!$A$2:$A$23,ProductMaster!$B$2:$B$23,"NA",0) -> Formal Shirt | Q72: =_xlfn.XLOOKUP(tbl_sale[[#This Row],[Product ID]],ProductMaster!$A$2:$A$23,ProductMaster!$C$2:$C$23,"NA",0) -> Fashion | R72: =IFERROR(IF(tbl_sale[[#This Row],[Delivery Date]]="","Pending",IF(tbl_sale[[#This Row],[Delivery Date]]-tbl_sale[[#This Row],[Order Date]]<= 2,"Fast","Slow")),"Error") -> Slow | S72: =_xlfn.XLOOKUP(tbl_sale[[#This Row],[Region]],RegionGoals!$A$2:$A$6,RegionGoals!$B$2:$B$6, ,0) -> 50500 | T72: =_xlfn.XLOOKUP(tbl_sale[[#This Row],[Customer ID]],CustomerMaster!$A:$A,CustomerMaster!$C:$C,"NA",0) -> Prime | U72: =IF(tbl_sale[[#This Row],[Delivery Status]]="Cancelled",1,0) -> 0 | V72: =IF(tbl_sale[[#This Row],[Order ID]]<>"",1,0) -> 1 | W72: =IF(AND(tbl_sale[[#This Row],[Delivery Status]]="Delivered",tbl_sale[[#This Row],[Delivery Performance]]="Fast"),1,0) -> 0 | X72: =IF(tbl_sale[[#This Row],[Delivery Status]]="Delivered",1,0) -> 1
A73: ORD0072 | B73: 44992 | E73: =TEXT(tbl_sale[[#This Row],[Order Date]],"MMM") -> Mar | F73: =IF(D73<>"","Cancelled",IF(C73<>"","Delivered","In Transit")) -> In Transit | G73: CUST022 | H73: PROD004 | I73: East | J73: 62 | K73: 4 | L73: 248 | M73: Debit Card | N73: Amazon Logistics | O73: =_xlfn.XLOOKUP(tbl_sale[[#This Row],[Customer ID]],CustomerMaster!A:A,CustomerMaster!B:B,"NA",0) -> Elijah Lewis | P73: =_xlfn.XLOOKUP(tbl_sale[[#This Row],[Product ID]],ProductMaster!$A$2:$A$23,ProductMaster!$B$2:$B$23,"NA",0) -> Leg Set | Q73: =_xlfn.XLOOKUP(tbl_sale[[#This Row],[Product ID]],ProductMaster!$A$2:$A$23,ProductMaster!$C$2:$C$23,"NA",0) -> Toys | R73: =IFERROR(IF(tbl_sale[[#This Row],[Delivery Date]]="","Pending",IF(tbl_sale[[#This Row],[Delivery Date]]-tbl_sale[[#This Row],[Order Date]]<= 2,"Fast","Slow")),"Error") -> Pending | S73: =_xlfn.XLOOKUP(tbl_sale[[#This Row],[Region]],RegionGoals!$A$2:$A$6,RegionGoals!$B$2:$B$6, ,0) -> 50500 | T73: =_xlfn.XLOOKUP(tbl_sale[[#This Row],[Customer ID]],CustomerMaster!$A:$A,CustomerMaster!$C:$C,"NA",0) -> Individual | U73: =IF(tbl_sale[[#This Row],[Delivery Status]]="Cancelled",1,0) -> 0 | V73: =IF(tbl_sale[[#This Row],[Order ID]]<>"",1,0) -> 1 | W73: =IF(AND(tbl_sale[[#This Row],[Delivery Status]]="Delivered",tbl_sale[[#This Row],[Delivery Performance]]="Fast"),1,0) -> 0 | X73: =IF(tbl_sale[[#This Row],[Delivery Status]]="Delivered",1,0) -> 0
A74: ORD0073 | B74: 45129 | D74: 45132 | E74: =TEXT(tbl_sale[[#This Row],[Order Date]],"MMM") -> Jul | F74: =IF(D74<>"","Cancelled",IF(C74<>"","Delivered","In Transit")) -> Cancelled | G74: CUST028 | H74: PROD006 | I74: North | J74: 95 | K74: 2 | L74: 190 | M74: PayPal | N74: UPS | O74: =_xlfn.XLOOKUP(tbl_sale[[#This Row],[Customer ID]],CustomerMaster!A:A,CustomerMaster!B:B,"NA",0) -> Lily Bennett | P74: =_xlfn.XLOOKUP(tbl_sale[[#This Row],[Product ID]],ProductMaster!$A$2:$A$23,ProductMaster!$B$2:$B$23,"NA",0) -> Shoes | Q74: =_xlfn.XLOOKUP(tbl_sale[[#This Row],[Product ID]],ProductMaster!$A$2:$A$23,ProductMaster!$C$2:$C$23,"NA",0) -> Fashion | R74: =IFERROR(IF(tbl_sale[[#This Row],[Delivery Date]]="","Pending",IF(tbl_sale[[#This Row],[Delivery Date]]-tbl_sale[[#This Row],[Order Date]]<= 2,"Fast","Slow")),"Error") -> Pending | S74: =_xlfn.XLOOKUP(tbl_sale[[#This Row],[Region]],RegionGoals!$A$2:$A$6,RegionGoals!$B$2:$B$6, ,0) -> 105000 | T74: =_xlfn.XLOOKUP(tbl_sale[[#This Row],[Customer ID]],CustomerMaster!$A:$A,CustomerMaster!$C:$C,"NA",0) -> Business | U74: =IF(tbl_sale[[#This Row],[Delivery Status]]="Cancelled",1,0) -> 1 | V74: =IF(tbl_sale[[#This Row],[Order ID]]<>"",1,0) -> 1 | W74: =IF(AND(tbl_sale[[#This Row],[Delivery Status]]="Delivered",tbl_sale[[#This Row],[Delivery Performance]]="Fast"),1,0) -> 0 | X74: =IF(tbl_sale[[#This Row],[Delivery Status]]="Delivered",1,0) -> 0
A75: ORD0074 | B75: 44944 | C75: 44950 | E75: =TEXT(tbl_sale[[#This Row],[Order Date]],"MMM") -> Jan | F75: =IF(D75<>"","Cancelled",IF(C75<>"","Delivered","In Transit")) -> Delivered | G75: CUST016 | H75: PROD021 | I75: Central | J75: 36 | K75: 4 | L75: 144 | M75: Apple Pay | N75: FedEx | O75: =_xlfn.XLOOKUP(tbl_sale[[#This Row],[Customer ID]],CustomerMaster!A:A,CustomerMaster!B:B,"NA",0) -> Elijah Lewis | P75: =_xlfn.XLOOKUP(tbl_sale[[#This Row],[Product ID]],ProductMaster!$A$2:$A$23,ProductMaster!$B$2:$B$23,"NA",0) -> Wall Clock | Q75: =_xlfn.XLOOKUP(tbl_sale[[#This Row],[Product ID]],ProductMaster!$A$2:$A$23,ProductMaster!$C$2:$C$23,"NA",0) -> Home | R75: =IFERROR(IF(tbl_sale[[#This Row],[Delivery Date]]="","Pending",IF(tbl_sale[[#This Row],[Delivery Date]]-tbl_sale[[#This Row],[Order Date]]<= 2,"Fast","Slow")),"Error") -> Slow | S75: =_xlfn.XLOOKUP(tbl_sale[[#This Row],[Region]],RegionGoals!$A$2:$A$6,RegionGoals!$B$2:$B$6, ,0) -> 97500 | T75: =_xlfn.XLOOKUP(tbl_sale[[#This Row],[Customer ID]],CustomerMaster!$A:$A,CustomerMaster!$C:$C,"NA",0) -> Prime | U75: =IF(tbl_sale[[#This Row],[Delivery Status]]="Cancelled",1,0) -> 0 | V75: =IF(tbl_sale[[#This Row],[Order ID]]<>"",1,0) -> 1 | W75: =IF(AND(tbl_sale[[#This Row],[Delivery Status]]="Delivered",tbl_sale[[#This Row],[Delivery Performance]]="Fast"),1,0) -> 0 | X75: =IF(tbl_sale[[#This Row],[Delivery Status]]="Delivered",1,0) -> 1
A76: ORD0075 | B76: 45070 | E76: =TEXT(tbl_sale[[#This Row],[Order Date]],"MMM") -> May | F76: =IF(D76<>"","Cancelled",IF(C76<>"","Delivered","In Transit")) -> In Transit | G76: CUST042 | H76: PROD017 | I76: East | J76: 73 | K76: 5 | L76: 365 | M76: Apple Pay | N76: DHL | O76: =_xlfn.XLOOKUP(tbl_sale[[#This Row],[Customer ID]],CustomerMaster!A:A,CustomerMaster!B:B,"NA",0) -> Noah Wilson | P76: =_xlfn.XLOOKUP(tbl_sale[[#This Row],[Product ID]],ProductMaster!$A$2:$A$23,ProductMaster!$B$2:$B$23,"NA",0) -> Gaming Mouse | Q76: =_xlfn.XLOOKUP(tbl_sale[[#This Row],[Product ID]],ProductMaster!$A$2:$A$23,ProductMaster!$C$2:$C$23,"NA",0) -> Electronics | R76: =IFERROR(IF(tbl_sale[[#This Row],[Delivery Date]]="","Pending",IF(tbl_sale[[#This Row],[Delivery Date]]-tbl_sale[[#This Row],[Order Date]]<= 2,"Fast","Slow")),"Error") -> Pending | S76: =_xlfn.XLOOKUP(tbl_sale[[#This Row],[Region]],RegionGoals!$A$2:$A$6,RegionGoals!$B$2:$B$6, ,0) -> 50500 | T76: =_xlfn.XLOOKUP(tbl_sale[[#This Row],[Customer ID]],CustomerMaster!$A:$A,CustomerMaster!$C:$C,"NA",0) -> Prime | U76: =IF(tbl_sale[[#This Row],[Delivery Status]]="Cancelled",1,0) -> 0 | V76: =IF(tbl_sale[[#This Row],[Order ID]]<>"",1,0) -> 1 | W76: =IF(AND(tbl_sale[[#This Row],[Delivery Status]]="Delivered",tbl_sale[[#This Row],[Delivery Performance]]="Fast"),1,0) -> 0 | X76: =IF(tbl_sale[[#This Row],[Delivery Status]]="Delivered",1,0) -> 0
A77: ORD0076 | B77: 45172 | C77: 45178 | E77: =TEXT(tbl_sale[[#This Row],[Order Date]],"MMM") -> Sep | F77: =IF(D77<>"","Cancelled",IF(C77<>"","Delivered","In Transit")) -> Delivered | G77: CUST023 | H77: PROD019 | I77: North | J77: 43 | K77: 4 | L77: 172 | M77: Debit Card | N77: DHL | O77: =_xlfn.XLOOKUP(tbl_sale[[#This Row],[Customer ID]],CustomerMaster!A:A,CustomerMaster!B:B,"NA",0) -> Charlotte Reed | P77: =_xlfn.XLOOKUP(tbl_sale[[#This Row],[Product ID]],ProductMaster!$A$2:$A$23,ProductMaster!$B$2:$B$23,"NA",0) -> Formal Shirt | Q77: =_xlfn.XLOOKUP(tbl_sale[[#This Row],[Product ID]],ProductMaster!$A$2:$A$23,ProductMaster!$C$2:$C$23,"NA",0) -> Fashion | R77: =IFERROR(IF(tbl_sale[[#This Row],[Delivery Date]]="","Pending",IF(tbl_sale[[#This Row],[Delivery Date]]-tbl_sale[[#This Row],[Order Date]]<= 2,"Fast","Slow")),"Error") -> Slow | S77: =_xlfn.XLOOKUP(tbl_sale[[#This Row],[Region]],RegionGoals!$A$2:$A$6,RegionGoals!$B$2:$B$6, ,0) -> 105000 | T77: =_xlfn.XLOOKUP(tbl_sale[[#This Row],[Customer ID]],CustomerMaster!$A:$A,CustomerMaster!$C:$C,"NA",0) -> Individual | U77: =IF(tbl_sale[[#This Row],[Delivery Status]]="Cancelled",1,0) -> 0 | V77: =IF(tbl_sale[[#This Row],[Order ID]]<>"",1,0) -> 1 | W77: =IF(AND(tbl_sale[[#This Row],[Delivery Status]]="Delivered",tbl_sale[[#This Row],[Delivery Performance]]="Fast"),1,0) -> 0 | X77: =IF(tbl_sale[[#This Row],[Delivery Status]]="Delivered",1,0) -> 1
A78: ORD0077 | B78: 45232 | C78: 45234 | E78: =TEXT(tbl_sale[[#This Row],[Order Date]],"MMM") -> Nov | F78: =IF(D78<>"","Cancelled",IF(C78<>"","Delivered","In Transit")) -> Delivered | G78: CUST004 | H78: PROD016 | I78: West | J78: 214 | K78: 5 | L78: 1070 | M78: Debit Card | N78: UPS | O78: =_xlfn.XLOOKUP(tbl_sale[[#This Row],[Customer ID]],CustomerMaster!A:A,CustomerMaster!B:B,"NA",0) -> Noah Wilson | P78: =_xlfn.XLOOKUP(tbl_sale[[#This Row],[Product ID]],ProductMaster!$A$2:$A$23,ProductMaster!$B$2:$B$23,"NA",0) -> Cookware Set Pro | Q78: =_xlfn.XLOOKUP(tbl_sale[[#This Row],[Product ID]],ProductMaster!$A$2:$A$23,ProductMaster!$C$2:$C$23,"NA",0) -> Home | R78: =IFERROR(IF(tbl_sale[[#This Row],[Delivery Date]]="","Pending",IF(tbl_sale[[#This Row],[Delivery Date]]-tbl_sale[[#This Row],[Order Date]]<= 2,"Fast","Slow")),"Error") -> Fast | S78: =_xlfn.XLOOKUP(tbl_sale[[#This Row],[Region]],RegionGoals!$A$2:$A$6,RegionGoals!$B$2:$B$6, ,0) -> 90750 | T78: =_xlfn.XLOOKUP(tbl_sale[[#This Row],[Customer ID]],CustomerMaster!$A:$A,CustomerMaster!$C:$C,"NA",0) -> Prime | U78: =IF(tbl_sale[[#This Row],[Delivery Status]]="Cancelled",1,0) -> 0 | V78: =IF(tbl_sale[[#This Row],[Order ID]]<>"",1,0) -> 1 | W78: =IF(AND(tbl_sale[[#This Row],[Delivery Status]]="Delivered",tbl_sale[[#This Row],[Delivery Performance]]="Fast"),1,0) -> 1 | X78: =IF(tbl_sale[[#This Row],[Delivery Status]]="Delivered",1,0) -> 1
A79: ORD0078 | B79: 45263 | D79: 45266 | E79: =TEXT(tbl_sale[[#This Row],[Order Date]],"MMM") -> Dec | F79: =IF(D79<>"","Cancelled",IF(C79<>"","Delivered","In Transit")) -> Cancelled | G79: CUST048 | H79: PROD002 | I79: Central | J79: 42 | K79: 2 | L79: 84 | M79: Apple Pay | N79: UPS | O79: =_xlfn.XLOOKUP(tbl_sale[[#This Row],[Customer ID]],CustomerMaster!A:A,CustomerMaster!B:B,"NA",0) -> Noah Wilson | P79: =_xlfn.XLOOKUP(tbl_sale[[#This Row],[Product ID]],ProductMaster!$A$2:$A$23,ProductMaster!$B$2:$B$23,"NA",0) -> Action Figure | Q79: =_xlfn.XLOOKUP(tbl_sale[[#This Row],[Product ID]],ProductMaster!$A$2:$A$23,ProductMaster!$C$2:$C$23,"NA",0) -> Toys | R79: =IFERROR(IF(tbl_sale[[#This Row],[Delivery Date]]="","Pending",IF(tbl_sale[[#This Row],[Delivery Date]]-tbl_sale[[#This Row],[Order Date]]<= 2,"Fast","Slow")),"Error") -> Pending | S79: =_xlfn.XLOOKUP(tbl_sale[[#This Row],[Region]],RegionGoals!$A$2:$A$6,RegionGoals!$B$2:$B$6, ,0) -> 97500 | T79: =_xlfn.XLOOKUP(tbl_sale[[#This Row],[Customer ID]],CustomerMaster!$A:$A,CustomerMaster!$C:$C,"NA",0) -> Business | U79: =IF(tbl_sale[[#This Row],[Delivery Status]]="Cancelled",1,0) -> 1 | V79: =IF(tbl_sale[[#This Row],[Order ID]]<>"",1,0) -> 1 | W79: =IF(AND(tbl_sale[[#This Row],[Delivery Status]]="Delivered",tbl_sale[[#This Row],[Delivery Performance]]="Fast"),1,0) -> 0 | X79: =IF(tbl_sale[[#This Row],[Delivery Status]]="Delivered",1,0) -> 0
A80: ORD0079 | B80: 45017 | E80: =TEXT(tbl_sale[[#This Row],[Order Date]],"MMM") -> Apr | F80: =IF(D80<>"","Cancelled",IF(C80<>"","Delivered","In Transit")) -> In Transit | G80: CUST048 | H80: PROD012 | I80: North | J80: 46 | K80: 1 | L80: 46 | M80: Amazon Pay | N80: UPS | O80: =_xlfn.XLOOKUP(tbl_sale[[#This Row],[Customer ID]],CustomerMaster!A:A,CustomerMaster!B:B,"NA",0) -> Noah Wilson | P80: =_xlfn.XLOOKUP(tbl_sale[[#This Row],[Product ID]],ProductMaster!$A$2:$A$23,ProductMaster!$B$2:$B$23,"NA",0) -> Lamp | Q80: =_xlfn.XLOOKUP(tbl_sale[[#This Row],[Product ID]],ProductMaster!$A$2:$A$23,ProductMaster!$C$2:$C$23,"NA",0) -> Home | R80: =IFERROR(IF(tbl_sale[[#This Row],[Delivery Date]]="","Pending",IF(tbl_sale[[#This Row],[Delivery Date]]-tbl_sale[[#This Row],[Order Date]]<= 2,"Fast","Slow")),"Error") -> Pending | S80: =_xlfn.XLOOKUP(tbl_sale[[#This Row],[Region]],RegionGoals!$A$2:$A$6,RegionGoals!$B$2:$B$6, ,0) -> 105000 | T80: =_xlfn.XLOOKUP(tbl_sale[[#This Row],[Customer ID]],CustomerMaster!$A:$A,CustomerMaster!$C:$C,"NA",0) -> Business | U80: =IF(tbl_sale[[#This Row],[Delivery Status]]="Cancelled",1,0) -> 0 | V80: =IF(tbl_sale[[#This Row],[Order ID]]<>"",1,0) -> 1 | W80: =IF(AND(tbl_sale[[#This Row],[Delivery Status]]="Delivered",tbl_sale[[#This Row],[Delivery Performance]]="Fast"),1,0) -> 0 | X80: =IF(tbl_sale[[#This Row],[Delivery Status]]="Delivered",1,0) -> 0
A81: ORD0080 | B81: 45215 | C81: 45218 | E81: =TEXT(tbl_sale[[#This Row],[Order Date]],"MMM") -> Oct | F81: =IF(D81<>"","Cancelled",IF(C81<>"","Delivered","In Transit")) -> Delivered | G81: CUST032 | H81: PROD018 | I81: East | J81: 95 | K81: 4 | L81: 380 | M81: Credit Card | N81: UPS | O81: =_xlfn.XLOOKUP(tbl_sale[[#This Row],[Customer ID]],CustomerMaster!A:A,CustomerMaster!B:B,"NA",0) -> Luke Gray | P81: =_xlfn.XLOOKUP(tbl_sale[[#This Row],[Product ID]],ProductMaster!$A$2:$A$23,ProductMaster!$B$2:$B$23,"NA",0) -> Doll House | Q81: =_xlfn.XLOOKUP(tbl_sale[[#This Row],[Product ID]],ProductMaster!$A$2:$A$23,ProductMaster!$C$2:$C$23,"NA",0) -> Toys | R81: =IFERROR(IF(tbl_sale[[#This Row],[Delivery Date]]="","Pending",IF(tbl_sale[[#This Row],[Delivery Date]]-tbl_sale[[#This Row],[Order Date]]<= 2,"Fast","Slow")),"Error") -> Slow | S81: =_xlfn.XLOOKUP(tbl_sale[[#This Row],[Region]],RegionGoals!$A$2:$A$6,RegionGoals!$B$2:$B$6, ,0) -> 50500 | T81: =_xlfn.XLOOKUP(tbl_sale[[#This Row],[Customer ID]],CustomerMaster!$A:$A,CustomerMaster!$C:$C,"NA",0) -> Business | U81: =IF(tbl_sale[[#This Row],[Delivery Status]]="Cancelled",1,0) -> 0 | V81: =IF(tbl_sale[[#This Row],[Order ID]]<>"",1,0) -> 1 | W81: =IF(AND(tbl_sale[[#This Row],[Delivery Status]]="Delivered",tbl_sale[[#This Row],[Delivery Performance]]="Fast"),1,0) -> 0 | X81: =IF(tbl_sale[[#This Row],[Delivery Status]]="Delivered",1,0) -> 1
A82: ORD0081 | B82: 45235 | E82: =TEXT(tbl_sale[[#This Row],[Order Date]],"MMM") -> Nov | F82: =IF(D82<>"","Cancelled",IF(C82<>"","Delivered","In Transit")) -> In Transit | G82: CUST001 | H82: PROD011 | I82: West | J82: 174 | K82: 2 | L82: 348 | M82: PayPal | N82: UPS | O82: =_xlfn.XLOOKUP(tbl_sale[[#This Row],[Customer ID]],CustomerMaster!A:A,CustomerMaster!B:B,"NA",0) -> James Miller | P82: =_xlfn.XLOOKUP(tbl_sale[[#This Row],[Product ID]],ProductMaster!$A$2:$A$23,ProductMaster!$B$2:$B$23,"NA",0) -> Headphones | Q82: =_xlfn.XLOOKUP(tbl_sale[[#This Row],[Product ID]],ProductMaster!$A$2:$A$23,ProductMaster!$C$2:$C$23,"NA",0) -> Electronics | R82: =IFERROR(IF(tbl_sale[[#This Row],[Delivery Date]]="","Pending",IF(tbl_sale[[#This Row],[Delivery Date]]-tbl_sale[[#This Row],[Order Date]]<= 2,"Fast","Slow")),"Error") -> Pending | S82: =_xlfn.XLOOKUP(tbl_sale[[#This Row],[Region]],RegionGoals!$A$2:$A$6,RegionGoals!$B$2:$B$6, ,0) -> 90750 | T82: =_xlfn.XLOOKUP(tbl_sale[[#This Row],[Customer ID]],CustomerMaster!$A:$A,CustomerMaster!$C:$C,"NA",0) -> Business | U82: =IF(tbl_sale[[#This Row],[Delivery Status]]="Cancelled",1,0) -> 0 | V82: =IF(tbl_sale[[#This Row],[Order ID]]<>"",1,0) -> 1 | W82: =IF(AND(tbl_sale[[#This Row],[Delivery Status]]="Delivered",tbl_sale[[#This Row],[Delivery Performance]]="Fast"),1,0) -> 0 | X82: =IF(tbl_sale[[#This Row],[Delivery Status]]="Delivered",1,0) -> 0
A83: ORD0082 | B83: 45092 | D83: 45095 | E83: =TEXT(tbl_sale[[#This Row],[Order Date]],"MMM") -> Jun | F83: =IF(D83<>"","Cancelled",IF(C83<>"","Delivered","In Transit")) -> Cancelled | G83: CUST046 | H83: PROD005 | I83: North | J83: 27 | K83: 5 | L83: 135 | M83: Credit Card | N83: Amazon Logistics | O83: =_xlfn.XLOOKUP(tbl_sale[[#This Row],[Customer ID]],CustomerMaster!A:A,CustomerMaster!B:B,"NA",0) -> Emily Johnson | P83: =_xlfn.XLOOKUP(tbl_sale[[#This Row],[Product ID]],ProductMaster!$A$2:$A$23,ProductMaster!$B$2:$B$23,"NA",0) -> T-Shirt | Q83: =_xlfn.XLOOKUP(tbl_sale[[#This Row],[Product ID]],ProductMaster!$A$2:$A$23,ProductMaster!$C$2:$C$23,"NA",0) -> Fashion | R83: =IFERROR(IF(tbl_sale[[#This Row],[Delivery Date]]="","Pending",IF(tbl_sale[[#This Row],[Delivery Date]]-tbl_sale[[#This Row],[Order Date]]<= 2,"Fast","Slow")),"Error") -> Pending | S83: =_xlfn.XLOOKUP(tbl_sale[[#This Row],[Region]],RegionGoals!$A$2:$A$6,RegionGoals!$B$2:$B$6, ,0) -> 105000 | T83: =_xlfn.XLOOKUP(tbl_sale[[#This Row],[Customer ID]],CustomerMaster!$A:$A,CustomerMaster!$C:$C,"NA",0) -> Prime | U83: =IF(tbl_sale[[#This Row],[Delivery Status]]="Cancelled",1,0) -> 1 | V83: =IF(tbl_sale[[#This Row],[Order ID]]<>"",1,0) -> 1 | W83: =IF(AND(tbl_sale[[#This Row],[Delivery Status]]="Delivered",tbl_sale[[#This Row],[Delivery Performance]]="Fast"),1,0) -> 0 | X83: =IF(tbl_sale[[#This Row],[Delivery Status]]="Delivered",1,0) -> 0
A84: ORD0083 | B84: 45227 | C84: 45229 | E84: =TEXT(tbl_sale[[#This Row],[Order Date]],"MMM") -> Oct | F84: =IF(D84<>"","Cancelled",IF(C84<>"","Delivered","In Transit")) -> Delivered | G84: CUST021 | H84: PROD005 | I84: South | J84: 27 | K84: 4 | L84: 108 | M84: PayPal | N84: USPS | O84: =_xlfn.XLOOKUP(tbl_sale[[#This Row],[Customer ID]],CustomerMaster!A:A,CustomerMaster!B:B,"NA",0) -> Zoe Mitchell | P84: =_xlfn.XLOOKUP(tbl_sale[[#This Row],[Product ID]],ProductMaster!$A$2:$A$23,ProductMaster!$B$2:$B$23,"NA",0) -> T-Shirt | Q84: =_xlfn.XLOOKUP(tbl_sale[[#This Row],[Product ID]],ProductMaster!$A$2:$A$23,ProductMaster!$C$2:$C$23,"NA",0) -> Fashion | R84: =IFERROR(IF(tbl_sale[[#This Row],[Delivery Date]]="","Pending",IF(tbl_sale[[#This Row],[Delivery Date]]-tbl_sale[[#This Row],[Order Date]]<= 2,"Fast","Slow")),"Error") -> Fast | S84: =_xlfn.XLOOKUP(tbl_sale[[#This Row],[Region]],RegionGoals!$A$2:$A$6,RegionGoals!$B$2:$B$6, ,0) -> 91500 | T84: =_xlfn.XLOOKUP(tbl_sale[[#This Row],[Customer ID]],CustomerMaster!$A:$A,CustomerMaster!$C:$C,"NA",0) -> Individual | U84: =IF(tbl_sale[[#This Row],[Delivery Status]]="Cancelled",1,0) -> 0 | V84: =IF(tbl_sale[[#This Row],[Order ID]]<>"",1,0) -> 1 | W84: =IF(AND(tbl_sale[[#This Row],[Delivery Status]]="Delivered",tbl_sale[[#This Row],[Delivery Performance]]="Fast"),1,0) -> 1 | X84: =IF(tbl_sale[[#This Row],[Delivery Status]]="Delivered",1,0) -> 1
A85: ORD0084 | B85: 45282 | E85: =TEXT(tbl_sale[[#This Row],[Order Date]],"MMM") -> Dec | F85: =IF(D85<>"","Cancelled",IF(C85<>"","Delivered","In Transit")) -> In Transit | G85: CUST015 | H85: PROD022 | I85: South | J85: 65 | K85: 2 | L85: 130 | M85: PayPal | N85: DHL | O85: =_xlfn.XLOOKUP(tbl_sale[[#This Row],[Customer ID]],CustomerMaster!A:A,CustomerMaster!B:B,"NA",0) -> Ava White | P85: =_xlfn.XLOOKUP(tbl_sale[[#This Row],[Product ID]],ProductMaster!$A$2:$A$23,ProductMaster!$B$2:$B$23,"NA",0) -> Backpack | Q85: =_xlfn.XLOOKUP(tbl_sale[[#This Row],[Product ID]],ProductMaster!$A$2:$A$23,ProductMaster!$C$2:$C$23,"NA",0) -> Fashion | R85: =IFERROR(IF(tbl_sale[[#This Row],[Delivery Date]]="","Pending",IF(tbl_sale[[#This Row],[Delivery Date]]-tbl_sale[[#This Row],[Order Date]]<= 2,"Fast","Slow")),"Error") -> Pending | S85: =_xlfn.XLOOKUP(tbl_sale[[#This Row],[Region]],RegionGoals!$A$2:$A$6,RegionGoals!$B$2:$B$6, ,0) -> 91500 | T85: =_xlfn.XLOOKUP(tbl_sale[[#This Row],[Customer ID]],CustomerMaster!$A:$A,CustomerMaster!$C:$C,"NA",0) -> Individual | U85: =IF(tbl_sale[[#This Row],[Delivery Status]]="Cancelled",1,0) -> 0 | V85: =IF(tbl_sale[[#This Row],[Order ID]]<>"",1,0) -> 1 | W85: =IF(AND(tbl_sale[[#This Row],[Delivery Status]]="Delivered",tbl_sale[[#This Row],[Delivery Performance]]="Fast"),1,0) -> 0 | X85: =IF(tbl_sale[[#This Row],[Delivery Status]]="Delivered",1,0) -> 0
A86: ORD0085 | B86: 44992 | E86: =TEXT(tbl_sale[[#This Row],[Order Date]],"MMM") -> Mar | F86: =IF(D86<>"","Cancelled",IF(C86<>"","Delivered","In Transit")) -> In Transit | G86: CUST045 | H86: PROD019 | I86: East | J86: 43 | K86: 5 | L86: 215 | M86: Debit Card | N86: DHL | O86: =_xlfn.XLOOKUP(tbl_sale[[#This Row],[Customer ID]],CustomerMaster!A:A,CustomerMaster!B:B,"NA",0) -> Emily Johnson | P86: =_xlfn.XLOOKUP(tbl_sale[[#This Row],[Product ID]],ProductMaster!$A$2:$A$23,ProductMaster!$B$2:$B$23,"NA",0) -> Formal Shirt | Q86: =_xlfn.XLOOKUP(tbl_sale[[#This Row],[Product ID]],ProductMaster!$A$2:$A$23,ProductMaster!$C$2:$C$23,"NA",0) -> Fashion | R86: =IFERROR(IF(tbl_sale[[#This Row],[Delivery Date]]="","Pending",IF(tbl_sale[[#This Row],[Delivery Date]]-tbl_sale[[#This Row],[Order Date]]<= 2,"Fast","Slow")),"Error") -> Pending | S86: =_xlfn.XLOOKUP(tbl_sale[[#This Row],[Region]],RegionGoals!$A$2:$A$6,RegionGoals!$B$2:$B$6, ,0) -> 50500 | T86: =_xlfn.XLOOKUP(tbl_sale[[#This Row],[Customer ID]],CustomerMaster!$A:$A,CustomerMaster!$C:$C,"NA",0) -> Individual | U86: =IF(tbl_sale[[#This Row],[Delivery Status]]="Cancelled",1,0) -> 0 | V86: =IF(tbl_sale[[#This Row],[Order ID]]<>"",1,0) -> 1 | W86: =IF(AND(tbl_sale[[#This Row],[Delivery Status]]="Delivered",tbl_sale[[#This Row],[Delivery Performance]]="Fast"),1,0) -> 0 | X86: =IF(tbl_sale[[#This Row],[Delivery Status]]="Delivered",1,0) -> 0
A87: ORD0086 | B87: 45240 | E87: =TEXT(tbl_sale[[#This Row],[Order Date]],"MMM") -> Nov | F87: =IF(D87<>"","Cancelled",IF(C87<>"","Delivered","In Transit")) -> In Transit | G87: CUST007 | H87: PROD016 | I87: West | J87: 210 | K87: 1 | L87: 210 | M87: PayPal | N87: UPS | O87: =_xlfn.XLOOKUP(tbl_sale[[#This Row],[Customer ID]],CustomerMaster!A:A,CustomerMaster!B:B,"NA",0) -> Liam Walker | P87: =_xlfn.XLOOKUP(tbl_sale[[#This Row],[Product ID]],ProductMaster!$A$2:$A$23,ProductMaster!$B$2:$B$23,"NA",0) -> Cookware Set Pro | Q87: =_xlfn.XLOOKUP(tbl_sale[[#This Row],[Product ID]],ProductMaster!$A$2:$A$23,ProductMaster!$C$2:$C$23,"NA",0) -> Home | R87: =IFERROR(IF(tbl_sale[[#This Row],[Delivery Date]]="","Pending",IF(tbl_sale[[#This Row],[Delivery Date]]-tbl_sale[[#This Row],[Order Date]]<= 2,"Fast","Slow")),"Error") -> Pending | S87: =_xlfn.XLOOKUP(tbl_sale[[#This Row],[Region]],RegionGoals!$A$2:$A$6,RegionGoals!$B$2:$B$6, ,0) -> 90750 | T87: =_xlfn.XLOOKUP(tbl_sale[[#This Row],[Customer ID]],CustomerMaster!$A:$A,CustomerMaster!$C:$C,"NA",0) -> Prime | U87: =IF(tbl_sale[[#This Row],[Delivery Status]]="Cancelled",1,0) -> 0 | V87: =IF(tbl_sale[[#This Row],[Order ID]]<>"",1,0) -> 1 | W87: =IF(AND(tbl_sale[[#This Row],[Delivery Status]]="Delivered",tbl_sale[[#This Row],[Delivery Performance]]="Fast"),1,0) -> 0 | X87: =IF(tbl_sale[[#This Row],[Delivery Status]]="Delivered",1,0) -> 0
A88: ORD0087 | B88: 45252 | E88: =TEXT(tbl_sale[[#This Row],[Order Date]],"MMM") -> Nov | F88: =IF(D88<>"","Cancelled",IF(C88<>"","Delivered","In Transit")) -> In Transit | G88: CUST043 | H88: PROD021 | I88: South | J88: 37 | K88: 3 | L88: 111 | M88: Credit Card | N88: UPS | O88: =_xlfn.XLOOKUP(tbl_sale[[#This Row],[Customer ID]],CustomerMaster!A:A,CustomerMaster!B:B,"NA",0) -> Lily Reed | P88: =_xlfn.XLOOKUP(tbl_sale[[#This Row],[Product ID]],ProductMaster!$A$2:$A$23,ProductMaster!$B$2:$B$23,"NA",0) -> Wall Clock | Q88: =_xlfn.XLOOKUP(tbl_sale[[#This Row],[Product ID]],ProductMaster!$A$2:$A$23,ProductMaster!$C$2:$C$23,"NA",0) -> Home | R88: =IFERROR(IF(tbl_sale[[#This Row],[Delivery Date]]="","Pending",IF(tbl_sale[[#This Row],[Delivery Date]]-tbl_sale[[#This Row],[Order Date]]<= 2,"Fast","Slow")),"Error") -> Pending | S88: =_xlfn.XLOOKUP(tbl_sale[[#This Row],[Region]],RegionGoals!$A$2:$A$6,RegionGoals!$B$2:$B$6, ,0) -> 91500 | T88: =_xlfn.XLOOKUP(tbl_sale[[#This Row],[Customer ID]],CustomerMaster!$A:$A,CustomerMaster!$C:$C,"NA",0) -> Individual | U88: =IF(tbl_sale[[#This Row],[Delivery Status]]="Cancelled",1,0) -> 0 | V88: =IF(tbl_sale[[#This Row],[Order ID]]<>"",1,0) -> 1 | W88: =IF(AND(tbl_sale[[#This Row],[Delivery Status]]="Delivered",tbl_sale[[#This Row],[Delivery Performance]]="Fast"),1,0) -> 0 | X88: =IF(tbl_sale[[#This Row],[Delivery Status]]="Delivered",1,0) -> 0
A89: ORD0088 | B89: 45054 | E89: =TEXT(tbl_sale[[#This Row],[Order Date]],"MMM") -> May | F89: =IF(D89<>"","Cancelled",IF(C89<>"","Delivered","In Transit")) -> In Transit | G89: CUST007 | H89: PROD001 | I89: South | J89: 788 | K89: 4 | L89: 3152 | M89: Debit Card | N89: Amazon Logistics | O89: =_xlfn.XLOOKUP(tbl_sale[[#This Row],[Customer ID]],CustomerMaster!A:A,CustomerMaster!B:B,"NA",0) -> Liam Walker | P89: =_xlfn.XLOOKUP(tbl_sale[[#This Row],[Product ID]],ProductMaster!$A$2:$A$23,ProductMaster!$B$2:$B$23,"NA",0) -> Smartphone | Q89: =_xlfn.XLOOKUP(tbl_sale[[#This Row],[Product ID]],ProductMaster!$A$2:$A$23,ProductMaster!$C$2:$C$23,"NA",0) -> Electronics | R89: =IFERROR(IF(tbl_sale[[#This Row],[Delivery Date]]="","Pending",IF(tbl_sale[[#This Row],[Delivery Date]]-tbl_sale[[#This Row],[Order Date]]<= 2,"Fast","Slow")),"Error") -> Pending | S89: =_xlfn.XLOOKUP(tbl_sale[[#This Row],[Region]],RegionGoals!$A$2:$A$6,RegionGoals!$B$2:$B$6, ,0) -> 91500 | T89: =_xlfn.XLOOKUP(tbl_sale[[#This Row],[Customer ID]],CustomerMaster!$A:$A,CustomerMaster!$C:$C,"NA",0) -> Prime | U89: =IF(tbl_sale[[#This Row],[Delivery Status]]="Cancelled",1,0) -> 0 | V89: =IF(tbl_sale[[#This Row],[Order ID]]<>"",1,0) -> 1 | W89: =IF(AND(tbl_sale[[#This Row],[Delivery Status]]="Delivered",tbl_sale[[#This Row],[Delivery Performance]]="Fast"),1,0) -> 0 | X89: =IF(tbl_sale[[#This Row],[Delivery Status]]="Delivered",1,0) -> 0
A90: ORD0089 | B90: 45120 | E90: =TEXT(tbl_sale[[#This Row],[Order Date]],"MMM") -> Jul | F90: =IF(D90<>"","Cancelled",IF(C90<>"","Delivered","In Transit")) -> In Transit | G90: CUST007 | H90: PROD016 | I90: West | J90: 217 | K90: 5 | L90: 1085 | M90: Debit Card | N90: FedEx | O90: =_xlfn.XLOOKUP(tbl_sale[[#This Row],[Customer ID]],CustomerMaster!A:A,CustomerMaster!B:B,"NA",0) -> Liam Walker | P90: =_xlfn.XLOOKUP(tbl_sale[[#This Row],[Product ID]],ProductMaster!$A$2:$A$23,ProductMaster!$B$2:$B$23,"NA",0) -> Cookware Set Pro | Q90: =_xlfn.XLOOKUP(tbl_sale[[#This Row],[Product ID]],ProductMaster!$A$2:$A$23,ProductMaster!$C$2:$C$23,"NA",0) -> Home | R90: =IFERROR(IF(tbl_sale[[#This Row],[Delivery Date]]="","Pending",IF(tbl_sale[[#This Row],[Delivery Date]]-tbl_sale[[#This Row],[Order Date]]<= 2,"Fast","Slow")),"Error") -> Pending | S90: =_xlfn.XLOOKUP(tbl_sale[[#This Row],[Region]],RegionGoals!$A$2:$A$6,RegionGoals!$B$2:$B$6, ,0) -> 90750 | T90: =_xlfn.XLOOKUP(tbl_sale[[#This Row],[Customer ID]],CustomerMaster!$A:$A,CustomerMaster!$C:$C,"NA",0) -> Prime | U90: =IF(tbl_sale[[#This Row],[Delivery Status]]="Cancelled",1,0) -> 0 | V90: =IF(tbl_sale[[#This Row],[Order ID]]<>"",1,0) -> 1 | W90: =IF(AND(tbl_sale[[#This Row],[Delivery Status]]="Delivered",tbl_sale[[#This Row],[Delivery Performance]]="Fast"),1,0) -> 0 | X90: =IF(tbl_sale[[#This Row],[Delivery Status]]="Delivered",1,0) -> 0
A91: ORD0090 | B91: 44944 | E91: =TEXT(tbl_sale[[#This Row],[Order Date]],"MMM") -> Jan | F91: =IF(D91<>"","Cancelled",IF(C91<>"","Delivered","In Transit")) -> In Transit | G91: CUST007 | H91: PROD003 | I91: West | J91: 138 | K91: 4 | L91: 552 | M91: Credit Card | N91: FedEx | O91: =_xlfn.XLOOKUP(tbl_sale[[#This Row],[Customer ID]],CustomerMaster!A:A,CustomerMaster!B:B,"NA",0) -> Liam Walker | P91: =_xlfn.XLOOKUP(tbl_sale[[#This Row],[Product ID]],ProductMaster!$A$2:$A$23,ProductMaster!$B$2:$B$23,"NA",0) -> Cookware Set | Q91: =_xlfn.XLOOKUP(tbl_sale[[#This Row],[Product ID]],ProductMaster!$A$2:$A$23,ProductMaster!$C$2:$C$23,"NA",0) -> Home | R91: =IFERROR(IF(tbl_sale[[#This Row],[Delivery Date]]="","Pending",IF(tbl_sale[[#This Row],[Delivery Date]]-tbl_sale[[#This Row],[Order Date]]<= 2,"Fast","Slow")),"Error") -> Pending | S91: =_xlfn.XLOOKUP(tbl_sale[[#This Row],[Region]],RegionGoals!$A$2:$A$6,RegionGoals!$B$2:$B$6, ,0) -> 90750 | T91: =_xlfn.XLOOKUP(tbl_sale[[#This Row],[Customer ID]],CustomerMaster!$A:$A,CustomerMaster!$C:$C,"NA",0) -> Prime | U91: =IF(tbl_sale[[#This Row],[Delivery Status]]="Cancelled",1,0) -> 0 | V91: =IF(tbl_sale[[#This Row],[Order ID]]<>"",1,0) -> 1 | W91: =IF(AND(tbl_sale[[#This Row],[Delivery Status]]="Delivered",tbl_sale[[#This Row],[Delivery Performance]]="Fast"),1,0) -> 0 | X91: =IF(tbl_sale[[#This Row],[Delivery Status]]="Delivered",1,0) -> 0
A92: ORD0091 | B92: 45100 | C92: 45106 | E92: =TEXT(tbl_sale[[#This Row],[Order Date]],"MMM") -> Jun | F92: =IF(D92<>"","Cancelled",IF(C92<>"","Delivered","In Transit")) -> Delivered | G92: CUST031 | H92: PROD001 | I92: Central | J92: 803 | K92: 2 | L92: 1606 | M92: Apple Pay | N92: FedEx | O92: =_xlfn.XLOOKUP(tbl_sale[[#This Row],[Customer ID]],CustomerMaster!A:A,CustomerMaster!B:B,"NA",0) -> Mason Collins | P92: =_xlfn.XLOOKUP(tbl_sale[[#This Row],[Product ID]],ProductMaster!$A$2:$A$23,ProductMaster!$B$2:$B$23,"NA",0) -> Smartphone | Q92: =_xlfn.XLOOKUP(tbl_sale[[#This Row],[Product ID]],ProductMaster!$A$2:$A$23,ProductMaster!$C$2:$C$23,"NA",0) -> Electronics | R92: =IFERROR(IF(tbl_sale[[#This Row],[Delivery Date]]="","Pending",IF(tbl_sale[[#This Row],[Delivery Date]]-tbl_sale[[#This Row],[Order Date]]<= 2,"Fast","Slow")),"Error") -> Slow | S92: =_xlfn.XLOOKUP(tbl_sale[[#This Row],[Region]],RegionGoals!$A$2:$A$6,RegionGoals!$B$2:$B$6, ,0) -> 97500 | T92: =_xlfn.XLOOKUP(tbl_sale[[#This Row],[Customer ID]],CustomerMaster!$A:$A,CustomerMaster!$C:$C,"NA",0) -> Business | U92: =IF(tbl_sale[[#This Row],[Delivery Status]]="Cancelled",1,0) -> 0 | V92: =IF(tbl_sale[[#This Row],[Order ID]]<>"",1,0) -> 1 | W92: =IF(AND(tbl_sale[[#This Row],[Delivery Status]]="Delivered",tbl_sale[[#This Row],[Delivery Performance]]="Fast"),1,0) -> 0 | X92: =IF(tbl_sale[[#This Row],[Delivery Status]]="Delivered",1,0) -> 1
A93: ORD0092 | B93: 44978 | D93: 44982 | E93: =TEXT(tbl_sale[[#This Row],[Order Date]],"MMM") -> Feb | F93: =IF(D93<>"","Cancelled",IF(C93<>"","Delivered","In Transit")) -> Cancelled | G93: CUST013 | H93: PROD014 | I93: North | J93: 248 | K93: 5 | L93: 1240 | M93: PayPal | N93: UPS | O93: =_xlfn.XLOOKUP(tbl_sale[[#This Row],[Customer ID]],CustomerMaster!A:A,CustomerMaster!B:B,"NA",0) -> Olivia Martinez | P93: =_xlfn.XLOOKUP(tbl_sale[[#This Row],[Product ID]],ProductMaster!$A$2:$A$23,ProductMaster!$B$2:$B$23,"NA",0) -> Smartwatch | Q93: =_xlfn.XLOOKUP(tbl_sale[[#This Row],[Product ID]],ProductMaster!$A$2:$A$23,ProductMaster!$C$2:$C$23,"NA",0) -> Electronics | R93: =IFERROR(IF(tbl_sale[[#This Row],[Delivery Date]]="","Pending",IF(tbl_sale[[#This Row],[Delivery Date]]-tbl_sale[[#This Row],[Order Date]]<= 2,"Fast","Slow")),"Error") -> Pending | S93: =_xlfn.XLOOKUP(tbl_sale[[#This Row],[Region]],RegionGoals!$A$2:$A$6,RegionGoals!$B$2:$B$6, ,0) -> 105000 | T93: =_xlfn.XLOOKUP(tbl_sale[[#This Row],[Customer ID]],CustomerMaster!$A:$A,CustomerMaster!$C:$C,"NA",0) -> Prime | U93: =IF(tbl_sale[[#This Row],[Delivery Status]]="Cancelled",1,0) -> 1 | V93: =IF(tbl_sale[[#This Row],[Order ID]]<>"",1,0) -> 1 | W93: =IF(AND(tbl_sale[[#This Row],[Delivery Status]]="Delivered",tbl_sale[[#This Row],[Delivery Performance]]="Fast"),1,0) -> 0 | X93: =IF(tbl_sale[[#This Row],[Delivery Status]]="Delivered",1,0) -> 0
A94: ORD0093 | B94: 44976 | C94: 44978 | E94: =TEXT(tbl_sale[[#This Row],[Order Date]],"MMM") -> Feb | F94: =IF(D94<>"","Cancelled",IF(C94<>"","Delivered","In Transit")) -> Delivered | G94: CUST036 | H94: PROD016 | I94: East | J94: 210 | K94: 3 | L94: 630 | M94: Apple Pay | N94: DHL | O94: =_xlfn.XLOOKUP(tbl_sale[[#This Row],[Customer ID]],CustomerMaster!A:A,CustomerMaster!B:B,"NA",0) -> Ethan Davis | P94: =_xlfn.XLOOKUP(tbl_sale[[#This Row],[Product ID]],ProductMaster!$A$2:$A$23,ProductMaster!$B$2:$B$23,"NA",0) -> Cookware Set Pro | Q94: =_xlfn.XLOOKUP(tbl_sale[[#This Row],[Product ID]],ProductMaster!$A$2:$A$23,ProductMaster!$C$2:$C$23,"NA",0) -> Home | R94: =IFERROR(IF(tbl_sale[[#This Row],[Delivery Date]]="","Pending",IF(tbl_sale[[#This Row],[Delivery Date]]-tbl_sale[[#This Row],[Order Date]]<= 2,"Fast","Slow")),"Error") -> Fast | S94: =_xlfn.XLOOKUP(tbl_sale[[#This Row],[Region]],RegionGoals!$A$2:$A$6,RegionGoals!$B$2:$B$6, ,0) -> 50500 | T94: =_xlfn.XLOOKUP(tbl_sale[[#This Row],[Customer ID]],CustomerMaster!$A:$A,CustomerMaster!$C:$C,"NA",0) -> Business | U94: =IF(tbl_sale[[#This Row],[Delivery Status]]="Cancelled",1,0) -> 0 | V94: =IF(tbl_sale[[#This Row],[Order ID]]<>"",1,0) -> 1 | W94: =IF(AND(tbl_sale[[#This Row],[Delivery Status]]="Delivered",tbl_sale[[#This Row],[Delivery Performance]]="Fast"),1,0) -> 1 | X94: =IF(tbl_sale[[#This Row],[Delivery Status]]="Delivered",1,0) -> 1
A95: ORD0094 | B95: 45265 | D95: 45272 | E95: =TEXT(tbl_sale[[#This Row],[Order Date]],"MMM") -> Dec | F95: =IF(D95<>"","Cancelled",IF(C95<>"","Delivered","In Transit")) -> Cancelled | G95: CUST013 | H95: PROD004 | I95: North | J95: 62 | K95: 2 | L95: 124 | M95: Credit Card | N95: FedEx | O95: =_xlfn.XLOOKUP(tbl_sale[[#This Row],[Customer ID]],CustomerMaster!A:A,CustomerMaster!B:B,"NA",0) -> Olivia Martinez | P95: =_xlfn.XLOOKUP(tbl_sale[[#This Row],[Product ID]],ProductMaster!$A$2:$A$23,ProductMaster!$B$2:$B$23,"NA",0) -> Leg Set | Q95: =_xlfn.XLOOKUP(tbl_sale[[#This Row],[Product ID]],ProductMaster!$A$2:$A$23,ProductMaster!$C$2:$C$23,"NA",0) -> Toys | R95: =IFERROR(IF(tbl_sale[[#This Row],[Delivery Date]]="","Pending",IF(tbl_sale[[#This Row],[Delivery Date]]-tbl_sale[[#This Row],[Order Date]]<= 2,"Fast","Slow")),"Error") -> Pending | S95: =_xlfn.XLOOKUP(tbl_sale[[#This Row],[Region]],RegionGoals!$A$2:$A$6,RegionGoals!$B$2:$B$6, ,0) -> 105000 | T95: =_xlfn.XLOOKUP(tbl_sale[[#This Row],[Customer ID]],CustomerMaster!$A:$A,CustomerMaster!$C:$C,"NA",0) -> Prime | U95: =IF(tbl_sale[[#This Row],[Delivery Status]]="Cancelled",1,0) -> 1 | V95: =IF(tbl_sale[[#This Row],[Order ID]]<>"",1,0) -> 1 | W95: =IF(AND(tbl_sale[[#This Row],[Delivery Status]]="Delivered",tbl_sale[[#This Row],[Delivery Performance]]="Fast"),1,0) -> 0 | X95: =IF(tbl_sale[[#This Row],[Delivery Status]]="Delivered",1,0) -> 0
A96: ORD0095 | B96: 45084 | D96: 45089 | E96: =TEXT(tbl_sale[[#This Row],[Order Date]],"MMM") -> Jun | F96: =IF(D96<>"","Cancelled",IF(C96<>"","Delivered","In Transit")) -> Cancelled | G96: CUST043 | H96: PROD009 | I96: South | J96: 11 | K96: 5 | L96: 55 | M96: Debit Card | N96: Amazon Logistics | O96: =_xlfn.XLOOKUP(tbl_sale[[#This Row],[Customer ID]],CustomerMaster!A:A,CustomerMaster!B:B,"NA",0) -> Lily Reed | P96: =_xlfn.XLOOKUP(tbl_sale[[#This Row],[Product ID]],ProductMaster!$A$2:$A$23,ProductMaster!$B$2:$B$23,"NA",0) -> Magazine | Q96: =_xlfn.XLOOKUP(tbl_sale[[#This Row],[Product ID]],ProductMaster!$A$2:$A$23,ProductMaster!$C$2:$C$23,"NA",0) -> Books | R96: =IFERROR(IF(tbl_sale[[#This Row],[Delivery Date]]="","Pending",IF(tbl_sale[[#This Row],[Delivery Date]]-tbl_sale[[#This Row],[Order Date]]<= 2,"Fast","Slow")),"Error") -> Pending | S96: =_xlfn.XLOOKUP(tbl_sale[[#This Row],[Region]],RegionGoals!$A$2:$A$6,RegionGoals!$B$2:$B$6, ,0) -> 91500 | T96: =_xlfn.XLOOKUP(tbl_sale[[#This Row],[Customer ID]],CustomerMaster!$A:$A,CustomerMaster!$C:$C,"NA",0) -> Individual | U96: =IF(tbl_sale[[#This Row],[Delivery Status]]="Cancelled",1,0) -> 1 | V96: =IF(tbl_sale[[#This Row],[Order ID]]<>"",1,0) -> 1 | W96: =IF(AND(tbl_sale[[#This Row],[Delivery Status]]="Delivered",tbl_sale[[#This Row],[Delivery Performance]]="Fast"),1,0) -> 0 | X96: =IF(tbl_sale[[#This Row],[Delivery Status]]="Delivered",1,0) -> 0
A97: ORD0096 | B97: 45116 | C97: 45119 | E97: =TEXT(tbl_sale[[#This Row],[Order Date]],"MMM") -> Jul | F97: =IF(D97<>"","Cancelled",IF(C97<>"","Delivered","In Transit")) -> Delivered | G97: CUST017 | H97: PROD015 | I97: North | J97: 21 | K97: 2 | L97: 42 | M97: Amazon Pay | N97: UPS | O97: =_xlfn.XLOOKUP(tbl_sale[[#This Row],[Customer ID]],CustomerMaster!A:A,CustomerMaster!B:B,"NA",0) -> Emma King | P97: =_xlfn.XLOOKUP(tbl_sale[[#This Row],[Product ID]],ProductMaster!$A$2:$A$23,ProductMaster!$B$2:$B$23,"NA",0) -> Novel | Q97: =_xlfn.XLOOKUP(tbl_sale[[#This Row],[Product ID]],ProductMaster!$A$2:$A$23,ProductMaster!$C$2:$C$23,"NA",0) -> Books | R97: =IFERROR(IF(tbl_sale[[#This Row],[Delivery Date]]="","Pending",IF(tbl_sale[[#This Row],[Delivery Date]]-tbl_sale[[#This Row],[Order Date]]<= 2,"Fast","Slow")),"Error") -> Slow | S97: =_xlfn.XLOOKUP(tbl_sale[[#This Row],[Region]],RegionGoals!$A$2:$A$6,RegionGoals!$B$2:$B$6, ,0) -> 105000 | T97: =_xlfn.XLOOKUP(tbl_sale[[#This Row],[Customer ID]],CustomerMaster!$A:$A,CustomerMaster!$C:$C,"NA",0) -> Business | U97: =IF(tbl_sale[[#This Row],[Delivery Status]]="Cancelled",1,0) -> 0 | V97: =IF(tbl_sale[[#This Row],[Order ID]]<>"",1,0) -> 1 | W97: =IF(AND(tbl_sale[[#This Row],[Delivery Status]]="Delivered",tbl_sale[[#This Row],[Delivery Performance]]="Fast"),1,0) -> 0 | X97: =IF(tbl_sale[[#This Row],[Delivery Status]]="Delivered",1,0) -> 1
A98: ORD0097 | B98: 45283 | C98: 45286 | E98: =TEXT(tbl_sale[[#This Row],[Order Date]],"MMM") -> Dec | F98: =IF(D98<>"","Cancelled",IF(C98<>"","Delivered","In Transit")) -> Delivered | G98: CUST023 | H98: PROD018 | I98: West | J98: 95 | K98: 5 | L98: 475 | M98: Amazon Pay | N98: Amazon Logistics | O98: =_xlfn.XLOOKUP(tbl_sale[[#This Row],[Customer ID]],CustomerMaster!A:A,CustomerMaster!B:B,"NA",0) -> Charlotte Reed | P98: =_xlfn.XLOOKUP(tbl_sale[[#This Row],[Product ID]],ProductMaster!$A$2:$A$23,ProductMaster!$B$2:$B$23,"NA",0) -> Doll House | Q98: =_xlfn.XLOOKUP(tbl_sale[[#This Row],[Product ID]],ProductMaster!$A$2:$A$23,ProductMaster!$C$2:$C$23,"NA",0) -> Toys | R98: =IFERROR(IF(tbl_sale[[#This Row],[Delivery Date]]="","Pending",IF(tbl_sale[[#This Row],[Delivery Date]]-tbl_sale[[#This Row],[Order Date]]<= 2,"Fast","Slow")),"Error") -> Slow | S98: =_xlfn.XLOOKUP(tbl_sale[[#This Row],[Region]],RegionGoals!$A$2:$A$6,RegionGoals!$B$2:$B$6, ,0) -> 90750 | T98: =_xlfn.XLOOKUP(tbl_sale[[#This Row],[Customer ID]],CustomerMaster!$A:$A,CustomerMaster!$C:$C,"NA",0) -> Individual | U98: =IF(tbl_sale[[#This Row],[Delivery Status]]="Cancelled",1,0) -> 0 | V98: =IF(tbl_sale[[#This Row],[Order ID]]<>"",1,0) -> 1 | W98: =IF(AND(tbl_sale[[#This Row],[Delivery Status]]="Delivered",tbl_sale[[#This Row],[Delivery Performance]]="Fast"),1,0) -> 0 | X98: =IF(tbl_sale[[#This Row],[Delivery Status]]="Delivered",1,0) -> 1
A99: ORD0098 | B99: 45194 | C99: 45199 | E99: =TEXT(tbl_sale[[#This Row],[Order Date]],"MMM") -> Sep | F99: =IF(D99<>"","Cancelled",IF(C99<>"","Delivered","In Transit")) -> Delivered | G99: CUST044 | H99: PROD016 | I99: South | J99: 215 | K99: 2 | L99: 430 | M99: PayPal | N99: Amazon Logistics | O99: =_xlfn.XLOOKUP(tbl_sale[[#This Row],[Customer ID]],CustomerMaster!A:A,CustomerMaster!B:B,"NA",0) -> Grace Ward | P99: =_xlfn.XLOOKUP(tbl_sale[[#This Row],[Product ID]],ProductMaster!$A$2:$A$23,ProductMaster!$B$2:$B$23,"NA",0) -> Cookware Set Pro | Q99: =_xlfn.XLOOKUP(tbl_sale[[#This Row],[Product ID]],ProductMaster!$A$2:$A$23,ProductMaster!$C$2:$C$23,"NA",0) -> Home | R99: =IFERROR(IF(tbl_sale[[#This Row],[Delivery Date]]="","Pending",IF(tbl_sale[[#This Row],[Delivery Date]]-tbl_sale[[#This Row],[Order Date]]<= 2,"Fast","Slow")),"Error") -> Slow | S99: =_xlfn.XLOOKUP(tbl_sale[[#This Row],[Region]],RegionGoals!$A$2:$A$6,RegionGoals!$B$2:$B$6, ,0) -> 91500 | T99: =_xlfn.XLOOKUP(tbl_sale[[#This Row],[Customer ID]],CustomerMaster!$A:$A,CustomerMaster!$C:$C,"NA",0) -> Business | U99: =IF(tbl_sale[[#This Row],[Delivery Status]]="Cancelled",1,0) -> 0 | V99: =IF(tbl_sale[[#This Row],[Order ID]]<>"",1,0) -> 1 | W99: =IF(AND(tbl_sale[[#This Row],[Delivery Status]]="Delivered",tbl_sale[[#This Row],[Delivery Performance]]="Fast"),1,0) -> 0 | X99: =IF(tbl_sale[[#This Row],[Delivery Status]]="Delivered",1,0) -> 1
A100: ORD0099 | B100: 44944 | D100: 44950 | E100: =TEXT(tbl_sale[[#This Row],[Order Date]],"MMM") -> Jan | F100: =IF(D100<>"","Cancelled",IF(C100<>"","Delivered","In Transit")) -> Cancelled | G100: CUST034 | H100: PROD019 | I100: West | J100: 43 | K100: 5 | L100: 215 | M100: Credit Card | N100: UPS | O100: =_xlfn.XLOOKUP(tbl_sale[[#This Row],[Customer ID]],CustomerMaster!A:A,CustomerMaster!B:B,"NA",0) -> Lily Simmons | P100: =_xlfn.XLOOKUP(tbl_sale[[#This Row],[Product ID]],ProductMaster!$A$2:$A$23,ProductMaster!$B$2:$B$23,"NA",0) -> Formal Shirt | Q100: =_xlfn.XLOOKUP(tbl_sale[[#This Row],[Product ID]],ProductMaster!$A$2:$A$23,ProductMaster!$C$2:$C$23,"NA",0) -> Fashion | R100: =IFERROR(IF(tbl_sale[[#This Row],[Delivery Date]]="","Pending",IF(tbl_sale[[#This Row],[Delivery Date]]-tbl_sale[[#This Row],[Order Date]]<= 2,"Fast","Slow")),"Error") -> Pending | S100: =_xlfn.XLOOKUP(tbl_sale[[#This Row],[Region]],RegionGoals!$A$2:$A$6,RegionGoals!$B$2:$B$6, ,0) -> 90750 | T100: =_xlfn.XLOOKUP(tbl_sale[[#This Row],[Customer ID]],CustomerMaster!$A:$A,CustomerMaster!$C:$C,"NA",0) -> Individual | U100: =IF(tbl_sale[[#This Row],[Delivery Status]]="Cancelled",1,0) -> 1 | V100: =IF(tbl_sale[[#This Row],[Order ID]]<>"",1,0) -> 1 | W100: =IF(AND(tbl_sale[[#This Row],[Delivery Status]]="Delivered",tbl_sale[[#This Row],[Delivery Performance]]="Fast"),1,0) -> 0 | X100: =IF(tbl_sale[[#This Row],[Delivery Status]]="Delivered",1,0) -> 0
...

Sheet ProductMaster
A1: Product ID | B1: Product Name | C1: Category | D1: Cost Price | E1: Description
A2: PROD001 | B2: Smartphone | C2: Electronics | D2: 749 | E2: Latest model with 5G, dual SIM, and OLED display
A3: PROD002 | B3: Action Figure | C3: Toys | D3: 39 | E3: Collectible superhero action figure for ages 8+
A4: PROD003 | B4: Cookware Set | C4: Home | D4: 129 | E4: Non-stick 5-piece cookware set for daily use
A5: PROD004 | B5: Leg Set | C5: Toys | D5: 59 | E5: 300-piece creative building block toy set
A6: PROD005 | B6: T-Shirt | C6: Fashion | D6: 25 | E6: Cotton t-shirt, available in multiple colors
A7: PROD006 | B7: Shoes | C7: Fashion | D7: 89 | E7: Casual wear shoes for men and women
A8: PROD007 | B8: Puzzle | C8: Toys | D8: 29 | E8: 1000-piece jigsaw puzzle
A9: PROD008 | B9: Textbook | C9: Books | D9: 65 | E9: University-level textbook on computer science
A10: PROD009 | B10: Magazine | C10: Books | D10: 10 | E10: Monthly lifestyle magazine
A11: PROD010 | B11: Jeans | C11: Fashion | D11: 55 | E11: Slim fit denim jeans with stretch
A12: PROD011 | B12: Headphones | C12: Electronics | D12: 159 | E12: Wireless noise-cancelling over-ear headphones
A13: PROD012 | B13: Lamp | C13: Home | D13: 42 | E13: LED desk lamp with dimmable light
... A23: PROD022 | B23: Backpack | C23: Fashion | D23: 60 | E23: Waterproof backpack with laptop compartment

Sheet RegionGoals
A1: Region | B1: Sales Target
A2: Central | B2: 97500
A3: East | B3: 50500
A4: North | B4: 105000
A5: South | B5: 91500
A6: West | B6: 90750

Sheet CustomerMaster
A1: Customer ID | B1: Customer Name | C1: Customer Type | D1: City | E1: State
A2: CUST001 | B2: James Miller | C2: Business | D2: New York | E2: New York
A3: CUST002 | B3: Emily Johnson | C3: Prime | D3: Seattle | E3: Washington
A4: CUST003 | B4: Ethan Davis | C4: Prime | D4: Austin | E4: Texas
A5: CUST004 | B5: Noah Wilson | C5: Prime | D5: San Francisco | E5: California
A6: CUST005 | B6: Olivia Martinez | C6: Prime | D6: Seattle | E6: Washington
A7: CUST006 | B7: Ava Robinson | C7: Prime | D7: Chicago | E7: Illinois
A8: CUST007 | B8: Liam Walker | C8: Prime | D8: San Francisco | E8: California
A9: CUST008 | B9: Harper Young | C9: Business | D9: Dallas | E9: Texas
A10: CUST009 | B10: Jackson Allen | C10: Business | D10: Seattle | E10: Washington
A11: CUST010 | B11: Charlotte Harris | C11: Prime | D11: Chicago | E11: Illinois
A12: CUST011 | B12: Mason Hall | C12: Business | D12: Miami | E12: Florida
... A50: CUST049 | B50: Hazel Gray | C50: Business | D50: Chicago | E50: Illinois
